Workbook
Name AFFILIATION_SYNDICALE_DECEMBRE_2015: #REF!
Name Day_One: #REF!
Name FACTURE: #REF!
Name SYNDICAT: #REF!
Name SYNDICATII: #REF!
Name VAR: #REF!

Sheet Params
A2: Taux du jour | B2: 2308
A3: Mois du rapport | B3: 46234

Sheet BASE
A1: Emp Number | B1: Names | C1: Gender | D1: Nationality | E1: Position | F1: Grade | G1: Birth | H1: Age | I1: AGE_CAT | J1: Empl_Date | K1: Length of Service | L1: Length of Service_CAT | M1: Departments | N1: Location_Site | O1: Leave_Balance | P1: Leave Allowance_Amount | Q1: OVT_Hours | R1: OVT_Cost
A2: 70000002 | B2: Gaël Mbodi | C2: Male | D2: Congo | E2: Site Manager | F2: D2 | G2: 31575 | H2: =DATEDIF(G2,Params!$B$3,"Y") -> 40 | I2: =IF(H2<25,"<25 ans",IF(H2<=29,"25 - 29 ans",IF(H2<=34,"30 - 34 ans ",IF(H2<=39,"35 - 39 ans ",IF(H2<=44,"40 - 44 ans ",IF(H2<=49,"45 - 49 ans ",IF(H2<=54,"50 - 54 ans ",">55"))))))) -> 40 - 44 ans | J2: 41852 | K2: =DATEDIF(J2,Params!$B$3,"Y") -> 11 | L2: =IF(K2<1,"<1 year",IF(K2<=3,"1 - 3 year(s)",IF(K2<=6,"4 - 6 years",IF(K2<=9,"7 - 9 years",">= 10 years")))) -> >= 10 years | M2: Production | N2: Lubudi | O2: {=IFERROR(VLOOKUP($A2&"Annual",CHOOSE({1,2},leavebalances_base!$E$3:$E$1230&leavebalances_base!$T$3:$T$1230,leavebalances_base!$AC$3:$AC$1230),2,FALSE),"")} -> 23.89 | P2: {=IFERROR(VLOOKUP($A2&"Annual",CHOOSE({1,2},leavebalances_base!$E$3:$E$1230&leavebalances_base!$T$3:$T$1230,leavebalances_base!$AD$3:$AD$1230),2,FALSE)/Params!$B$2,"")} -> 4404.548 | Q2: =IFERROR(VLOOKUP(A2,overtime_base!$J:$L,2,FALSE),0) -> 0 | R2: =IFERROR(VLOOKUP(A2,overtime_base!$J:$L,3,FALSE)/Params!$B$2,0) -> 0
A3: 70000008 | B3: Serge Muakasa | C3: Male | D3: Congo | E3: Estate Officer | F3: C4 | G3: 28524 | H3: =DATEDIF(G3,Params!$B$3,"Y") -> 48 | I3: =IF(H3<25,"<25 ans",IF(H3<=29,"25 - 29 ans",IF(H3<=34,"30 - 34 ans ",IF(H3<=39,"35 - 39 ans ",IF(H3<=44,"40 - 44 ans ",IF(H3<=49,"45 - 49 ans ",IF(H3<=54,"50 - 54 ans ",">55"))))))) -> 45 - 49 ans | J3: 42099 | K3: =DATEDIF(J3,Params!$B$3,"Y") -> 11 | L3: =IF(K3<1,"<1 year",IF(K3<=3,"1 - 3 year(s)",IF(K3<=6,"4 - 6 years",IF(K3<=9,"7 - 9 years",">= 10 years")))) -> >= 10 years | M3: HR | N3: Plant | O3: {=IFERROR(VLOOKUP($A3&"Annual",CHOOSE({1,2},leavebalances_base!$E$3:$E$1230&leavebalances_base!$T$3:$T$1230,leavebalances_base!$AC$3:$AC$1230),2,FALSE),"")} -> 18.903333 | P3: {=IFERROR(VLOOKUP($A3&"Annual",CHOOSE({1,2},leavebalances_base!$E$3:$E$1230&leavebalances_base!$T$3:$T$1230,leavebalances_base!$AD$3:$AD$1230),2,FALSE)/Params!$B$2,"")} -> 2724.8657 | Q3: =IFERROR(VLOOKUP(A3,overtime_base!$J:$L,2,FALSE),0) -> 0 | R3: =IFERROR(VLOOKUP(A3,overtime_base!$J:$L,3,FALSE)/Params!$B$2,0) -> 0
A4: 70000009 | B4: Jean Jacques Zodulua | C4: Male | D4: Congo | E4: Driver | F4: B2 | G4: 25429 | H4: =DATEDIF(G4,Params!$B$3,"Y") -> 56 | I4: =IF(H4<25,"<25 ans",IF(H4<=29,"25 - 29 ans",IF(H4<=34,"30 - 34 ans ",IF(H4<=39,"35 - 39 ans ",IF(H4<=44,"40 - 44 ans ",IF(H4<=49,"45 - 49 ans ",IF(H4<=54,"50 - 54 ans ",">55"))))))) -> >55 | J4: 42135 | K4: =DATEDIF(J4,Params!$B$3,"Y") -> 11 | L4: =IF(K4<1,"<1 year",IF(K4<=3,"1 - 3 year(s)",IF(K4<=6,"4 - 6 years",IF(K4<=9,"7 - 9 years",">= 10 years")))) -> >= 10 years | M4: HR | N4: Kinshasa_Regions | O4: {=IFERROR(VLOOKUP($A4&"Annual",CHOOSE({1,2},leavebalances_base!$E$3:$E$1230&leavebalances_base!$T$3:$T$1230,leavebalances_base!$AC$3:$AC$1230),2,FALSE),"")} -> 27.833333 | P4: {=IFERROR(VLOOKUP($A4&"Annual",CHOOSE({1,2},leavebalances_base!$E$3:$E$1230&leavebalances_base!$T$3:$T$1230,leavebalances_base!$AD$3:$AD$1230),2,FALSE)/Params!$B$2,"")} -> 868.75904 | Q4: =IFERROR(VLOOKUP(A4,overtime_base!$J:$L,2,FALSE),0) -> 0 | R4: =IFERROR(VLOOKUP(A4,overtime_base!$J:$L,3,FALSE)/Params!$B$2,0) -> 0
A5: 70000011 | B5: Kimbanzi Feinta | C5: Male | D5: Congo | E5: Senior Sales Consultant | F5: C4 | G5: 25330 | H5: =DATEDIF(G5,Params!$B$3,"Y") -> 57 | I5: =IF(H5<25,"<25 ans",IF(H5<=29,"25 - 29 ans",IF(H5<=34,"30 - 34 ans ",IF(H5<=39,"35 - 39 ans ",IF(H5<=44,"40 - 44 ans ",IF(H5<=49,"45 - 49 ans ",IF(H5<=54,"50 - 54 ans ",">55"))))))) -> >55 | J5: 42240 | K5: =DATEDIF(J5,Params!$B$3,"Y") -> 10 | L5: =IF(K5<1,"<1 year",IF(K5<=3,"1 - 3 year(s)",IF(K5<=6,"4 - 6 years",IF(K5<=9,"7 - 9 years",">= 10 years")))) -> >= 10 years | M5: Sales_CEC | N5: Kinshasa_Regions | O5: {=IFERROR(VLOOKUP($A5&"Annual",CHOOSE({1,2},leavebalances_base!$E$3:$E$1230&leavebalances_base!$T$3:$T$1230,leavebalances_base!$AC$3:$AC$1230),2,FALSE),"")} -> 29.416667 | P5: {=IFERROR(VLOOKUP($A5&"Annual",CHOOSE({1,2},leavebalances_base!$E$3:$E$1230&leavebalances_base!$T$3:$T$1230,leavebalances_base!$AD$3:$AD$1230),2,FALSE)/Params!$B$2,"")} -> 2939.8699 | Q5: =IFERROR(VLOOKUP(A5,overtime_base!$J:$L,2,FALSE),0) -> 0 | R5: =IFERROR(VLOOKUP(A5,overtime_base!$J:$L,3,FALSE)/Params!$B$2,0) -> 0
A6: 70000015 | B6: LUZOLO NSEMBOLO | C6: Male | D6: Congo | E6: Mechanic | F6: C2 | G6: 32509 | H6: =DATEDIF(G6,Params!$B$3,"Y") -> 37 | I6: =IF(H6<25,"<25 ans",IF(H6<=29,"25 - 29 ans",IF(H6<=34,"30 - 34 ans ",IF(H6<=39,"35 - 39 ans ",IF(H6<=44,"40 - 44 ans ",IF(H6<=49,"45 - 49 ans ",IF(H6<=54,"50 - 54 ans ",">55"))))))) -> 35 - 39 ans | J6: 44866 | K6: =DATEDIF(J6,Params!$B$3,"Y") -> 3 | L6: =IF(K6<1,"<1 year",IF(K6<=3,"1 - 3 year(s)",IF(K6<=6,"4 - 6 years",IF(K6<=9,"7 - 9 years",">= 10 years")))) -> 1 - 3 year(s) | M6: Engineering | N6: Plant | O6: {=IFERROR(VLOOKUP($A6&"Annual",CHOOSE({1,2},leavebalances_base!$E$3:$E$1230&leavebalances_base!$T$3:$T$1230,leavebalances_base!$AC$3:$AC$1230),2,FALSE),"")} -> 20.843333 | P6: {=IFERROR(VLOOKUP($A6&"Annual",CHOOSE({1,2},leavebalances_base!$E$3:$E$1230&leavebalances_base!$T$3:$T$1230,leavebalances_base!$AD$3:$AD$1230),2,FALSE)/Params!$B$2,"")} -> 1423.8186 | Q6: =IFERROR(VLOOKUP(A6,overtime_base!$J:$L,2,FALSE),0) -> 42.2 | R6: =IFERROR(VLOOKUP(A6,overtime_base!$J:$L,3,FALSE)/Params!$B$2,0) -> 519.11275
A7: 70000019 | B7: Kiesse Banguli | C7: Female | D7: Congo | E7: Payroll and Admin Manager | F7: D1 | G7: 28799 | H7: =DATEDIF(G7,Params!$B$3,"Y") -> 47 | I7: =IF(H7<25,"<25 ans",IF(H7<=29,"25 - 29 ans",IF(H7<=34,"30 - 34 ans ",IF(H7<=39,"35 - 39 ans ",IF(H7<=44,"40 - 44 ans ",IF(H7<=49,"45 - 49 ans ",IF(H7<=54,"50 - 54 ans ",">55"))))))) -> 45 - 49 ans | J7: 41768 | K7: =DATEDIF(J7,Params!$B$3,"Y") -> 12 | L7: =IF(K7<1,"<1 year",IF(K7<=3,"1 - 3 year(s)",IF(K7<=6,"4 - 6 years",IF(K7<=9,"7 - 9 years",">= 10 years")))) -> >= 10 years | M7: HR | N7: Kinshasa_Regions | O7: {=IFERROR(VLOOKUP($A7&"Annual",CHOOSE({1,2},leavebalances_base!$E$3:$E$1230&leavebalances_base!$T$3:$T$1230,leavebalances_base!$AC$3:$AC$1230),2,FALSE),"")} -> 36 | P7: {=IFERROR(VLOOKUP($A7&"Annual",CHOOSE({1,2},leavebalances_base!$E$3:$E$1230&leavebalances_base!$T$3:$T$1230,leavebalances_base!$AD$3:$AD$1230),2,FALSE)/Params!$B$2,"")} -> 7176.7111 | Q7: =IFERROR(VLOOKUP(A7,overtime_base!$J:$L,2,FALSE),0) -> 0 | R7: =IFERROR(VLOOKUP(A7,overtime_base!$J:$L,3,FALSE)/Params!$B$2,0) -> 0
A8: 70000021 | B8: Marie Josee Lisangola | C8: Female | D8: Congo | E8: Facilities Officer | F8: C4 | G8: 29643 | H8: =DATEDIF(G8,Params!$B$3,"Y") -> 45 | I8: =IF(H8<25,"<25 ans",IF(H8<=29,"25 - 29 ans",IF(H8<=34,"30 - 34 ans ",IF(H8<=39,"35 - 39 ans ",IF(H8<=44,"40 - 44 ans ",IF(H8<=49,"45 - 49 ans ",IF(H8<=54,"50 - 54 ans ",">55"))))))) -> 45 - 49 ans | J8: 41771 | K8: =DATEDIF(J8,Params!$B$3,"Y") -> 12 | L8: =IF(K8<1,"<1 year",IF(K8<=3,"1 - 3 year(s)",IF(K8<=6,"4 - 6 years",IF(K8<=9,"7 - 9 years",">= 10 years")))) -> >= 10 years | M8: HR | N8: Kinshasa_Regions | O8: {=IFERROR(VLOOKUP($A8&"Annual",CHOOSE({1,2},leavebalances_base!$E$3:$E$1230&leavebalances_base!$T$3:$T$1230,leavebalances_base!$AC$3:$AC$1230),2,FALSE),"")} -> 30.166667 | P8: {=IFERROR(VLOOKUP($A8&"Annual",CHOOSE({1,2},leavebalances_base!$E$3:$E$1230&leavebalances_base!$T$3:$T$1230,leavebalances_base!$AD$3:$AD$1230),2,FALSE)/Params!$B$2,"")} -> 3472.0591 | Q8: =IFERROR(VLOOKUP(A8,overtime_base!$J:$L,2,FALSE),0) -> 0 | R8: =IFERROR(VLOOKUP(A8,overtime_base!$J:$L,3,FALSE)/Params!$B$2,0) -> 0
A9: 70000022 | B9: Dina Munanga | C9: Female | D9: Congo | E9: Customer Demand Supply Planner | F9: C5 | G9: 29181 | H9: =DATEDIF(G9,Params!$B$3,"Y") -> 46 | I9: =IF(H9<25,"<25 ans",IF(H9<=29,"25 - 29 ans",IF(H9<=34,"30 - 34 ans ",IF(H9<=39,"35 - 39 ans ",IF(H9<=44,"40 - 44 ans ",IF(H9<=49,"45 - 49 ans ",IF(H9<=54,"50 - 54 ans ",">55"))))))) -> 45 - 49 ans | J9: 41771 | K9: =DATEDIF(J9,Params!$B$3,"Y") -> 12 | L9: =IF(K9<1,"<1 year",IF(K9<=3,"1 - 3 year(s)",IF(K9<=6,"4 - 6 years",IF(K9<=9,"7 - 9 years",">= 10 years")))) -> >= 10 years | M9: Sales_CEC | N9: Kinshasa_Regions | O9: {=IFERROR(VLOOKUP($A9&"Annual",CHOOSE({1,2},leavebalances_base!$E$3:$E$1230&leavebalances_base!$T$3:$T$1230,leavebalances_base!$AC$3:$AC$1230),2,FALSE),"")} -> 29 | P9: {=IFERROR(VLOOKUP($A9&"Annual",CHOOSE({1,2},leavebalances_base!$E$3:$E$1230&leavebalances_base!$T$3:$T$1230,leavebalances_base!$AD$3:$AD$1230),2,FALSE)/Params!$B$2,"")} -> 3918.9485 | Q9: =IFERROR(VLOOKUP(A9,overtime_base!$J:$L,2,FALSE),0) -> 0 | R9: =IFERROR(VLOOKUP(A9,overtime_base!$J:$L,3,FALSE)/Params!$B$2,0) -> 0
A10: 70000023 | B10: Banga Banga Onesime | C10: Male | D10: Congo | E10: Driver | F10: B2 | G10: 25208 | H10: =DATEDIF(G10,Params!$B$3,"Y") -> 57 | I10: =IF(H10<25,"<25 ans",IF(H10<=29,"25 - 29 ans",IF(H10<=34,"30 - 34 ans ",IF(H10<=39,"35 - 39 ans ",IF(H10<=44,"40 - 44 ans ",IF(H10<=49,"45 - 49 ans ",IF(H10<=54,"50 - 54 ans ",">55"))))))) -> >55 | J10: 41913 | K10: =DATEDIF(J10,Params!$B$3,"Y") -> 11 | L10: =IF(K10<1,"<1 year",IF(K10<=3,"1 - 3 year(s)",IF(K10<=6,"4 - 6 years",IF(K10<=9,"7 - 9 years",">= 10 years")))) -> >= 10 years | M10: HR | N10: Kinshasa_Regions | O10: {=IFERROR(VLOOKUP($A10&"Annual",CHOOSE({1,2},leavebalances_base!$E$3:$E$1230&leavebalances_base!$T$3:$T$1230,leavebalances_base!$AC$3:$AC$1230),2,FALSE),"")} -> 17.833333 | P10: {=IFERROR(VLOOKUP($A10&"Annual",CHOOSE({1,2},leavebalances_base!$E$3:$E$1230&leavebalances_base!$T$3:$T$1230,leavebalances_base!$AD$3:$AD$1230),2,FALSE)/Params!$B$2,"")} -> 557.51431 | Q10: =IFERROR(VLOOKUP(A10,overtime_base!$J:$L,2,FALSE),0) -> 0 | R10: =IFERROR(VLOOKUP(A10,overtime_base!$J:$L,3,FALSE)/Params!$B$2,0) -> 0
A11: 70000024 | B11: Medard Kitambo | C11: Male | D11: Congo | E11: Driver | F11: B2 | G11: 23836 | H11: =DATEDIF(G11,Params!$B$3,"Y") -> 61 | I11: =IF(H11<25,"<25 ans",IF(H11<=29,"25 - 29 ans",IF(H11<=34,"30 - 34 ans ",IF(H11<=39,"35 - 39 ans ",IF(H11<=44,"40 - 44 ans ",IF(H11<=49,"45 - 49 ans ",IF(H11<=54,"50 - 54 ans ",">55"))))))) -> >55 | J11: 41827 | K11: =DATEDIF(J11,Params!$B$3,"Y") -> 12 | L11: =IF(K11<1,"<1 year",IF(K11<=3,"1 - 3 year(s)",IF(K11<=6,"4 - 6 years",IF(K11<=9,"7 - 9 years",">= 10 years")))) -> >= 10 years | M11: HR | N11: Plant | O11: {=IFERROR(VLOOKUP($A11&"Annual",CHOOSE({1,2},leavebalances_base!$E$3:$E$1230&leavebalances_base!$T$3:$T$1230,leavebalances_base!$AC$3:$AC$1230),2,FALSE),"")} -> 14.47 | P11: {=IFERROR(VLOOKUP($A11&"Annual",CHOOSE({1,2},leavebalances_base!$E$3:$E$1230&leavebalances_base!$T$3:$T$1230,leavebalances_base!$AD$3:$AD$1230),2,FALSE)/Params!$B$2,"")} -> 452.49045 | Q11: =IFERROR(VLOOKUP(A11,overtime_base!$J:$L,2,FALSE),0) -> 0 | R11: =IFERROR(VLOOKUP(A11,overtime_base!$J:$L,3,FALSE)/Params!$B$2,0) -> 0
A12: 70000026 | B12: Kabangu Mutambayi | C12: Male | D12: Congo | E12: Shift Supervisor | F12: C3 | G12: 32392 | H12: =DATEDIF(G12,Params!$B$3,"Y") -> 37 | I12: =IF(H12<25,"<25 ans",IF(H12<=29,"25 - 29 ans",IF(H12<=34,"30 - 34 ans ",IF(H12<=39,"35 - 39 ans ",IF(H12<=44,"40 - 44 ans ",IF(H12<=49,"45 - 49 ans ",IF(H12<=54,"50 - 54 ans ",">55"))))))) -> 35 - 39 ans | J12: 42317 | K12: =DATEDIF(J12,Params!$B$3,"Y") -> 10 | L12: =IF(K12<1,"<1 year",IF(K12<=3,"1 - 3 year(s)",IF(K12<=6,"4 - 6 years",IF(K12<=9,"7 - 9 years",">= 10 years")))) -> >= 10 years | M12: Production | N12: Plant | O12: {=IFERROR(VLOOKUP($A12&"Annual",CHOOSE({1,2},leavebalances_base!$E$3:$E$1230&leavebalances_base!$T$3:$T$1230,leavebalances_base!$AC$3:$AC$1230),2,FALSE),"")} -> 28.67 | P12: {=IFERROR(VLOOKUP($A12&"Annual",CHOOSE({1,2},leavebalances_base!$E$3:$E$1230&leavebalances_base!$T$3:$T$1230,leavebalances_base!$AD$3:$AD$1230),2,FALSE)/Params!$B$2,"")} -> 3484.0653 | Q12: =IFERROR(VLOOKUP(A12,overtime_base!$J:$L,2,FALSE),0) -> 15.71 | R12: =IFERROR(VLOOKUP(A12,overtime_base!$J:$L,3,FALSE)/Params!$B$2,0) -> 309.13287
A13: 70000027 | B13: KABEYA Tresor-Michel | C13: Male | D13: The Democratic Republic of the Congo | E13: Production Manager | F13: D4 | G13: 31255 | H13: =DATEDIF(G13,Params!$B$3,"Y") -> 41 | I13: =IF(H13<25,"<25 ans",IF(H13<=29,"25 - 29 ans",IF(H13<=34,"30 - 34 ans ",IF(H13<=39,"35 - 39 ans ",IF(H13<=44,"40 - 44 ans ",IF(H13<=49,"45 - 49 ans ",IF(H13<=54,"50 - 54 ans ",">55"))))))) -> 40 - 44 ans | J13: 42317 | K13: =DATEDIF(J13,Params!$B$3,"Y") -> 10 | L13: =IF(K13<1,"<1 year",IF(K13<=3,"1 - 3 year(s)",IF(K13<=6,"4 - 6 years",IF(K13<=9,"7 - 9 years",">= 10 years")))) -> >= 10 years | M13: Production | N13: Plant | O13: {=IFERROR(VLOOKUP($A13&"Annual",CHOOSE({1,2},leavebalances_base!$E$3:$E$1230&leavebalances_base!$T$3:$T$1230,leavebalances_base!$AC$3:$AC$1230),2,FALSE),"")} -> 3.3433333 | P13: {=IFERROR(VLOOKUP($A13&"Annual",CHOOSE({1,2},leavebalances_base!$E$3:$E$1230&leavebalances_base!$T$3:$T$1230,leavebalances_base!$AD$3:$AD$1230),2,FALSE)/Params!$B$2,"")} -> 1197.7706 | Q13: =IFERROR(VLOOKUP(A13,overtime_base!$J:$L,2,FALSE),0) -> 0 | R13: =IFERROR(VLOOKUP(A13,overtime_base!$J:$L,3,FALSE)/Params!$B$2,0) -> 0
... A176: 70000266 | B176: Giscard Rukomeza | C176: Male | D176: The Democratic Republic of the Congo | E176: Mining Manager | F176: D2 | G176: 31578 | H176: =DATEDIF(G176,Params!$B$3,"Y") -> 40 | I176: =IF(H176<25,"<25 ans",IF(H176<=29,"25 - 29 ans",IF(H176<=34,"30 - 34 ans ",IF(H176<=39,"35 - 39 ans ",IF(H176<=44,"40 - 44 ans ",IF(H176<=49,"45 - 49 ans ",IF(H176<=54,"50 - 54 ans ",">55"))))))) -> 40 - 44 ans | J176: 45414 | K176: =DATEDIF(J176,Params!$B$3,"Y") -> 2 | L176: =IF(K176<1,"<1 year",IF(K176<=3,"1 - 3 year(s)",IF(K176<=6,"4 - 6 years",IF(K176<=9,"7 - 9 years",">= 10 years")))) -> 1 - 3 year(s) | M176: Mining | N176: Plant | O176: {=IFERROR(VLOOKUP($A176&"Annual",CHOOSE({1,2},leavebalances_base!$E$3:$E$1230&leavebalances_base!$T$3:$T$1230,leavebalances_base!$AC$3:$AC$1230),2,FALSE),"")} -> 21.935484 | P176: {=IFERROR(VLOOKUP($A176&"Annual",CHOOSE({1,2},leavebalances_base!$E$3:$E$1230&leavebalances_base!$T$3:$T$1230,leavebalances_base!$AD$3:$AD$1230),2,FALSE)/Params!$B$2,"")} -> 4912.4301 | Q176: =IFERROR(VLOOKUP(A176,overtime_base!$J:$L,2,FALSE),0) -> 0 | R176: =IFERROR(VLOOKUP(A176,overtime_base!$J:$L,3,FALSE)/Params!$B$2,0) -> 0

Sheet Headacount
B1: Effectifs | F1: Gender per location | G1: Male | H1: Female | I1: Total | K1: Male % | L1: Female %
B2: Headcount | C2: =COUNTA(BASE!$A$2:$A$176) -> 175 | D2: =C2/$C$2 -> 1 | F2: Kinshasa_Regions | G2: =COUNTIFS(BASE!$N$2:$N$176,F2,BASE!$C$2:$C$176,$G$1) -> 46 | H2: =COUNTIFS(BASE!$N$2:$N$176,F2,BASE!$C$2:$C$176,$H$1) -> 20 | I2: =COUNTIF(BASE!$N$2:$N$176,F2) -> 66 | K2: =G2/G$5 -> 0.31081081 | L2: =H2/H$5 -> 0.74074074
B3: M | C3: =COUNTIF(BASE!$C$2:$C$176,"Male") -> 148 | D3: =C3/$C$2 -> 0.84571429 | F3: Plant | G3: =COUNTIFS(BASE!$N$2:$N$176,F3,BASE!$C$2:$C$176,$G$1) -> 96 | H3: =COUNTIFS(BASE!$N$2:$N$176,F3,BASE!$C$2:$C$176,$H$1) -> 6 | I3: =COUNTIF(BASE!$N$2:$N$176,F3) -> 102 | K3: =G3/G$5 -> 0.64864865 | L3: =H3/H$5 -> 0.22222222
B4: F | C4: =COUNTIF(BASE!$C$2:$C$176,"Female") -> 27 | D4: =C4/$C$2 -> 0.15428571 | F4: Lubudi | G4: =COUNTIFS(BASE!$N$2:$N$176,F4,BASE!$C$2:$C$176,$G$1) -> 6 | H4: =COUNTIFS(BASE!$N$2:$N$176,F4,BASE!$C$2:$C$176,$H$1) -> 1 | I4: =COUNTIF(BASE!$N$2:$N$176,F4) -> 7 | K4: =G4/G$5 -> 0.040540541 | L4: =H4/H$5 -> 0.037037037
G5: =SUM(G2:G4) -> 148 | H5: =SUM(H2:H4) -> 27 | I5: =SUM(I2:I4) -> 175 | K5: =SUM(K2:K4) -> 1 | L5: =SUM(L2:L4) -> 1
B6: Age
B7: Range age | C7: Count | D7: % | K7: Average age
B8: <25 ans | C8: {=SUMPRODUCT(--(TRIM(BASE!$I$2:$I$176)=TRIM(B8)))} -> 1 | D8: =C8/$C$16 -> 0.0057142857 | K8: Average Age | L8: =AVERAGE(BASE!$H$2:$H$176) -> 40.102857
B9: 25 - 29 ans | C9: {=SUMPRODUCT(--(TRIM(BASE!$I$2:$I$176)=TRIM(B9)))} -> 14 | D9: =C9/$C$16 -> 0.08 | K9: Male Average Age | L9: =AVERAGEIF(BASE!$C$2:$C$176,"Male",BASE!$H$2:$H$176) -> 40.722973
B10: 30 - 34 ans | C10: {=SUMPRODUCT(--(TRIM(BASE!$I$2:$I$176)=TRIM(B10)))} -> 23 | D10: =C10/$C$16 -> 0.13142857 | K10: Female Average Age | L10: =AVERAGEIF(BASE!$C$2:$C$176,"Female",BASE!$H$2:$H$176) -> 36.703704
B11: 35 - 39 ans | C11: {=SUMPRODUCT(--(TRIM(BASE!$I$2:$I$176)=TRIM(B11)))} -> 55 | D11: =C11/$C$16 -> 0.31428571 | K11: Retirement | L11: =COUNTIF(BASE!$H$2:$H$176,">=65") -> 0
B12: 40 - 44 ans | C12: {=SUMPRODUCT(--(TRIM(BASE!$I$2:$I$176)=TRIM(B12)))} -> 38 | D12: =C12/$C$16 -> 0.21714286 | K12: Pre-retirement | L12: =COUNTIFS(BASE!$H$2:$H$176,">=55",BASE!$H$2:$H$176,"<65") -> 11
B13: 45 - 49 ans | C13: {=SUMPRODUCT(--(TRIM(BASE!$I$2:$I$176)=TRIM(B13)))} -> 24 | D13: =C13/$C$16 -> 0.13714286
B14: 50 - 54 ans | C14: {=SUMPRODUCT(--(TRIM(BASE!$I$2:$I$176)=TRIM(B14)))} -> 9 | D14: =C14/$C$16 -> 0.051428571
B15: >55 | C15: {=SUMPRODUCT(--(TRIM(BASE!$I$2:$I$176)=TRIM(B15)))} -> 11 | D15: =C15/$C$16 -> 0.062857143
B16: Total | C16: =SUM(C8:C15) -> 175 | D16: =SUM(D8:D15) -> 1
B18: Length Of Service
B19: Length of service | C19: Count | D19: %
B20: <1 year | C20: {=SUMPRODUCT(--(TRIM(BASE!$L$2:$L$176)=TRIM(B20)))} -> 14 | D20: =C20/$C$25 -> 0.08 | K20: Average Length Of Service
B21: 1 - 3 year(s) | C21: {=SUMPRODUCT(--(TRIM(BASE!$L$2:$L$176)=TRIM(B21)))} -> 46 | D21: =C21/$C$25 -> 0.26285714 | K21: Average Length Of Service | L21: =AVERAGE(BASE!$K$2:$K$176) -> 5.7257143
B22: 4 - 6 years | C22: {=SUMPRODUCT(--(TRIM(BASE!$L$2:$L$176)=TRIM(B22)))} -> 36 | D22: =C22/$C$25 -> 0.20571429
B23: 7 - 9 years | C23: {=SUMPRODUCT(--(TRIM(BASE!$L$2:$L$176)=TRIM(B23)))} -> 51 | D23: =C23/$C$25 -> 0.29142857
B24: >= 10 years | C24: {=SUMPRODUCT(--(TRIM(BASE!$L$2:$L$176)=TRIM(B24)))} -> 28 | D24: =C24/$C$25 -> 0.16
B25: Total | C25: =SUM(C20:C24) -> 175 | D25: =SUM(D20:D24) -> 1

Sheet IN OUT
A1: Turnover and Attrition
A3: IN – OUT YTD | B3: APR | C3: MAY | D3: JUN | E3: JULY | F3: AUG | G3: SEPT | H3: OCT | I3: NOV | J3: DEC | K3: JAN | L3: FEB | M3: MAR | N3: FY26 YTD
A4: IN | B4: 0 | C4: 1 | D4: 3 | E4: =COUNTA(A21:A29) -> 0 | N4: =SUM(B4:M4) -> 4
A5: Out | B5: 1 | C5: 1 | D5: 0 | E5: =COUNTA(J21:J29) -> 1 | N5: =SUM(B5:M5) -> 3
A6: Attrition Rate | B6: =IFERROR(B5/B8, 0) -> 0.0057803468 | C6: =IFERROR(C5/C8, 0) -> 0.0057803468 | D6: =IFERROR(D5/D8, 0) -> 0 | E6: =IFERROR(E5/E8, 0) -> 0.0057142857 | F6: =IFERROR(F5/F8, 0) -> 0 | G6: =IFERROR(G5/G8, 0) -> 0 | H6: =IFERROR(H5/H8, 0) -> 0 | I6: =IFERROR(I5/I8, 0) -> 0 | ... N6: =IFERROR(N5/N8, 0) -> 0.017142857
A7: Turnover | B7: =IFERROR((B5+B4)/2/B8,0) -> 0.0028901734 | C7: =IFERROR((C5+C4)/2/B8,0) -> 0.0057803468 | D7: =IFERROR((D5+D4)/2/C8,0) -> 0.0086705202 | E7: =IFERROR((E5+E4)/2/D8,0) -> 0.0028409091 | F7: =IFERROR((F5+F4)/2/E8,0) -> 0 | G7: =IFERROR((G5+G4)/2/F8,0) -> 0 | H7: =IFERROR((H5+H4)/2/G8,0) -> 0 | I7: =IFERROR((I5+I4)/2/H8,0) -> 0 | J7: =IFERROR((J5+J4)/2/I8,0) -> 0 | ... M7: =IFERROR((M5+M4)/2/L8,0) -> 0 | N7: =IFERROR((N5+N4)/2/B8,0) -> 0.020231214
A8: Total Headcount | B8: 173 | C8: =B8+C4-C5 -> 173 | D8: =C8+D4-D5 -> 176 | E8: =D8+E4-E5 -> 175 | F8: =E8+F4-F5 -> 175 | G8: =F8+G4-G5 -> 175 | H8: =G8+H4-H5 -> 175 | I8: =H8+I4-I5 -> 175 | J8: =I8+J4-J5 -> 175 | ... M8: =L8+M4-M5 -> 175 | N8: =M8 -> 175
A11: FY 2026 | B11: Number | C11: %
A12: Amicable Separation | B12: 0 | C12: =B12/$B$17 -> 0
A13: Dismissal | B13: 1 | C13: =B13/$B$17 -> 1
A14: Resignation | B14: 0 | C14: =B14/$B$17 -> 0
A15: Contract Expired | B15: =IFERROR(VLOOKUP(A15, B49:C51, 2, FALSE), 0) -> 0 | C15: =B15/$B$17 -> 0
A16: Retirement | B16: =IFERROR(VLOOKUP(A16, B50:C52, 2, FALSE), 0) -> 0 | C16: =B16/$B$17 -> 0
B17: =SUM(B12:B16) -> 1 | C17: =B17/$O$9 -> #DIV/0!
A19: IN FY26 | J19: OUT FY26
A20: Emp Number | B20: Emp Last Name | C20: First Name | D20: Gender | E20: Grade | F20: Position | G20: Departments | H20: Employment Date | J20: Emp Number | K20: Emp Last Name | L20: First Name | M20: Gender | N20: Grade | O20: Position | P20: Departement | Q20: Length of Service | R20: Termination Date | S20: Termination Reason
J21: 70000273 | K21: NDUSHA | L21: CLEMENT | M21: M | N21: C2 | O21: Process Technician | P21: Production | Q21: 2 | R21: 16/07/2026 | S21: Dismisal

Sheet Staff_Cost_KPI
A1: Staff Cost KPI
A3: Months | B3: April | C3: May | D3: June | E3: July | F3: August | G3: September | H3: October | I3: November | J3: December | K3: January | L3: February | M3: March
A4: Actual YTD | B4: 173 | C4: 173 | D4: 176 | E4: =Headacount!C2 -> 175
A5: Salaries | B5: 898096 | C5: 1696233 | D5: 2637490 | E5: 5866469
A6: Volumes | B6: 32403 | C6: 95147 | D6: 152792 | E6: 376622
A7: Revenue | B7: 5454809 | C7: 15754563 | D7: 24871414 | E7: 60292193
A9: Plan Budget YTD | B9: 192 | C9: 192 | D9: 192 | E9: 192 | F9: 192 | G9: 192 | H9: 192 | I9: 192 | J9: 192 | K9: 192 | L9: 192 | M9: 192
A10: Salaries | B10: 1021708 | C10: 1803143 | D10: 3066435 | E10: 6525994
A11: Volumes | B11: 55000 | C11: 130697 | D11: 199444 | E11: 470634
A12: Revenue | B12: 8971598 | C12: 21304079 | D12: 32630028 | E12: 77519384
A13: %
A14: Salaries | B14: =B21/B36 -> 0.87901436 | C14: =C21/C36 -> 0.94070908 | D14: =D21/D36 -> 0.86011606 | E14: =E21/E36 -> 0.89893877
A15: Volumes | B15: =B27/B42 -> 0.65384929 | C15: =C27/C42 -> 0.80795022 | D15: =D27/D42 -> 0.83573425 | E15: =E27/E42 -> 0.87798191
A16: Revenue | B16: =B29/B43 -> 0.67478414 | C16: =C29/C43 -> 0.820727 | D16: =D29/D43 -> 0.83151788 | E16: =E29/E43 -> 0.85332397
A18: ACTUAL
A19: FY25 - Actual | B19: April | C19: May | D19: June | E19: July | F19: August | G19: September | H19: October | I19: November | J19: December | K19: January | L19: February | M19: March | N19: Total
A20: Staff_Cost | B20: 898096 | C20: 798137 | D20: 941257 | E20: =E5-D21 -> 3228979 | F20: =F5-E21 -> -5866469 | G20: =G5-F21 -> 0 | H20: =H5-G21 -> 0 | I20: =I5-H21 -> 0 | J20: =J5-I21 -> 0 | K20: =K5-J21 -> 0 | L20: =L5-K21 -> 0 | M20: =M5-L21 -> 0 | N20: =SUM(B20:M20) -> 0
A21: Staff_Cumul | B21: =B20 -> 898096 | C21: =B21+C20 -> 1696233 | D21: =C21+D20 -> 2637490 | E21: =D21+E20 -> 5866469 | F21: =E21+F20 -> 0 | G21: =F21+G20 -> 0 | H21: =G21+H20 -> 0 | I21: =H21+I20 -> 0 | J21: =I21+J20 -> 0 | ... M21: =L21+M20 -> 0 | N21: =MAX(B21:M21) -> 5866469
A22: Volume | B22: 32403 | C22: 62744 | D22: 57645 | E22: =E6-D23 -> 223830 | F22: =F6-E23 -> -376622 | G22: =G6-F23 -> 0 | H22: =H6-G23 -> 0 | I22: =I6-H23 -> 0 | J22: =J6-I23 -> 0 | K22: =K6-J23 -> 0 | L22: =L6-K23 -> 0 | M22: =M6-L23 -> 0 | N22: =SUM(B22:M22) -> 0
A23: Volume_Cum | B23: =B22 -> 32403 | C23: =B23+C22 -> 95147 | D23: =C23+D22 -> 152792 | E23: =D23+E22 -> 376622 | F23: =E23+F22 -> 0 | G23: =F23+G22 -> 0 | H23: =G23+H22 -> 0 | I23: =H23+I22 -> 0 | J23: =I23+J22 -> 0 | ... M23: =L23+M22 -> 0 | N23: =MAX(B23:M23) -> 376622
A24: Revenue | B24: 5454809 | C24: 10299754 | D24: 9116851 | E24: =E7-D25 -> 35420779 | F24: =F7-E25 -> -60292193 | G24: =G7-F25 -> 0 | H24: =H7-G25 -> 0 | I24: =I7-H25 -> 0 | J24: =J7-I25 -> 0 | K24: =K7-J25 -> 0 | L24: =L7-K25 -> 0 | M24: =M7-L25 -> 0 | N24: =SUM(B24:M24) -> 0
A25: Revenue_Cum | B25: =B24 -> 5454809 | C25: =B25+C24 -> 15754563 | D25: =C25+D24 -> 24871414 | E25: =D25+E24 -> 60292193 | F25: =E25+F24 -> 0 | G25: =F25+G24 -> 0 | H25: =G25+H24 -> 0 | I25: =H25+I24 -> 0 | J25: =I25+J24 -> 0 | ... M25: =L25+M24 -> 0 | N25: =MAX(B25:M25) -> 60292193
A27: T/employee YTD | B27: =IFERROR(B23/B$4, 0) -> 187.30058 | C27: =IFERROR(C23/C$4, 0) -> 549.98266 | D27: =IFERROR(D23/D$4, 0) -> 868.13636 | E27: =IFERROR(E23/E$4, 0) -> 2152.1257 | F27: =IFERROR(F23/F$4, 0) -> 0 | G27: =IFERROR(G23/G$4, 0) -> 0 | H27: =IFERROR(H23/H$4, 0) -> 0 | I27: =IFERROR(I23/I$4, 0) -> 0 | ... M27: =IFERROR(M23/M$4, 0) -> 0 | N27: =SUM(B27:M27) -> 3757.5453
A28: T/employee | B28: =IFERROR(B22/B$4,0) -> 187.30058 | C28: =IFERROR(C22/C$4,0) -> 362.68208 | D28: =IFERROR(D22/D$4,0) -> 327.52841 | E28: =IFERROR(E22/E$4,0) -> 1279.0286 | F28: =IFERROR(F22/F$4,0) -> 0 | G28: =IFERROR(G22/G$4,0) -> 0 | H28: =IFERROR(H22/H$4,0) -> 0 | I28: =IFERROR(I22/I$4,0) -> 0 | ... M28: =IFERROR(M22/M$4,0) -> 0 | N28: =SUM(B28:M28) -> 2156.5396
A29: Revenue/Employee YTD | B29: =IFERROR(B25/B$4,0) -> 31530.688 | C29: =IFERROR(C25/C$4,0) -> 91066.838 | D29: =IFERROR(D25/D$4,0) -> 141314.85 | E29: =IFERROR(E25/E$4,0) -> 344526.82 | F29: =IFERROR(F25/F$4,0) -> 0 | G29: =IFERROR(G25/G$4,0) -> 0 | H29: =IFERROR(H25/H$4,0) -> 0 | I29: =IFERROR(I25/I$4,0) -> 0 | ... M29: =IFERROR(M25/M$4,0) -> 0 | N29: =SUM(B29:M29) -> 608439.2
A30: Revenue/Employee | B30: =IFERROR(B24/B$4, 0) -> 31530.688 | C30: =IFERROR(C24/C$4, 0) -> 59536.15 | D30: =IFERROR(D24/D$4, 0) -> 51800.29 | E30: =IFERROR(E24/E$4, 0) -> 202404.45 | F30: =IFERROR(F24/F$4, 0) -> 0 | G30: =IFERROR(G24/G$4, 0) -> 0 | H30: =IFERROR(H24/H$4, 0) -> 0 | I30: =IFERROR(I24/I$4, 0) -> 0 | ... M30: =IFERROR(M24/M$4, 0) -> 0 | N30: =SUM(B30:M30) -> 345271.58
A33: BUDGET
A34: FY25 - Budget | B34: April | C34: May | D34: June | E34: July | F34: August | G34: September | H34: October | I34: November | J34: December | K34: January | L34: February | M34: March | N34: Total
A35: Staff_Cost | B35: 1021708 | C35: 781435 | D35: 1263292 | E35: =E10-D36 -> 3459559 | F35: =F10-E36 -> -6525994 | G35: =G10-F36 -> 0 | H35: =H10-G36 -> 0 | I35: =I10-H36 -> 0 | J35: =J10-I36 -> 0 | K35: =K10-J36 -> 0 | L35: =L10-K36 -> 0 | M35: =M10-L36 -> 0 | N35: =SUM(B35:M35) -> 0
A36: Staff_Cumul | B36: =B35 -> 1021708 | C36: =B36+C35 -> 1803143 | D36: =C36+D35 -> 3066435 | E36: =D36+E35 -> 6525994 | F36: =E36+F35 -> 0 | G36: =F36+G35 -> 0 | H36: =G36+H35 -> 0 | I36: =H36+I35 -> 0 | J36: =I36+J35 -> 0 | ... M36: =L36+M35 -> 0 | N36: =MAX(B36:M36) -> 6525994
A37: Volume | B37: 55000 | C37: 75697 | D37: 68747 | E37: =E11-D38 -> 271190 | F37: =F12-E38 -> -470634 | N37: =SUM(B37:M37) -> 0
A38: Volume_Cum | B38: =B37 -> 55000 | C38: =B38+C37 -> 130697 | D38: =C38+D37 -> 199444 | E38: =D38+E37 -> 470634 | F38: =IF(E38+F37=0,E38,E38+F37) -> 470634 | G38: =F38+G37 -> 470634 | H38: =G38+H37 -> 470634 | I38: =H38+I37 -> 470634 | J38: =I38+J37 -> 470634 | K38: =J38+K37 -> 470634 | L38: =K38+L37 -> 470634 | M38: =L38+M37 -> 470634 | N38: =MAX(B38:M38) -> 470634
A39: Revenue | B39: 8971598 | C39: 12332481 | D39: 11325949 | E39: =E12-D40 -> 44889356 | F39: =F14-E40 -> -77519384 | N39: =SUM(B39:M39) -> 0
A40: Revenue_Cum | B40: =B39 -> 8971598 | C40: =B40+C39 -> 21304079 | D40: =C40+D39 -> 32630028 | E40: =D40+E39 -> 77519384 | F40: =IF(E40+F39=0,E40,E40+F39) -> 77519384 | G40: =F40+G39 -> 77519384 | H40: =G40+H39 -> 77519384 | I40: =H40+I39 -> 77519384 | J40: =I40+J39 -> 77519384 | K40: =J40+K39 -> 77519384 | L40: =K40+L39 -> 77519384 | M40: =L40+M39 -> 77519384 | N40: =MAX(B40:M40) -> 77519384
A42: T/employee | B42: =IFERROR(B38/B$9, 0) -> 286.45833 | C42: =IFERROR(C38/C$9, 0) -> 680.71354 | D42: =IFERROR(D38/D$9, 0) -> 1038.7708 | E42: =IFERROR(E38/E$9, 0) -> 2451.2188 | F42: =IFERROR(F38/F$9, 0) -> 2451.2188 | G42: =IFERROR(G38/G$9, 0) -> 2451.2188 | H42: =IFERROR(H38/H$9, 0) -> 2451.2188 | I42: =IFERROR(I38/I$9, 0) -> 2451.2188 | ... M42: =IFERROR(M38/M$9, 0) -> 2451.2188 | N42: =SUM(B42:M42) -> 24066.911
A43: Revenue/Employee | B43: =IFERROR(B40/B$9,0) -> 46727.073 | C43: =IFERROR(C40/C$9,0) -> 110958.74 | D43: =IFERROR(D40/D$9,0) -> 169948.06 | E43: =IFERROR(E40/E$9,0) -> 403746.79 | F43: =IFERROR(F40/F$9,0) -> 403746.79 | G43: =IFERROR(G40/G$9,0) -> 403746.79 | H43: =IFERROR(H40/H$9,0) -> 403746.79 | I43: =IFERROR(I40/I$9,0) -> 403746.79 | ... M43: =IFERROR(M40/M$9,0) -> 403746.79 | N43: =SUM(B43:M43) -> 3961355

Sheet OVT
A1: OVERTIME
A2: Dept | B2: Hours | C2: Cost | R2: Employee | S2: Name | T2: Hours | U2: Cost | V2: Leave | W2: Department
A3: {=_xlfn.UNIQUE(BASE!M2:M176)} -> Production | B3: =SUMIFS(BASE!$Q$2:$Q$176,BASE!$M$2:$M$176,OVT!A3) -> 378.92 | C3: =SUMIFS(BASE!$R$2:$R$176,BASE!$M$2:$M$176,OVT!A3) -> 3481.9248 | R3: {=_xlfn.UNIQUE(overtime_base!C2:C111)} -> 70000076 | S3: =VLOOKUP(R3,BASE!$A:$R,2,FALSE) -> Erick Nlandu | T3: =VLOOKUP(R3,BASE!$A:$R,17,FALSE) -> 21.74 | U3: =VLOOKUP(R3,BASE!$A:$R,18,FALSE) -> 176.59836 | V3: =VLOOKUP(R3,BASE!$A:$R,15,FALSE) -> 5.1666667 | W3: =VLOOKUP(R3,BASE!$A:$M,13,FALSE) -> Quality Assurance
A4: HR | B4: =SUMIFS(BASE!$Q$2:$Q$176,BASE!$M$2:$M$176,OVT!A4) -> 0 | C4: =SUMIFS(BASE!$R$2:$R$176,BASE!$M$2:$M$176,OVT!A4) -> 0 | R4: 70000077 | S4: =VLOOKUP(R4,BASE!$A:$R,2,FALSE) -> Cadet Samba | T4: =VLOOKUP(R4,BASE!$A:$R,17,FALSE) -> 3.03 | U4: =VLOOKUP(R4,BASE!$A:$R,18,FALSE) -> 15.699185 | V4: =VLOOKUP(R4,BASE!$A:$R,15,FALSE) -> 12.166667 | W4: =VLOOKUP(R4,BASE!$A:$M,13,FALSE) -> Quality Assurance
A5: Sales_CEC | B5: =SUMIFS(BASE!$Q$2:$Q$176,BASE!$M$2:$M$176,OVT!A5) -> 0 | C5: =SUMIFS(BASE!$R$2:$R$176,BASE!$M$2:$M$176,OVT!A5) -> 0 | R5: 70000080 | S5: =VLOOKUP(R5,BASE!$A:$R,2,FALSE) -> Nadege Nsilu | T5: =VLOOKUP(R5,BASE!$A:$R,17,FALSE) -> 18.81 | U5: =VLOOKUP(R5,BASE!$A:$R,18,FALSE) -> 142.30669 | V5: =VLOOKUP(R5,BASE!$A:$R,15,FALSE) -> 16.166667 | W5: =VLOOKUP(R5,BASE!$A:$M,13,FALSE) -> Quality Assurance
A6: Engineering | B6: =SUMIFS(BASE!$Q$2:$Q$176,BASE!$M$2:$M$176,OVT!A6) -> 639.19 | C6: =SUMIFS(BASE!$R$2:$R$176,BASE!$M$2:$M$176,OVT!A6) -> 6262.8717 | R6: 70000081 | S6: =VLOOKUP(R6,BASE!$A:$R,2,FALSE) -> Bertin Tandu | T6: =VLOOKUP(R6,BASE!$A:$R,17,FALSE) -> 9.05 | U6: =VLOOKUP(R6,BASE!$A:$R,18,FALSE) -> 69.187249 | V6: =VLOOKUP(R6,BASE!$A:$R,15,FALSE) -> 12.666667 | W6: =VLOOKUP(R6,BASE!$A:$M,13,FALSE) -> Quality Assurance
A7: Optimization | B7: =SUMIFS(BASE!$Q$2:$Q$176,BASE!$M$2:$M$176,OVT!A7) -> 0 | C7: =SUMIFS(BASE!$R$2:$R$176,BASE!$M$2:$M$176,OVT!A7) -> 0 | R7: 70000083 | S7: =VLOOKUP(R7,BASE!$A:$R,2,FALSE) -> Moise Musako | T7: =VLOOKUP(R7,BASE!$A:$R,17,FALSE) -> 10.21 | U7: =VLOOKUP(R7,BASE!$A:$R,18,FALSE) -> 175.99413 | V7: =VLOOKUP(R7,BASE!$A:$R,15,FALSE) -> 12.833333 | W7: =VLOOKUP(R7,BASE!$A:$M,13,FALSE) -> Quality Assurance
A8: Finance | B8: =SUMIFS(BASE!$Q$2:$Q$176,BASE!$M$2:$M$176,OVT!A8) -> 0 | C8: =SUMIFS(BASE!$R$2:$R$176,BASE!$M$2:$M$176,OVT!A8) -> 0 | R8: 70000084 | S8: =VLOOKUP(R8,BASE!$A:$R,2,FALSE) -> Delvis Mvilambi | T8: =VLOOKUP(R8,BASE!$A:$R,17,FALSE) -> 8.57 | U8: =VLOOKUP(R8,BASE!$A:$R,18,FALSE) -> 40.804736 | V8: =VLOOKUP(R8,BASE!$A:$R,15,FALSE) -> 13.166667 | W8: =VLOOKUP(R8,BASE!$A:$M,13,FALSE) -> Quality Assurance
A9: Mining | B9: =SUMIFS(BASE!$Q$2:$Q$176,BASE!$M$2:$M$176,OVT!A9) -> 57.3 | C9: =SUMIFS(BASE!$R$2:$R$176,BASE!$M$2:$M$176,OVT!A9) -> 430.45051 | R9: 70000210 | S9: =VLOOKUP(R9,BASE!$A:$R,2,FALSE) -> Sosthene Nyomba Kamanda | T9: =VLOOKUP(R9,BASE!$A:$R,17,FALSE) -> 15.43 | U9: =VLOOKUP(R9,BASE!$A:$R,18,FALSE) -> 177.08857 | V9: =VLOOKUP(R9,BASE!$A:$R,15,FALSE) -> 12.17 | W9: =VLOOKUP(R9,BASE!$A:$M,13,FALSE) -> Quality Assurance
A10: Quality Assurance | B10: =SUMIFS(BASE!$Q$2:$Q$176,BASE!$M$2:$M$176,OVT!A10) -> 111 | C10: =SUMIFS(BASE!$R$2:$R$176,BASE!$M$2:$M$176,OVT!A10) -> 942.05118 | R10: 70000276 | S10: =VLOOKUP(R10,BASE!$A:$R,2,FALSE) -> Emmanuel Mawete | T10: =VLOOKUP(R10,BASE!$A:$R,17,FALSE) -> 24.16 | U10: =VLOOKUP(R10,BASE!$A:$R,18,FALSE) -> 144.37226 | V10: =VLOOKUP(R10,BASE!$A:$R,15,FALSE) -> 15.222222 | W10: =VLOOKUP(R10,BASE!$A:$M,13,FALSE) -> Quality Assurance
A11: MD Office | B11: =SUMIFS(BASE!$Q$2:$Q$176,BASE!$M$2:$M$176,OVT!A11) -> 0 | C11: =SUMIFS(BASE!$R$2:$R$176,BASE!$M$2:$M$176,OVT!A11) -> 0 | R11: 70000069 | S11: =VLOOKUP(R11,BASE!$A:$R,2,FALSE) -> Gervais Bavibidila | T11: =VLOOKUP(R11,BASE!$A:$R,17,FALSE) -> 3.17 | U11: =VLOOKUP(R11,BASE!$A:$R,18,FALSE) -> 13.601131 | V11: =VLOOKUP(R11,BASE!$A:$R,15,FALSE) -> 18.33 | W11: =VLOOKUP(R11,BASE!$A:$M,13,FALSE) -> Production
A12: Procurement | B12: =SUMIFS(BASE!$Q$2:$Q$176,BASE!$M$2:$M$176,OVT!A12) -> 0 | C12: =SUMIFS(BASE!$R$2:$R$176,BASE!$M$2:$M$176,OVT!A12) -> 0 | R12: 70000070 | S12: =VLOOKUP(R12,BASE!$A:$R,2,FALSE) -> Eder Bitutu | T12: =VLOOKUP(R12,BASE!$A:$R,17,FALSE) -> 6 | U12: =VLOOKUP(R12,BASE!$A:$R,18,FALSE) -> 25.838653 | V12: =VLOOKUP(R12,BASE!$A:$R,15,FALSE) -> 28.75 | W12: =VLOOKUP(R12,BASE!$A:$M,13,FALSE) -> Production
A13: SHE | B13: =SUMIFS(BASE!$Q$2:$Q$176,BASE!$M$2:$M$176,OVT!A13) -> 0 | C13: =SUMIFS(BASE!$R$2:$R$176,BASE!$M$2:$M$176,OVT!A13) -> 0 | R13: 70000026 | S13: =VLOOKUP(R13,BASE!$A:$R,2,FALSE) -> Kabangu Mutambayi | T13: =VLOOKUP(R13,BASE!$A:$R,17,FALSE) -> 15.71 | U13: =VLOOKUP(R13,BASE!$A:$R,18,FALSE) -> 309.13287 | V13: =VLOOKUP(R13,BASE!$A:$R,15,FALSE) -> 28.67 | W13: =VLOOKUP(R13,BASE!$A:$M,13,FALSE) -> Production
A14: Logistic | B14: =SUMIFS(BASE!$Q$2:$Q$176,BASE!$M$2:$M$176,OVT!A14) -> 65.57 | C14: =SUMIFS(BASE!$R$2:$R$176,BASE!$M$2:$M$176,OVT!A14) -> 716.59825 | R14: 70000063 | S14: =VLOOKUP(R14,BASE!$A:$R,2,FALSE) -> Jisca Muanda | T14: =VLOOKUP(R14,BASE!$A:$R,17,FALSE) -> 41.34 | U14: =VLOOKUP(R14,BASE!$A:$R,18,FALSE) -> 616.99775 | V14: =VLOOKUP(R14,BASE!$A:$R,15,FALSE) -> 16.996667 | W14: =VLOOKUP(R14,BASE!$A:$M,13,FALSE) -> Production
A15: Transport and Transit | B15: =SUMIFS(BASE!$Q$2:$Q$176,BASE!$M$2:$M$176,OVT!A15) -> 0 | C15: =SUMIFS(BASE!$R$2:$R$176,BASE!$M$2:$M$176,OVT!A15) -> 0 | R15: 70000064 | S15: =VLOOKUP(R15,BASE!$A:$R,2,FALSE) -> Ramses Kalunga | T15: =VLOOKUP(R15,BASE!$A:$R,17,FALSE) -> 6.11 | U15: =VLOOKUP(R15,BASE!$A:$R,18,FALSE) -> 84.021902 | V15: =VLOOKUP(R15,BASE!$A:$R,15,FALSE) -> 0.99666667 | W15: =VLOOKUP(R15,BASE!$A:$M,13,FALSE) -> Production
... A19: Sales and Marketing | B19: =SUMIFS(BASE!$Q$2:$Q$176,BASE!$M$2:$M$176,OVT!A19) -> 0 | C19: =SUMIFS(BASE!$R$2:$R$176,BASE!$M$2:$M$176,OVT!A19) -> 0 | R19: 70000264 | S19: =VLOOKUP(R19,BASE!$A:$R,2,FALSE) -> Yannick Kamunga | T19: =VLOOKUP(R19,BASE!$A:$R,17,FALSE) -> 42.51 | U19: =VLOOKUP(R19,BASE!$A:$R,18,FALSE) -> 287.86904 | V19: =VLOOKUP(R19,BASE!$A:$R,15,FALSE) -> 18.166667 | W19: =VLOOKUP(R19,BASE!$A:$M,13,FALSE) -> Production
R20: 70000057 | S20: =VLOOKUP(R20,BASE!$A:$R,2,FALSE) -> Olivier Lutonadio | T20: =VLOOKUP(R20,BASE!$A:$R,17,FALSE) -> 18 | U20: =VLOOKUP(R20,BASE!$A:$R,18,FALSE) -> 188.72856 | V20: =VLOOKUP(R20,BASE!$A:$R,15,FALSE) -> 8.9166667 | W20: =VLOOKUP(R20,BASE!$A:$M,13,FALSE) -> Production
A21: HOURS | B21: MAR | C21: APR | D21: MAY | E21: JUN | F21: JUL | G21: AUG | H21: SEP | I21: OCT | J21: NOV | K21: DEC | L21: JAN | M21: FEB | N21: MAR | O21: % | P21: Total | R21: 70000059 | S21: =VLOOKUP(R21,BASE!$A:$R,2,FALSE) -> Rodrigue Luzolawo | T21: =VLOOKUP(R21,BASE!$A:$R,17,FALSE) -> 22 | U21: =VLOOKUP(R21,BASE!$A:$R,18,FALSE) -> 240.20083 | V21: =VLOOKUP(R21,BASE!$A:$R,15,FALSE) -> 2.9966667 | W21: =VLOOKUP(R21,BASE!$A:$M,13,FALSE) -> Production
A22: CEC | B22: 0 | C22: 0 | D22: 16 | E22: 0 | F22: =IFERROR(VLOOKUP(A22,$A$3:$C$19,2,FALSE),0) -> 0 | O22: =P22/$P$29 -> 0.0039209536 | P22: =SUM(C22:N22) -> 16 | R22: 70000061 | S22: =VLOOKUP(R22,BASE!$A:$R,2,FALSE) -> Joel Nzuzi | T22: =VLOOKUP(R22,BASE!$A:$R,17,FALSE) -> 22 | U22: =VLOOKUP(R22,BASE!$A:$R,18,FALSE) -> 253.08917 | V22: =VLOOKUP(R22,BASE!$A:$R,15,FALSE) -> 22.996667 | W22: =VLOOKUP(R22,BASE!$A:$M,13,FALSE) -> Production
A23: Engineering | B23: 356.34 | C23: 356.34 | D23: 538.73 | E23: 784.18 | F23: =IFERROR(VLOOKUP(A23,$A$3:$C$19,2,FALSE),0) -> 639.19 | O23: =P23/$P$29 -> 0.56815598 | P23: =SUM(C23:N23) -> 2318.44 | R23: 70000214 | S23: =VLOOKUP(R23,BASE!$A:$R,2,FALSE) -> Joel Matoko | T23: =VLOOKUP(R23,BASE!$A:$R,17,FALSE) -> 8 | U23: =VLOOKUP(R23,BASE!$A:$R,18,FALSE) -> 49.563349 | V23: =VLOOKUP(R23,BASE!$A:$R,15,FALSE) -> 16.34 | W23: =VLOOKUP(R23,BASE!$A:$M,13,FALSE) -> Production
A24: Mining | B24: 0 | C24: 64 | D24: 52.3 | E24: 60 | F24: =IFERROR(VLOOKUP(A24,$A$3:$C$19,2,FALSE),0) -> 57.3 | O24: =P24/$P$29 -> 0.057245922 | P24: =SUM(C24:N24) -> 233.6 | R24: 70000029 | S24: =VLOOKUP(R24,BASE!$A:$R,2,FALSE) -> Maphasi Vangu | T24: =VLOOKUP(R24,BASE!$A:$R,17,FALSE) -> 14.74 | U24: =VLOOKUP(R24,BASE!$A:$R,18,FALSE) -> 352.06016 | V24: =VLOOKUP(R24,BASE!$A:$R,15,FALSE) -> 20.67 | W24: =VLOOKUP(R24,BASE!$A:$M,13,FALSE) -> Production
A25: Optimization | B25: 0 | C25: 0 | D25: 6.3 | E25: 0 | F25: =IFERROR(VLOOKUP(A25,$A$3:$C$19,2,FALSE),0) -> 0 | O25: =P25/$P$29 -> 0.0015438755 | P25: =SUM(C25:N25) -> 6.3 | R25: 70000056 | S25: =VLOOKUP(R25,BASE!$A:$R,2,FALSE) -> Gaylor Nsakala | T25: =VLOOKUP(R25,BASE!$A:$R,17,FALSE) -> 8.39 | U25: =VLOOKUP(R25,BASE!$A:$R,18,FALSE) -> 48.529697 | V25: =VLOOKUP(R25,BASE!$A:$R,15,FALSE) -> 10.33 | W25: =VLOOKUP(R25,BASE!$A:$M,13,FALSE) -> Production
A26: Production | B26: 53.06 | C26: 53.06 | D26: 241.41 | E26: 163.52 | F26: =IFERROR(VLOOKUP(A26,$A$3:$C$19,2,FALSE),0) -> 378.92 | O26: =P26/$P$29 -> 0.20509283 | P26: =SUM(C26:N26) -> 836.91 | R26: 70000096 | S26: =VLOOKUP(R26,BASE!$A:$R,2,FALSE) -> Osee Lukuayi | T26: =VLOOKUP(R26,BASE!$A:$R,17,FALSE) -> 8.06 | U26: =VLOOKUP(R26,BASE!$A:$R,18,FALSE) -> 32.483349 | V26: =VLOOKUP(R26,BASE!$A:$R,15,FALSE) -> 3.0033333 | W26: =VLOOKUP(R26,BASE!$A:$M,13,FALSE) -> Production
A27: Logistic | B27: 57.99 | C27: 57.99 | D27: 128.91 | E27: 82.24 | F27: =IFERROR(VLOOKUP(A27,$A$3:$C$19,2,FALSE),0) -> 65.57 | O27: =P27/$P$29 -> 0.082023898 | P27: =SUM(C27:N27) -> 334.71 | R27: 70000211 | S27: =VLOOKUP(R27,BASE!$A:$R,2,FALSE) -> Joel Toko | T27: =VLOOKUP(R27,BASE!$A:$R,17,FALSE) -> 7.09 | U27: =VLOOKUP(R27,BASE!$A:$R,18,FALSE) -> 52.91049 | V27: =VLOOKUP(R27,BASE!$A:$R,15,FALSE) -> 25.493333 | W27: =VLOOKUP(R27,BASE!$A:$M,13,FALSE) -> Production
A28: Quality Assurance | B28: 68.58 | C28: 68.58 | D28: 53.97 | E28: 101.13 | F28: =IFERROR(VLOOKUP(A28,$A$3:$C$19,2,FALSE),0) -> 111 | O28: =P28/$P$29 -> 0.082016546 | P28: =SUM(C28:N28) -> 334.68 | R28: 70000212 | S28: =VLOOKUP(R28,BASE!$A:$R,2,FALSE) -> Albert Vangu | T28: =VLOOKUP(R28,BASE!$A:$R,17,FALSE) -> 27.43 | U28: =VLOOKUP(R28,BASE!$A:$R,18,FALSE) -> 99.566603 | V28: =VLOOKUP(R28,BASE!$A:$R,15,FALSE) -> 18.666667 | W28: =VLOOKUP(R28,BASE!$A:$M,13,FALSE) -> Production
B29: =SUM(B22:B28) -> 535.97 | C29: =SUM(C22:C28) -> 599.97 | D29: =SUM(D22:D28) -> 1037.62 | E29: =SUM(E22:E28) -> 1191.07 | F29: =SUM(F22:F28) -> 1251.98 | G29: =SUM(G22:G28) -> 0 | H29: =SUM(H22:H28) -> 0 | I29: =SUM(I22:I28) -> 0 | ... N29: =SUM(N22:N28) -> 0 | P29: =SUM(C29:N29) -> 4080.64 | R29: 70000226 | S29: =VLOOKUP(R29,BASE!$A:$R,2,FALSE) -> Alidor Kankonde | T29: =VLOOKUP(R29,BASE!$A:$R,17,FALSE) -> 34.93 | U29: =VLOOKUP(R29,BASE!$A:$R,18,FALSE) -> 154.52987 | V29: =VLOOKUP(R29,BASE!$A:$R,15,FALSE) -> 16 | W29: =VLOOKUP(R29,BASE!$A:$M,13,FALSE) -> Production
R30: 70000052 | S30: =VLOOKUP(R30,BASE!$A:$R,2,FALSE) -> Simon Bayisa | T30: =VLOOKUP(R30,BASE!$A:$R,17,FALSE) -> 38.49 | U30: =VLOOKUP(R30,BASE!$A:$R,18,FALSE) -> 396.10708 | V30: =VLOOKUP(R30,BASE!$A:$R,15,FALSE) -> 7.3333333 | W30: =VLOOKUP(R30,BASE!$A:$M,13,FALSE) -> Engineering
A31: Value | B31: MAR | C31: APR | D31: MAY | E31: JUN | F31: JUL | G31: AUG | H31: SEP | I31: OCT | J31: NOV | K31: DEC | L31: JAN | M31: FEB | N31: MAR | O31: % | P31: Total | R31: 70000079 | S31: =VLOOKUP(R31,BASE!$A:$R,2,FALSE) -> Dinandi Mvumbi | T31: =VLOOKUP(R31,BASE!$A:$R,17,FALSE) -> 26.91 | U31: =VLOOKUP(R31,BASE!$A:$R,18,FALSE) -> 325.50294 | V31: =VLOOKUP(R31,BASE!$A:$R,15,FALSE) -> 20.083333 | W31: =VLOOKUP(R31,BASE!$A:$M,13,FALSE) -> Engineering
A32: CEC | B32: 0 | C32: 0 | D32: 240.38846 | E32: 0 | F32: =IFERROR(VLOOKUP(A32,$A$3:$C$19,3,FALSE),0) -> 0 | O32: =P32/$P$39 -> 0.0060270231 | P32: =SUM(C32:N32) -> 240.38846 | R32: 70000088 | S32: =VLOOKUP(R32,BASE!$A:$R,2,FALSE) -> Ovie Tulomba | T32: =VLOOKUP(R32,BASE!$A:$R,17,FALSE) -> 29.43 | U32: =VLOOKUP(R32,BASE!$A:$R,18,FALSE) -> 365.32908 | V32: =VLOOKUP(R32,BASE!$A:$R,15,FALSE) -> -1.6666667 | W32: =VLOOKUP(R32,BASE!$A:$M,13,FALSE) -> Engineering
A33: Engineering | B33: 3832.8804 | C33: 3807.7021 | D33: 5326.2197 | E33: 8020.6187 | F33: =IFERROR(VLOOKUP(A33,$A$3:$C$19,3,FALSE),0) -> 6262.8717 | O33: =P33/$P$39 -> 0.58712171 | P33: =SUM(C33:N33) -> 23417.412 | R33: 70000104 | S33: =VLOOKUP(R33,BASE!$A:$R,2,FALSE) -> Dieu Ngoma | T33: =VLOOKUP(R33,BASE!$A:$R,17,FALSE) -> 78.89 | U33: =VLOOKUP(R33,BASE!$A:$R,18,FALSE) -> 938.92511 | V33: =VLOOKUP(R33,BASE!$A:$R,15,FALSE) -> 26.17 | W33: =VLOOKUP(R33,BASE!$A:$M,13,FALSE) -> Engineering
A34: Mining | B34: 0 | C34: 513.25302 | D34: 402.2201 | E34: 586.04397 | F34: =IFERROR(VLOOKUP(A34,$A$3:$C$19,3,FALSE),0) -> 430.45051 | O34: =P34/$P$39 -> 0.048438321 | P34: =SUM(C34:N34) -> 1931.9676 | R34: 70000115 | S34: =VLOOKUP(R34,BASE!$A:$R,2,FALSE) -> Lundi Onosamba | T34: =VLOOKUP(R34,BASE!$A:$R,17,FALSE) -> 69.95 | U34: =VLOOKUP(R34,BASE!$A:$R,18,FALSE) -> 743.89931 | V34: =VLOOKUP(R34,BASE!$A:$R,15,FALSE) -> 22.92 | W34: =VLOOKUP(R34,BASE!$A:$M,13,FALSE) -> Engineering
A35: Optimization | B35: 0 | C35: 0 | D35: 45.85425 | E35: 0 | F35: =IFERROR(VLOOKUP(A35,$A$3:$C$19,3,FALSE),0) -> 0 | O35: =P35/$P$39 -> 0.0011496585 | P35: =SUM(C35:N35) -> 45.85425 | R35: 70000116 | S35: =VLOOKUP(R35,BASE!$A:$R,2,FALSE) -> Antoine Nzungu | T35: =VLOOKUP(R35,BASE!$A:$R,17,FALSE) -> 69.79 | U35: =VLOOKUP(R35,BASE!$A:$R,18,FALSE) -> 787.641 | V35: =VLOOKUP(R35,BASE!$A:$R,15,FALSE) -> 20.92 | W35: =VLOOKUP(R35,BASE!$A:$M,13,FALSE) -> Engineering
A36: Production | B36: 624.12695 | C36: 620.02704 | D36: 2296.8059 | E36: 1749.3284 | F36: =IFERROR(VLOOKUP(A36,$A$3:$C$19,3,FALSE),0) -> 3481.9248 | O36: =P36/$P$39 -> 0.20428894 | P36: =SUM(C36:N36) -> 8148.0862 | R36: 70000215 | S36: =VLOOKUP(R36,BASE!$A:$R,2,FALSE) -> Alphonse Bindama | T36: =VLOOKUP(R36,BASE!$A:$R,17,FALSE) -> 35.29 | U36: =VLOOKUP(R36,BASE!$A:$R,18,FALSE) -> 515.48235 | V36: =VLOOKUP(R36,BASE!$A:$R,15,FALSE) -> 26.416667 | W36: =VLOOKUP(R36,BASE!$A:$M,13,FALSE) -> Engineering
A37: Logistic | B37: 642.17358 | C37: 637.95512 | D37: 1084.987 | E37: 824.61975 | F37: =IFERROR(VLOOKUP(A37,$A$3:$C$19,3,FALSE),0) -> 716.59825 | O37: =P37/$P$39 -> 0.081839071 | P37: =SUM(C37:N37) -> 3264.1601 | R37: 70000216 | S37: =VLOOKUP(R37,BASE!$A:$R,2,FALSE) -> Patience Mansiamina | T37: =VLOOKUP(R37,BASE!$A:$R,17,FALSE) -> 51.17 | U37: =VLOOKUP(R37,BASE!$A:$R,18,FALSE) -> 608.58357 | V37: =VLOOKUP(R37,BASE!$A:$R,15,FALSE) -> 24.416667 | W37: =VLOOKUP(R37,BASE!$A:$M,13,FALSE) -> Engineering
A38: Quality Assurance | B38: 549.04538 | C38: 545.43868 | D38: 575.1223 | E38: 774.6259 | F38: =IFERROR(VLOOKUP(A38,$A$3:$C$19,3,FALSE),0) -> 942.05118 | O38: =P38/$P$39 -> 0.071135275 | P38: =SUM(C38:N38) -> 2837.2381 | R38: 70000227 | S38: =VLOOKUP(R38,BASE!$A:$R,2,FALSE) -> Dieu-Merci Ntunga | T38: =VLOOKUP(R38,BASE!$A:$R,17,FALSE) -> 4.03 | U38: =VLOOKUP(R38,BASE!$A:$R,18,FALSE) -> 36.981785 | V38: =VLOOKUP(R38,BASE!$A:$R,15,FALSE) -> 1.5033333 | W38: =VLOOKUP(R38,BASE!$A:$M,13,FALSE) -> Engineering
B39: =SUM(B32:B38) -> 5648.2263 | C39: =SUM(C32:C38) -> 6124.376 | D39: =SUM(D32:D38) -> 9971.5978 | E39: 11955.237 | F39: =SUM(F32:F38) -> 11833.896 | G39: =SUM(G32:G38) -> 0 | H39: =SUM(H32:H38) -> 0 | I39: =SUM(I32:I38) -> 0 | J39: =SUM(J32:J38) -> 0 | K39: =SUM(K32:K38) -> 0 | L39: =SUM(L32:L38) -> 0 | M39: =SUM(M32:M38) -> 0 | N39: =SUM(N32:N38) -> 0 | P39: =SUM(P32:P38) -> 39885.107 | R39: 70000283 | S39: =VLOOKUP(R39,BASE!$A:$R,2,FALSE) -> Declairck Nsilulu Ngimbi | T39: =VLOOKUP(R39,BASE!$A:$R,17,FALSE) -> 38.28 | U39: =VLOOKUP(R39,BASE!$A:$R,18,FALSE) -> 133.68629 | V39: =VLOOKUP(R39,BASE!$A:$R,15,FALSE) -> 7.047619 | W39: =VLOOKUP(R39,BASE!$A:$M,13,FALSE) -> Engineering
R40: 70000284 | S40: =VLOOKUP(R40,BASE!$A:$R,2,FALSE) -> Oxano Muntanda | T40: =VLOOKUP(R40,BASE!$A:$R,17,FALSE) -> 9.42 | U40: =VLOOKUP(R40,BASE!$A:$R,18,FALSE) -> 80.597907 | V40: =VLOOKUP(R40,BASE!$A:$R,15,FALSE) -> 10.952381 | W40: =VLOOKUP(R40,BASE!$A:$M,13,FALSE) -> Engineering
R41: 70000306 | S41: =VLOOKUP(R41,BASE!$A:$R,2,FALSE) -> Blanchard Muzo | T41: =VLOOKUP(R41,BASE!$A:$R,17,FALSE) -> 22.6 | U41: =VLOOKUP(R41,BASE!$A:$R,18,FALSE) -> 124.52651 | V41: =VLOOKUP(R41,BASE!$A:$R,15,FALSE) -> 5.3225806 | W41: =VLOOKUP(R41,BASE!$A:$M,13,FALSE) -> Engineering
C42: APR | D42: MAY | E42: JUN | F42: JUL | G42: AUG | H42: SEP | I42: OCT | J42: NOV | K42: DEC | L42: JAN | M42: FEB | N42: MAR | R42: 70000309 | S42: =VLOOKUP(R42,BASE!$A:$R,2,FALSE) -> Junior Nlandu | T42: =VLOOKUP(R42,BASE!$A:$R,17,FALSE) -> 45.6 | U42: =VLOOKUP(R42,BASE!$A:$R,18,FALSE) -> 332.375 | V42: =VLOOKUP(R42,BASE!$A:$R,15,FALSE) -> 3.2388889 | W42: =VLOOKUP(R42,BASE!$A:$M,13,FALSE) -> Engineering
A43: Actual | C43: =C39 -> 6124.376 | D43: =D39 -> 9971.5978 | E43: =E39 -> 11955.237 | F43: =F39 -> 11833.896 | G43: =G39 -> 0 | H43: =H39 -> 0 | I43: =I39 -> 0 | J43: =J39 -> 0 | ... N43: =N39 -> 0 | O43: =SUM(C43:N43) -> 39885.107 | R43: 70000171 | S43: =VLOOKUP(R43,BASE!$A:$R,2,FALSE) -> CHRISTIAN KUABI | T43: =VLOOKUP(R43,BASE!$A:$R,17,FALSE) -> 2.58 | U43: =VLOOKUP(R43,BASE!$A:$R,18,FALSE) -> 21.264341 | V43: =VLOOKUP(R43,BASE!$A:$R,15,FALSE) -> 14.833333 | W43: =VLOOKUP(R43,BASE!$A:$M,13,FALSE) -> Production
A44: Budget | C44: 19182.83 | D44: 19182.83 | E44: 19182.83 | F44: 19182.83 | G44: 19182.83 | H44: 19182.83 | I44: 19182.83 | J44: 19182.83 | K44: 19182.83 | L44: 19182.83 | M44: 19182.83 | N44: 19182.83 | R44: 70000229 | S44: =VLOOKUP(R44,BASE!$A:$R,2,FALSE) -> Guylain Wampangulua | T44: =VLOOKUP(R44,BASE!$A:$R,17,FALSE) -> 61.73 | U44: =VLOOKUP(R44,BASE!$A:$R,18,FALSE) -> 188.14641 | V44: =VLOOKUP(R44,BASE!$A:$R,15,FALSE) -> 24.916667 | W44: =VLOOKUP(R44,BASE!$A:$M,13,FALSE) -> Engineering
R45: 70000232 | S45: =VLOOKUP(R45,BASE!$A:$R,2,FALSE) -> Lucio Da Conceição | T45: =VLOOKUP(R45,BASE!$A:$R,17,FALSE) -> 15.41 | U45: =VLOOKUP(R45,BASE!$A:$R,18,FALSE) -> 165.97458 | V45: =VLOOKUP(R45,BASE!$A:$R,15,FALSE) -> 27.544444 | W45: =VLOOKUP(R45,BASE!$A:$M,13,FALSE) -> Engineering
R46: 70000015 | S46: =VLOOKUP(R46,BASE!$A:$R,2,FALSE) -> LUZOLO NSEMBOLO | T46: =VLOOKUP(R46,BASE!$A:$R,17,FALSE) -> 42.2 | U46: =VLOOKUP(R46,BASE!$A:$R,18,FALSE) -> 519.11275 | V46: =VLOOKUP(R46,BASE!$A:$R,15,FALSE) -> 20.843333 | W46: =VLOOKUP(R46,BASE!$A:$M,13,FALSE) -> Engineering
R47: 70000241 | S47: =VLOOKUP(R47,BASE!$A:$R,2,FALSE) -> Jean Biawila | T47: =VLOOKUP(R47,BASE!$A:$R,17,FALSE) -> 29.11 | U47: =VLOOKUP(R47,BASE!$A:$R,18,FALSE) -> 243.10087 | V47: =VLOOKUP(R47,BASE!$A:$R,15,FALSE) -> 24.5 | W47: =VLOOKUP(R47,BASE!$A:$M,13,FALSE) -> Logistic
R48: 70000255 | S48: =VLOOKUP(R48,BASE!$A:$R,2,FALSE) -> Jonas LINGOMA | T48: =VLOOKUP(R48,BASE!$A:$R,17,FALSE) -> 36.46 | U48: =VLOOKUP(R48,BASE!$A:$R,18,FALSE) -> 473.49738 | V48: =VLOOKUP(R48,BASE!$A:$R,15,FALSE) -> 15 | W48: =VLOOKUP(R48,BASE!$A:$M,13,FALSE) -> Logistic
R49: 70000043 | S49: =VLOOKUP(R49,BASE!$A:$R,2,FALSE) -> EDDO MAKIVOVI | T49: =VLOOKUP(R49,BASE!$A:$R,17,FALSE) -> 7 | U49: =VLOOKUP(R49,BASE!$A:$R,18,FALSE) -> 41.582067 | V49: =VLOOKUP(R49,BASE!$A:$R,15,FALSE) -> 19.17 | W49: =VLOOKUP(R49,BASE!$A:$M,13,FALSE) -> Mining
R50: 70000097 | S50: =VLOOKUP(R50,BASE!$A:$R,2,FALSE) -> Masudi Nkosi | T50: =VLOOKUP(R50,BASE!$A:$R,17,FALSE) -> 13 | U50: =VLOOKUP(R50,BASE!$A:$R,18,FALSE) -> 42.609866 | V50: =VLOOKUP(R50,BASE!$A:$R,15,FALSE) -> 19.083333 | W50: =VLOOKUP(R50,BASE!$A:$M,13,FALSE) -> Mining
R51: 70000129 | S51: =VLOOKUP(R51,BASE!$A:$R,2,FALSE) -> RACHIE DIAWAWANA | T51: =VLOOKUP(R51,BASE!$A:$R,17,FALSE) -> 4.3 | U51: =VLOOKUP(R51,BASE!$A:$R,18,FALSE) -> 14.91477 | V51: =VLOOKUP(R51,BASE!$A:$R,15,FALSE) -> 11 | W51: =VLOOKUP(R51,BASE!$A:$M,13,FALSE) -> Mining
R52: 70000233 | S52: =VLOOKUP(R52,BASE!$A:$R,2,FALSE) -> Hassan Kananga | T52: =VLOOKUP(R52,BASE!$A:$R,17,FALSE) -> 6 | U52: =VLOOKUP(R52,BASE!$A:$R,18,FALSE) -> 61.700199 | V52: =VLOOKUP(R52,BASE!$A:$R,15,FALSE) -> 8.5444444 | W52: =VLOOKUP(R52,BASE!$A:$M,13,FALSE) -> Mining
R53: 70000124 | S53: =VLOOKUP(R53,BASE!$A:$R,2,FALSE) -> Longo Zola | T53: =VLOOKUP(R53,BASE!$A:$R,17,FALSE) -> 21 | U53: =VLOOKUP(R53,BASE!$A:$R,18,FALSE) -> 246.06878 | V53: =VLOOKUP(R53,BASE!$A:$R,15,FALSE) -> 31.17 | W53: =VLOOKUP(R53,BASE!$A:$M,13,FALSE) -> Mining
R54: 70000013 | S54: =VLOOKUP(R54,BASE!$A:$R,2,FALSE) -> KUASA KINSIONA | T54: =VLOOKUP(R54,BASE!$A:$R,17,FALSE) -> 6 | U54: =VLOOKUP(R54,BASE!$A:$R,18,FALSE) -> 23.574831 | V54: =VLOOKUP(R54,BASE!$A:$R,15,FALSE) -> 11.5 | W54: =VLOOKUP(R54,BASE!$A:$M,13,FALSE) -> Mining

Sheet overtime_base
A1: Employee Last Name | B1: Init. | C1: Employee Number | D1: Org. Unit | E1: Component | F1: Units | G1: Component Value
A2: Nlandu | B2: E | C2: 70000076 | D2: =VLOOKUP(C2,[1]Headcount_Kiesse!$A$19:$N$193,13,FALSE) -> Quality Assurance | E2: Heures supplémentaires x 1.3 du taux de base | F2: 2 | G2: 25265.39 | J2: Row Labels | K2: Sum of Units | L2: Sum of Component Value | N2: Employees with recorded hours | O2: =COUNTA(_xlfn.UNIQUE(C2:C111)) -> 52
A3: Nlandu | B3: E | C3: 70000076 | D3: =VLOOKUP(C3,[1]Headcount_Kiesse!$A$19:$N$193,13,FALSE) -> Quality Assurance | E3: Heures supplémentaires x 1.6 du taux de base | F3: 0.34 | G3: 5286.3 | J3: 70000013 | K3: 6 | L3: 54410.71 | N3: % sur le nombre des employés | O3: =O2/175 -> 0.29714286
A4: Nlandu | B4: E | C4: 70000076 | D4: =VLOOKUP(C4,[1]Headcount_Kiesse!$A$19:$N$193,13,FALSE) -> Quality Assurance | E4: Heures supplémentaires x 2.0 du taux de base | F4: 19.4 | G4: 377037.32 | J4: 70000015 | K4: 42.2 | L4: 1198112.2 | N4: Total Overtime | O4: =F112 -> 1251.98
A5: Samba | B5: C | C5: 70000077 | D5: =VLOOKUP(C5,[1]Headcount_Kiesse!$A$19:$N$193,13,FALSE) -> Quality Assurance | E5: Heures supplémentaires x 2.0 du taux de base | F5: 3.03 | G5: 36233.72 | J5: 70000026 | K5: 15.71 | L5: 713478.67 | N5: Average hours | O5: =O4/O2 -> 24.076538
A6: Nsilu | B6: N | C6: 70000080 | D6: =VLOOKUP(C6,[1]Headcount_Kiesse!$A$19:$N$193,13,FALSE) -> Quality Assurance | E6: Heures supplémentaires x 2.0 du taux de base | F6: 18.81 | G6: 328443.85 | J6: 70000029 | K6: 14.74 | L6: 812554.84 | N6: Total cost | O6: =G113 -> 11833.896
A7: Tandu | B7: B | C7: 70000081 | D7: =VLOOKUP(C7,[1]Headcount_Kiesse!$A$19:$N$193,13,FALSE) -> Quality Assurance | E7: Heures supplémentaires x 2.0 du taux de base | F7: 9.05 | G7: 159684.17 | J7: 70000043 | K7: 7 | L7: 95971.41 | N7: Average cost per employee | O7: =O6/O2 -> 227.57493
A8: Musako | B8: M | C8: 70000083 | D8: =VLOOKUP(C8,[1]Headcount_Kiesse!$A$19:$N$193,13,FALSE) -> Quality Assurance | E8: Heures supplémentaires x 2.0 du taux de base | F8: 10.21 | G8: 406194.45 | J8: 70000052 | K8: 38.49 | L8: 914215.14 | N8: Overtime represents
A9: Mvilambi | B9: DM | C9: 70000084 | D9: =VLOOKUP(C9,[1]Headcount_Kiesse!$A$19:$N$193,13,FALSE) -> Quality Assurance | E9: Heures supplémentaires x 2.0 du taux de base | F9: 8.57 | G9: 94177.33 | J9: 70000056 | K9: 8.39 | L9: 112006.54
A10: Kamanda | B10: SNK | C10: 70000210 | D10: =VLOOKUP(C10,[1]Headcount_Kiesse!$A$19:$N$193,13,FALSE) -> Quality Assurance | E10: Heures supplémentaires x 2.0 du taux de base | F10: 15.43 | G10: 408720.41 | J10: 70000057 | K10: 18 | L10: 435585.52
A11: Mawete | B11: ME | C11: 70000276 | D11: =VLOOKUP(C11,[1]Headcount_Kiesse!$A$19:$N$193,13,FALSE) -> Quality Assurance | E11: Heures supplémentaires x 2.0 du taux de base | F11: 24.16 | G11: 333211.18 | J11: 70000059 | K11: 22 | L11: 554383.51
A12: Bavibidila | B12: G | C12: 70000069 | D12: =VLOOKUP(C12,[1]Headcount_Kiesse!$A$19:$N$193,13,FALSE) -> Production | E12: Heures supplémentaires x 2.0 du taux de base | F12: 3.17 | G12: 31391.41 | J12: 70000061 | K12: 22 | L12: 584129.81
A13: Bitutu | B13: E | C13: 70000070 | D13: =VLOOKUP(C13,[1]Headcount_Kiesse!$A$19:$N$193,13,FALSE) -> Production | E13: Heures supplémentaires x 2.0 du taux de base | F13: 6 | G13: 59635.61 | J13: 70000063 | K13: 41.34 | L13: 1424030.8
A14: Mutambayi | B14: K | C14: 70000026 | D14: =VLOOKUP(C14,[1]Headcount_Kiesse!$A$19:$N$193,13,FALSE) -> Production | E14: Heures supplémentaires x 1.3 du taux de base | F14: 2 | G14: 68858.37 | J14: 70000064 | K14: 6.11 | L14: 193922.55
A15: Mutambayi | B15: K | C15: 70000026 | D15: =VLOOKUP(C15,[1]Headcount_Kiesse!$A$19:$N$193,13,FALSE) -> Production | E15: Heures supplémentaires x 1.6 du taux de base | F15: 7.7 | G15: 326282.75 | J15: 70000069 | K15: 3.17 | L15: 31391.41
A16: Mutambayi | B16: K | C16: 70000026 | D16: =VLOOKUP(C16,[1]Headcount_Kiesse!$A$19:$N$193,13,FALSE) -> Production | E16: Heures supplémentaires x 2.0 du taux de base | F16: 6.01 | G16: 318337.55 | J16: 70000070 | K16: 6 | L16: 59635.61
A17: Muanda | B17: J | C17: 70000063 | D17: =VLOOKUP(C17,[1]Headcount_Kiesse!$A$19:$N$193,13,FALSE) -> Production | E17: Heures supplémentaires x 1.3 du taux de base | F17: 4 | G17: 100408.96 | J17: 70000076 | K17: 21.74 | L17: 407589.01
A18: Muanda | B18: J | C18: 70000063 | D18: =VLOOKUP(C18,[1]Headcount_Kiesse!$A$19:$N$193,13,FALSE) -> Production | E18: Heures supplémentaires x 1.6 du taux de base | F18: 15.33 | G18: 473621.35 | J18: 70000077 | K18: 3.03 | L18: 36233.72
A19: Muanda | B19: J | C19: 70000063 | D19: =VLOOKUP(C19,[1]Headcount_Kiesse!$A$19:$N$193,13,FALSE) -> Production | E19: Heures supplémentaires x 2.0 du taux de base | F19: 22.01 | G19: 850000.49 | J19: 70000079 | K19: 26.91 | L19: 751260.78
A20: Kalunga | B20: R | C20: 70000064 | D20: =VLOOKUP(C20,[1]Headcount_Kiesse!$A$19:$N$193,13,FALSE) -> Production | E20: Heures supplémentaires x 2.0 du taux de base | F20: 6.11 | G20: 193922.55 | J20: 70000080 | K20: 18.81 | L20: 328443.85
... A55: Mvumbi | B55: D | C55: 70000079 | D55: =VLOOKUP(C55,[1]Headcount_Kiesse!$A$19:$N$193,13,FALSE) -> Engineering | E55: Heures supplémentaires x 1.3 du taux de base | F55: 0.32 | G55: 5831.12 | J55: Grand Total | K55: 1251.98 | L55: 27312633
A56: Mvumbi | B56: D | C56: 70000079 | D56: =VLOOKUP(C56,[1]Headcount_Kiesse!$A$19:$N$193,13,FALSE) -> Engineering | E56: Heures supplémentaires x 2.0 du taux de base | F56: 26.59 | G56: 745429.66
A57: Tulomba | B57: O | C57: 70000088 | D57: =VLOOKUP(C57,[1]Headcount_Kiesse!$A$19:$N$193,13,FALSE) -> Engineering | E57: Heures supplémentaires x 1.3 du taux de base | F57: 2 | G57: 38380.02
A58: Tulomba | B58: O | C58: 70000088 | D58: =VLOOKUP(C58,[1]Headcount_Kiesse!$A$19:$N$193,13,FALSE) -> Engineering | E58: Heures supplémentaires x 1.6 du taux de base | F58: 0.85 | G58: 20075.7
A59: Tulomba | B59: O | C59: 70000088 | D59: =VLOOKUP(C59,[1]Headcount_Kiesse!$A$19:$N$193,13,FALSE) -> Engineering | E59: Heures supplémentaires x 2.0 du taux de base | F59: 26.58 | G59: 784723.8
A60: Ngoma | B60: D | C60: 70000104 | D60: =VLOOKUP(C60,[1]Headcount_Kiesse!$A$19:$N$193,13,FALSE) -> Engineering | E60: Heures supplémentaires x 1.3 du taux de base | F60: 6 | G60: 125627.33
A61: Ngoma | B61: D | C61: 70000104 | D61: =VLOOKUP(C61,[1]Headcount_Kiesse!$A$19:$N$193,13,FALSE) -> Engineering | E61: Heures supplémentaires x 1.6 du taux de base | F61: 47.58 | G61: 1226122.7
A62: Ngoma | B62: D | C62: 70000104 | D62: =VLOOKUP(C62,[1]Headcount_Kiesse!$A$19:$N$193,13,FALSE) -> Engineering | E62: Heures supplémentaires x 2.0 du taux de base | F62: 25.31 | G62: 815289.13
A63: Onosamba | B63: L | C63: 70000115 | D63: =VLOOKUP(C63,[1]Headcount_Kiesse!$A$19:$N$193,13,FALSE) -> Engineering | E63: Heures supplémentaires x 1.3 du taux de base | F63: 5.87 | G63: 108434.48
A64: Onosamba | B64: L | C64: 70000115 | D64: =VLOOKUP(C64,[1]Headcount_Kiesse!$A$19:$N$193,13,FALSE) -> Engineering | E64: Heures supplémentaires x 1.6 du taux de base | F64: 37.41 | G64: 850537.88
A65: Onosamba | B65: L | C65: 70000115 | D65: =VLOOKUP(C65,[1]Headcount_Kiesse!$A$19:$N$193,13,FALSE) -> Engineering | E65: Heures supplémentaires x 2.0 du taux de base | F65: 26.67 | G65: 757947.24
A66: Nzungu | B66: A | C66: 70000116 | D66: =VLOOKUP(C66,[1]Headcount_Kiesse!$A$19:$N$193,13,FALSE) -> Engineering | E66: Heures supplémentaires x 1.3 du taux de base | F66: 4 | G66: 76410.96
A67: Nzungu | B67: A | C67: 70000116 | D67: =VLOOKUP(C67,[1]Headcount_Kiesse!$A$19:$N$193,13,FALSE) -> Engineering | E67: Heures supplémentaires x 1.6 du taux de base | F67: 32.67 | G67: 768106.44
... A111: KINSIONA | B111: K | C111: 70000013 | D111: =VLOOKUP(C111,[1]Headcount_Kiesse!$A$19:$N$193,13,FALSE) -> Mining | E111: Heures supplémentaires x 1.6 du taux de base | F111: 4 | G111: 38692.06
F112: =SUM(F2:F111) -> 1251.98 | G112: =SUM(G2:G111) -> 27312633
G113: =G112/2308 -> 11833.896
G114: =G113/52 -> 227.57493

Sheet leavebalances_base
A1: Last Name | B1: First Name | D1: Emp. No. | E1: Emp Number | F1: First Name | G1: Last Name | H1: Birth Date | I1: Gender | J1: Nationality | K1: Employment Date | L1: Position | O1: Grade | P1: Age | Q1: Length of Service | R1: Cost Centre | S1: Department | T1: Leave Type | U1: Leave Description | V1: Service Length Description | W1: Yrs of Service | X1: Start Date | Y1: Opening Balance | Z1: Accrual | AA1: Taken/Adjusted | AB1: Forfeited | AC1: Closing Balance | AD1: Value | AE1: Days to expire/carry over | AF1: Expiry/Carry over month
A3: KINSIONA | B3: KUASA | D3: 70000013 | E3: 70000013 | F3: KUASA | G3: KINSIONA | H3: 30277 | I3: Male | J3: Congo | K3: 42240 | L3: Drilling Operator | O3: B2 | P3: 43 | Q3: 10 | R3: KQ1010-Drilling & Blasting | S3: Mining | T3: Annual | U3: Annual Leave | V3: 23 days 3 to 6 years | W3: 10 | X3: 45018 | Y3: 9.5833333 | Z3: 1.9166667 | AA3: 0 | AB3: 0 | AC3: 11.5 | AD3: 980421.92
A4: KINSIONA | B4: KUASA | D4: 70000013 | E4: 70000013 | F4: KUASA | G4: KINSIONA | H4: 30277 | I4: Male | J4: Congo | K4: 42240 | L4: Drilling Operator | O4: B2 | P4: 43 | Q4: 10 | R4: KQ1010-Drilling & Blasting | S4: Mining | T4: Sick | U4: conge de maladie | X4: 45018 | Y4: 180 | Z4: 0 | AA4: 0 | AB4: 0 | AC4: 180 | AD4: 15345734 | AE4: 180 | AF4: 46357
A5: KINSIONA | B5: KUASA | D5: 70000013 | E5: 70000013 | F5: KUASA | G5: KINSIONA | H5: 30277 | I5: Male | J5: Congo | K5: 42240 | L5: Drilling Operator | O5: B2 | P5: 43 | Q5: 10 | R5: KQ1010-Drilling & Blasting | S5: Mining | T5: Special | U5: Circumstance Leave | X5: 45018 | Y5: 15 | Z5: 0 | AA5: 0 | AB5: 0 | AC5: 15 | AD5: 1278811.2 | AE5: 15 | AF5: 46357
A6: KINSIONA | B6: KUASA | D6: 70000013 | E6: 70000013 | F6: KUASA | G6: KINSIONA | H6: 30277 | I6: Male | J6: Congo | K6: 42240 | L6: Drilling Operator | O6: B2 | P6: 43 | Q6: 10 | R6: KQ1010-Drilling & Blasting | S6: Mining | T6: Special | U6: Maternity leave | X6: 45018 | Y6: 98 | Z6: 0 | AA6: 0 | AB6: 0 | AC6: 98 | AD6: 8354899.9 | AE6: 98 | AF6: 46357
A7: KINSIONA | B7: KUASA | D7: 70000013 | E7: 70000013 | F7: KUASA | G7: KINSIONA | H7: 30277 | I7: Male | J7: Congo | K7: 42240 | L7: Drilling Operator | O7: B2 | P7: 43 | Q7: 10 | R7: KQ1010-Drilling & Blasting | S7: Mining | T7: Special | U7: Paternity Leave | X7: 45018 | Y7: 2 | Z7: 0 | AA7: 0 | AB7: 0 | AC7: 2 | AD7: 170508.16 | AE7: 2 | AF7: 46357
A8: KINSIONA | B8: KUASA | D8: 70000013 | E8: 70000013 | F8: KUASA | G8: KINSIONA | H8: 30277 | I8: Male | J8: Congo | K8: 42240 | L8: Drilling Operator | O8: B2 | P8: 43 | Q8: 10 | R8: KQ1010-Drilling & Blasting | S8: Mining | T8: Special | U8: Special Leave | X8: 45018 | Y8: 5 | Z8: 0 | AA8: 0 | AB8: 0 | AC8: 5 | AD8: 426270.4 | AE8: 5 | AF8: 46357
A9: KINSIONA | B9: KUASA | D9: 70000013 | E9: 70000013 | F9: KUASA | G9: KINSIONA | H9: 30277 | I9: Male | J9: Congo | K9: 42240 | L9: Drilling Operator | O9: B2 | P9: 43 | Q9: 10 | R9: KQ1010-Drilling & Blasting | S9: Mining | T9: Special | U9: Unpaid leave | X9: 45018 | Y9: 0.5 | Z9: 0.08333333 | AA9: 0 | AB9: 0 | AC9: 0.58333333 | AD9: 49731.547 | AE9: 0.58 | AF9: 46357
A10: NZAZI | B10: TOUBI | D10: 70000042 | E10: 70000042 | F10: TOUBI | G10: NZAZI | H10: 25820 | I10: Male | J10: Congo | K10: 42499 | L10: Drilling Operator | O10: B2 | P10: 55 | Q10: 10 | R10: KQ1010-Drilling & Blasting | S10: Mining | T10: Annual | U10: Annual Leave | V10: 23 days 3 to 6 years | W10: 10 | X10: 45018 | Y10: 8.5866667 | Z10: 1.9166667 | AA10: 0 | AB10: 0 | AC10: 10.503333 | AD10: 761851.62
A11: NZAZI | B11: TOUBI | D11: 70000042 | E11: 70000042 | F11: TOUBI | G11: NZAZI | H11: 25820 | I11: Male | J11: Congo | K11: 42499 | L11: Drilling Operator | O11: B2 | P11: 55 | Q11: 10 | R11: KQ1010-Drilling & Blasting | S11: Mining | T11: Sick | U11: conge de maladie | X11: 45018 | Y11: 180 | Z11: 0 | AA11: 0 | AB11: 0 | AC11: 180 | AD11: 13056169 | AE11: 180 | AF11: 46357
A12: NZAZI | B12: TOUBI | D12: 70000042 | E12: 70000042 | F12: TOUBI | G12: NZAZI | H12: 25820 | I12: Male | J12: Congo | K12: 42499 | L12: Drilling Operator | O12: B2 | P12: 55 | Q12: 10 | R12: KQ1010-Drilling & Blasting | S12: Mining | T12: Special | U12: Circumstance Leave | X12: 45018 | Y12: 15 | Z12: 0 | AA12: 0 | AB12: 0 | AC12: 15 | AD12: 1088014.1 | AE12: 15 | AF12: 46357
A13: NZAZI | B13: TOUBI | D13: 70000042 | E13: 70000042 | F13: TOUBI | G13: NZAZI | H13: 25820 | I13: Male | J13: Congo | K13: 42499 | L13: Drilling Operator | O13: B2 | P13: 55 | Q13: 10 | R13: KQ1010-Drilling & Blasting | S13: Mining | T13: Special | U13: Maternity leave | X13: 45018 | Y13: 98 | Z13: 0 | AA13: 0 | AB13: 0 | AC13: 98 | AD13: 7108358.5 | AE13: 98 | AF13: 46357
A14: NZAZI | B14: TOUBI | D14: 70000042 | E14: 70000042 | F14: TOUBI | G14: NZAZI | H14: 25820 | I14: Male | J14: Congo | K14: 42499 | L14: Drilling Operator | O14: B2 | P14: 55 | Q14: 10 | R14: KQ1010-Drilling & Blasting | S14: Mining | T14: Special | U14: Paternity Leave | X14: 45018 | Y14: 2 | Z14: 0 | AA14: 0 | AB14: 0 | AC14: 2 | AD14: 145068.54 | AE14: 2 | AF14: 46357
A15: NZAZI | B15: TOUBI | D15: 70000042 | E15: 70000042 | F15: TOUBI | G15: NZAZI | H15: 25820 | I15: Male | J15: Congo | K15: 42499 | L15: Drilling Operator | O15: B2 | P15: 55 | Q15: 10 | R15: KQ1010-Drilling & Blasting | S15: Mining | T15: Special | U15: Special Leave | X15: 45018 | Y15: 5 | Z15: 0 | AA15: 0 | AB15: 0 | AC15: 5 | AD15: 362671.35 | AE15: 5 | AF15: 46357
A16: NZAZI | B16: TOUBI | D16: 70000042 | E16: 70000042 | F16: TOUBI | G16: NZAZI | H16: 25820 | I16: Male | J16: Congo | K16: 42499 | L16: Drilling Operator | O16: B2 | P16: 55 | Q16: 10 | R16: KQ1010-Drilling & Blasting | S16: Mining | T16: Special | U16: Unpaid leave | X16: 45018 | Y16: 0.5 | Z16: 0.08333333 | AA16: 0 | AB16: 0 | AC16: 0.58333333 | AD16: 42311.658 | AE16: 0.58 | AF16: 46357
A17: Nkosi | B17: Masudi | D17: 70000097 | E17: 70000097 | F17: Masudi | G17: Nkosi | H17: 32060 | I17: Male | J17: Congo | K17: 42679 | L17: Mining Mobile Equipment Operator | O17: B2 | P17: 38 | Q17: 9 | R17: KQ1910-Mining General | S17: Mining | T17: Annual | U17: Annual Leave | V17: 23 days 3 to 6 years | W17: 9 | X17: 45018 | Y17: 17.166667 | Z17: 1.9166667 | AA17: 0 | AB17: 0 | AC17: 19.083333 | AD17: 1392317.4
A18: Nkosi | B18: Masudi | D18: 70000097 | E18: 70000097 | F18: Masudi | G18: Nkosi | H18: 32060 | I18: Male | J18: Congo | K18: 42679 | L18: Mining Mobile Equipment Operator | O18: B2 | P18: 38 | Q18: 9 | R18: KQ1910-Mining General | S18: Mining | T18: Sick | U18: conge de maladie | X18: 45018 | Y18: 180 | Z18: 0 | AA18: 0 | AB18: 0 | AC18: 180 | AD18: 13132775 | AE18: 180 | AF18: 46357
A19: Nkosi | B19: Masudi | D19: 70000097 | E19: 70000097 | F19: Masudi | G19: Nkosi | H19: 32060 | I19: Male | J19: Congo | K19: 42679 | L19: Mining Mobile Equipment Operator | O19: B2 | P19: 38 | Q19: 9 | R19: KQ1910-Mining General | S19: Mining | T19: Special | U19: Circumstance Leave | X19: 45018 | Y19: 15 | Z19: 0 | AA19: 0 | AB19: 0 | AC19: 15 | AD19: 1094397.9 | AE19: 15 | AF19: 46357
A20: Nkosi | B20: Masudi | D20: 70000097 | E20: 70000097 | F20: Masudi | G20: Nkosi | H20: 32060 | I20: Male | J20: Congo | K20: 42679 | L20: Mining Mobile Equipment Operator | O20: B2 | P20: 38 | Q20: 9 | R20: KQ1910-Mining General | S20: Mining | T20: Special | U20: Maternity leave | X20: 45018 | Y20: 98 | Z20: 0 | AA20: 0 | AB20: 0 | AC20: 98 | AD20: 7150066.4 | AE20: 98 | AF20: 46357
A21: Nkosi | B21: Masudi | D21: 70000097 | E21: 70000097 | F21: Masudi | G21: Nkosi | H21: 32060 | I21: Male | J21: Congo | K21: 42679 | L21: Mining Mobile Equipment Operator | O21: B2 | P21: 38 | Q21: 9 | R21: KQ1910-Mining General | S21: Mining | T21: Special | U21: Paternity Leave | X21: 45018 | Y21: 2 | Z21: 0 | AA21: 0 | AB21: 0 | AC21: 2 | AD21: 145919.72 | AE21: 2 | AF21: 46357
A22: Nkosi | B22: Masudi | D22: 70000097 | E22: 70000097 | F22: Masudi | G22: Nkosi | H22: 32060 | I22: Male | J22: Congo | K22: 42679 | L22: Mining Mobile Equipment Operator | O22: B2 | P22: 38 | Q22: 9 | R22: KQ1910-Mining General | S22: Mining | T22: Special | U22: Special Leave | X22: 45018 | Y22: 5 | Z22: 0 | AA22: 0 | AB22: 0 | AC22: 5 | AD22: 364799.31 | AE22: 5 | AF22: 46357
A23: Nkosi | B23: Masudi | D23: 70000097 | E23: 70000097 | F23: Masudi | G23: Nkosi | H23: 32060 | I23: Male | J23: Congo | K23: 42679 | L23: Mining Mobile Equipment Operator | O23: B2 | P23: 38 | Q23: 9 | R23: KQ1910-Mining General | S23: Mining | T23: Special | U23: Unpaid leave | X23: 45018 | Y23: -4 | Z23: 0.08333333 | AA23: 0 | AB23: 0 | AC23: -3.9166667 | AD23: -285759.46 | AE23: 0 | AF23: 46357
A24: Wasolokele | B24: Lumanisa | D24: 70000102 | E24: 70000102 | F24: Lumanisa | G24: Wasolokele | H24: 30322 | I24: Male | J24: Congo | K24: 42679 | L24: Drilling Operator | O24: B1 | P24: 43 | Q24: 9 | R24: KQ1010-Drilling & Blasting | S24: Mining | T24: Annual | U24: Annual Leave | V24: 23 days 3 to 6 years | W24: 9 | X24: 45018 | Y24: 28.416667 | Z24: 1.9166667 | AA24: -23 | AB24: 0 | AC24: 7.3333333 | AD24: 510467.34
A25: Wasolokele | B25: Lumanisa | D25: 70000102 | E25: 70000102 | F25: Lumanisa | G25: Wasolokele | H25: 30322 | I25: Male | J25: Congo | K25: 42679 | L25: Drilling Operator | O25: B1 | P25: 43 | Q25: 9 | R25: KQ1010-Drilling & Blasting | S25: Mining | T25: Sick | U25: conge de maladie | X25: 45018 | Y25: 180 | Z25: 0 | AA25: 0 | AB25: 0 | AC25: 180 | AD25: 12529653 | AE25: 180 | AF25: 46357
A26: Wasolokele | B26: Lumanisa | D26: 70000102 | E26: 70000102 | F26: Lumanisa | G26: Wasolokele | H26: 30322 | I26: Male | J26: Congo | K26: 42679 | L26: Drilling Operator | O26: B1 | P26: 43 | Q26: 9 | R26: KQ1010-Drilling & Blasting | S26: Mining | T26: Special | U26: Circumstance Leave | X26: 45018 | Y26: 15 | Z26: 0 | AA26: 0 | AB26: 0 | AC26: 15 | AD26: 1044137.7 | AE26: 15 | AF26: 46357
A27: Wasolokele | B27: Lumanisa | D27: 70000102 | E27: 70000102 | F27: Lumanisa | G27: Wasolokele | H27: 30322 | I27: Male | J27: Congo | K27: 42679 | L27: Drilling Operator | O27: B1 | P27: 43 | Q27: 9 | R27: KQ1010-Drilling & Blasting | S27: Mining | T27: Special | U27: Maternity leave | X27: 45018 | Y27: 98 | Z27: 0 | AA27: 0 | AB27: 0 | AC27: 98 | AD27: 6821699.9 | AE27: 98 | AF27: 46357
A28: Wasolokele | B28: Lumanisa | D28: 70000102 | E28: 70000102 | F28: Lumanisa | G28: Wasolokele | H28: 30322 | I28: Male | J28: Congo | K28: 42679 | L28: Drilling Operator | O28: B1 | P28: 43 | Q28: 9 | R28: KQ1010-Drilling & Blasting | S28: Mining | T28: Special | U28: Paternity Leave | X28: 45018 | Y28: 2 | Z28: 0 | AA28: 0 | AB28: 0 | AC28: 2 | AD28: 139218.37 | AE28: 2 | AF28: 46357
A29: Wasolokele | B29: Lumanisa | D29: 70000102 | E29: 70000102 | F29: Lumanisa | G29: Wasolokele | H29: 30322 | I29: Male | J29: Congo | K29: 42679 | L29: Drilling Operator | O29: B1 | P29: 43 | Q29: 9 | R29: KQ1010-Drilling & Blasting | S29: Mining | T29: Special | U29: Special Leave | X29: 45018 | Y29: 5 | Z29: 0 | AA29: 0 | AB29: 0 | AC29: 5 | AD29: 348045.92 | AE29: 5 | AF29: 46357
A30: Wasolokele | B30: Lumanisa | D30: 70000102 | E30: 70000102 | F30: Lumanisa | G30: Wasolokele | H30: 30322 | I30: Male | J30: Congo | K30: 42679 | L30: Drilling Operator | O30: B1 | P30: 43 | Q30: 9 | R30: KQ1010-Drilling & Blasting | S30: Mining | T30: Special | U30: Unpaid leave | X30: 45018 | Y30: 0.5 | Z30: 0.08333333 | AA30: 0 | AB30: 0 | AC30: 0.58333333 | AD30: 40605.357 | AE30: 0.58 | AF30: 46357
A31: Zola | B31: Longo | D31: 70000124 | E31: 70000124 | F31: Longo | G31: Zola | H31: 28108 | I31: Male | J31: Congo | K31: 42240 | L31: Shift Supervisor | O31: C3 | P31: 49 | Q31: 10 | R31: KQ1023-Hauling | S31: Mining | T31: Annual | U31: Annual Leave | V31: 25 days 12 to 15 years | W31: 10 | X31: 45018 | Y31: 29.086667 | Z31: 2.0833333 | AA31: 0 | AB31: 0 | AC31: 31.17 | AD31: 5827211.6
A32: Zola | B32: Longo | D32: 70000124 | E32: 70000124 | F32: Longo | G32: Zola | H32: 28108 | I32: Male | J32: Congo | K32: 42240 | L32: Shift Supervisor | O32: C3 | P32: 49 | Q32: 10 | R32: KQ1023-Hauling | S32: Mining | T32: Sick | U32: conge de maladie | X32: 45018 | Y32: 180 | Z32: 0 | AA32: 0 | AB32: 0 | AC32: 180 | AD32: 33650885 | AE32: 180 | AF32: 46357
A33: Zola | B33: Longo | D33: 70000124 | E33: 70000124 | F33: Longo | G33: Zola | H33: 28108 | I33: Male | J33: Congo | K33: 42240 | L33: Shift Supervisor | O33: C3 | P33: 49 | Q33: 10 | R33: KQ1023-Hauling | S33: Mining | T33: Special | U33: Circumstance Leave | X33: 45018 | Y33: 15 | Z33: 0 | AA33: 0 | AB33: 0 | AC33: 15 | AD33: 2804240.4 | AE33: 15 | AF33: 46357
A34: Zola | B34: Longo | D34: 70000124 | E34: 70000124 | F34: Longo | G34: Zola | H34: 28108 | I34: Male | J34: Congo | K34: 42240 | L34: Shift Supervisor | O34: C3 | P34: 49 | Q34: 10 | R34: KQ1023-Hauling | S34: Mining | T34: Special | U34: Maternity leave | X34: 45018 | Y34: 98 | Z34: 0 | AA34: 0 | AB34: 0 | AC34: 98 | AD34: 18321037 | AE34: 98 | AF34: 46357
A35: Zola | B35: Longo | D35: 70000124 | E35: 70000124 | F35: Longo | G35: Zola | H35: 28108 | I35: Male | J35: Congo | K35: 42240 | L35: Shift Supervisor | O35: C3 | P35: 49 | Q35: 10 | R35: KQ1023-Hauling | S35: Mining | T35: Special | U35: Paternity Leave | X35: 45018 | Y35: 2 | Z35: 0 | AA35: 0 | AB35: 0 | AC35: 2 | AD35: 373898.72 | AE35: 2 | AF35: 46357
A36: Zola | B36: Longo | D36: 70000124 | E36: 70000124 | F36: Longo | G36: Zola | H36: 28108 | I36: Male | J36: Congo | K36: 42240 | L36: Shift Supervisor | O36: C3 | P36: 49 | Q36: 10 | R36: KQ1023-Hauling | S36: Mining | T36: Special | U36: Special Leave | X36: 45018 | Y36: 5 | Z36: 0 | AA36: 0 | AB36: 0 | AC36: 5 | AD36: 934746.81 | AE36: 5 | AF36: 46357
A37: Zola | B37: Longo | D37: 70000124 | E37: 70000124 | F37: Longo | G37: Zola | H37: 28108 | I37: Male | J37: Congo | K37: 42240 | L37: Shift Supervisor | O37: C3 | P37: 49 | Q37: 10 | R37: KQ1023-Hauling | S37: Mining | T37: Special | U37: Unpaid leave | X37: 45018 | Y37: 0.5 | Z37: 0.08333333 | AA37: 0 | AB37: 0 | AC37: 0.58333333 | AD37: 109053.79 | AE37: 0.58 | AF37: 46357
A38: DIAWAWANA | B38: RACHIE | D38: 70000129 | E38: 70000129 | F38: RACHIE | G38: DIAWAWANA | H38: 30536 | I38: Male | J38: Congo | K38: 43192 | L38: Mobile Equipment Operator - Grader | O38: B3 | P38: 42 | Q38: 8 | R38: KQ1910-Mining General | S38: Mining | T38: Annual | U38: Annual Leave | V38: 22 days 3 to 6 years | W38: 8 | X38: 45018 | Y38: 9.1666667 | Z38: 1.8333333 | AA38: 0 | AB38: 0 | AC38: 11 | AD38: 857449.48
A39: DIAWAWANA | B39: RACHIE | D39: 70000129 | E39: 70000129 | F39: RACHIE | G39: DIAWAWANA | H39: 30536 | I39: Male | J39: Congo | K39: 43192 | L39: Mobile Equipment Operator - Grader | O39: B3 | P39: 42 | Q39: 8 | R39: KQ1910-Mining General | S39: Mining | T39: Sick | U39: conge de maladie | X39: 45018 | Y39: 180 | Z39: 0 | AA39: 0 | AB39: 0 | AC39: 180 | AD39: 14030991 | AE39: 180 | AF39: 46357
A40: DIAWAWANA | B40: RACHIE | D40: 70000129 | E40: 70000129 | F40: RACHIE | G40: DIAWAWANA | H40: 30536 | I40: Male | J40: Congo | K40: 43192 | L40: Mobile Equipment Operator - Grader | O40: B3 | P40: 42 | Q40: 8 | R40: KQ1910-Mining General | S40: Mining | T40: Special | U40: Circumstance Leave | X40: 45018 | Y40: 15 | Z40: 0 | AA40: 0 | AB40: 0 | AC40: 15 | AD40: 1169249.3 | AE40: 15 | AF40: 46357
A41: DIAWAWANA | B41: RACHIE | D41: 70000129 | E41: 70000129 | F41: RACHIE | G41: DIAWAWANA | H41: 30536 | I41: Male | J41: Congo | K41: 43192 | L41: Mobile Equipment Operator - Grader | O41: B3 | P41: 42 | Q41: 8 | R41: KQ1910-Mining General | S41: Mining | T41: Special | U41: Maternity leave | X41: 45018 | Y41: 98 | Z41: 0 | AA41: 0 | AB41: 0 | AC41: 98 | AD41: 7639095.3 | AE41: 98 | AF41: 46357
A42: DIAWAWANA | B42: RACHIE | D42: 70000129 | E42: 70000129 | F42: RACHIE | G42: DIAWAWANA | H42: 30536 | I42: Male | J42: Congo | K42: 43192 | L42: Mobile Equipment Operator - Grader | O42: B3 | P42: 42 | Q42: 8 | R42: KQ1910-Mining General | S42: Mining | T42: Special | U42: Paternity Leave | X42: 45018 | Y42: 2 | Z42: 0 | AA42: 0 | AB42: 0 | AC42: 2 | AD42: 155899.9 | AE42: 2 | AF42: 46357
A43: DIAWAWANA | B43: RACHIE | D43: 70000129 | E43: 70000129 | F43: RACHIE | G43: DIAWAWANA | H43: 30536 | I43: Male | J43: Congo | K43: 43192 | L43: Mobile Equipment Operator - Grader | O43: B3 | P43: 42 | Q43: 8 | R43: KQ1910-Mining General | S43: Mining | T43: Special | U43: Special Leave | X43: 45018 | Y43: 5 | Z43: 0 | AA43: 0 | AB43: 0 | AC43: 5 | AD43: 389749.76 | AE43: 5 | AF43: 46357
A44: DIAWAWANA | B44: RACHIE | D44: 70000129 | E44: 70000129 | F44: RACHIE | G44: DIAWAWANA | H44: 30536 | I44: Male | J44: Congo | K44: 43192 | L44: Mobile Equipment Operator - Grader | O44: B3 | P44: 42 | Q44: 8 | R44: KQ1910-Mining General | S44: Mining | T44: Special | U44: Unpaid leave | X44: 45018 | Y44: 0.5 | Z44: 0.08333333 | AA44: 0 | AB44: 0 | AC44: 0.58333333 | AD44: 45470.806 | AE44: 0.58 | AF44: 46357
A45: Mpungwe | B45: Marques | D45: 70000204 | E45: 70000204 | F45: Marques | G45: Mpungwe | H45: 28290 | I45: Male | J45: The Democratic Republic of the Congo | K45: 44319 | L45: Mining Superintendant | O45: D1 | P45: 49 | Q45: 5 | R45: KQ1910-Mining General | S45: Mining | T45: Annual | U45: Conge Annuel | V45: 21 days 3 to6 Years | W45: 5 | X45: 45018 | Y45: 28.166667 | Z45: 2.0833333 | AA45: 0 | AB45: 0 | AC45: 30.25 | AD45: 14372259
A46: Mpungwe | B46: Marques | D46: 70000204 | E46: 70000204 | F46: Marques | G46: Mpungwe | H46: 28290 | I46: Male | J46: The Democratic Republic of the Congo | K46: 44319 | L46: Mining Superintendant | O46: D1 | P46: 49 | Q46: 5 | R46: KQ1910-Mining General | S46: Mining | T46: Sick | U46: Sick Leave | X46: 45018 | Y46: 180 | Z46: 0 | AA46: 0 | AB46: 0 | AC46: 180 | AD46: 85520879 | AE46: 180 | AF46: 46357
A47: Mpungwe | B47: Marques | D47: 70000204 | E47: 70000204 | F47: Marques | G47: Mpungwe | H47: 28290 | I47: Male | J47: The Democratic Republic of the Congo | K47: 44319 | L47: Mining Superintendant | O47: D1 | P47: 49 | Q47: 5 | R47: KQ1910-Mining General | S47: Mining | T47: Special | U47: Circumstance Leave | X47: 45018 | Y47: 15 | Z47: 0 | AA47: 0 | AB47: 0 | AC47: 15 | AD47: 7126739.9 | AE47: 15 | AF47: 46357
A48: Mpungwe | B48: Marques | D48: 70000204 | E48: 70000204 | F48: Marques | G48: Mpungwe | H48: 28290 | I48: Male | J48: The Democratic Republic of the Congo | K48: 44319 | L48: Mining Superintendant | O48: D1 | P48: 49 | Q48: 5 | R48: KQ1910-Mining General | S48: Mining | T48: Special | U48: Maternity leave | X48: 45018 | Y48: 98 | Z48: 0 | AA48: 0 | AB48: 0 | AC48: 98 | AD48: 46561367 | AE48: 98 | AF48: 46357
A49: Mpungwe | B49: Marques | D49: 70000204 | E49: 70000204 | F49: Marques | G49: Mpungwe | H49: 28290 | I49: Male | J49: The Democratic Republic of the Congo | K49: 44319 | L49: Mining Superintendant | O49: D1 | P49: 49 | Q49: 5 | R49: KQ1910-Mining General | S49: Mining | T49: Special | U49: Paternity Leave | X49: 45018 | Y49: 2 | Z49: 0 | AA49: 0 | AB49: 0 | AC49: 2 | AD49: 950231.98 | AE49: 2 | AF49: 46357
A50: Mpungwe | B50: Marques | D50: 70000204 | E50: 70000204 | F50: Marques | G50: Mpungwe | H50: 28290 | I50: Male | J50: The Democratic Republic of the Congo | K50: 44319 | L50: Mining Superintendant | O50: D1 | P50: 49 | Q50: 5 | R50: KQ1910-Mining General | S50: Mining | T50: Special | U50: Special Leave | X50: 45018 | Y50: 5 | Z50: 0 | AA50: 0 | AB50: 0 | AC50: 5 | AD50: 2375580 | AE50: 5 | AF50: 46357
A51: Mpungwe | B51: Marques | D51: 70000204 | E51: 70000204 | F51: Marques | G51: Mpungwe | H51: 28290 | I51: Male | J51: The Democratic Republic of the Congo | K51: 44319 | L51: Mining Superintendant | O51: D1 | P51: 49 | Q51: 5 | R51: KQ1910-Mining General | S51: Mining | T51: Special | U51: Unpaid leave | X51: 45018 | Y51: 1 | Z51: 0 | AA51: 0 | AB51: 0 | AC51: 1 | AD51: 475115.99 | AE51: 1 | AF51: 46357
A52: Kone | B52: Cyrille | D52: 70000208 | E52: 70000208 | F52: Cyrille | G52: Kone | H52: 33139 | I52: Male | J52: Côte d'Ivoire | K52: 44593 | L52: Finance Manager | O52: D2 | P52: 35 | Q52: 4 | R52: KQ1910-Mining General | S52: Mining | T52: Annual | U52: Conge Annuel | V52: 21 days 3 to6 Years | W52: 4 | X52: 45018 | Y52: 20.25 | Z52: 2.0833333 | AA52: 0 | AB52: 0 | AC52: 22.333333 | AD52: 13787873
A53: Kone | B53: Cyrille | D53: 70000208 | E53: 70000208 | F53: Cyrille | G53: Kone | H53: 33139 | I53: Male | J53: Côte d'Ivoire | K53: 44593 | L53: Finance Manager | O53: D2 | P53: 35 | Q53: 4 | R53: KQ1910-Mining General | S53: Mining | T53: Sick | U53: Sick Leave | X53: 45018 | Y53: 180 | Z53: 0 | AA53: 0 | AB53: 0 | AC53: 180 | AD53: 1.1112614e+08 | AE53: 180 | AF53: 46357
A54: Kone | B54: Cyrille | D54: 70000208 | E54: 70000208 | F54: Cyrille | G54: Kone | H54: 33139 | I54: Male | J54: Côte d'Ivoire | K54: 44593 | L54: Finance Manager | O54: D2 | P54: 35 | Q54: 4 | R54: KQ1910-Mining General | S54: Mining | T54: Special | U54: Circumstance Leave | X54: 45018 | Y54: 15 | Z54: 0 | AA54: 0 | AB54: 0 | AC54: 15 | AD54: 9260511.9 | AE54: 15 | AF54: 46357
A55: Kone | B55: Cyrille | D55: 70000208 | E55: 70000208 | F55: Cyrille | G55: Kone | H55: 33139 | I55: Male | J55: Côte d'Ivoire | K55: 44593 | L55: Finance Manager | O55: D2 | P55: 35 | Q55: 4 | R55: KQ1910-Mining General | S55: Mining | T55: Special | U55: Maternity leave | X55: 45018 | Y55: 98 | Z55: 0 | AA55: 0 | AB55: 0 | AC55: 98 | AD55: 60502011 | AE55: 98 | AF55: 46357
A56: Kone | B56: Cyrille | D56: 70000208 | E56: 70000208 | F56: Cyrille | G56: Kone | H56: 33139 | I56: Male | J56: Côte d'Ivoire | K56: 44593 | L56: Finance Manager | O56: D2 | P56: 35 | Q56: 4 | R56: KQ1910-Mining General | S56: Mining | T56: Special | U56: Paternity Leave | X56: 45018 | Y56: 2 | Z56: 0 | AA56: 0 | AB56: 0 | AC56: 2 | AD56: 1234734.9 | AE56: 2 | AF56: 46357
A57: Kone | B57: Cyrille | D57: 70000208 | E57: 70000208 | F57: Cyrille | G57: Kone | H57: 33139 | I57: Male | J57: Côte d'Ivoire | K57: 44593 | L57: Finance Manager | O57: D2 | P57: 35 | Q57: 4 | R57: KQ1910-Mining General | S57: Mining | T57: Special | U57: Special Leave | X57: 45018 | Y57: 5 | Z57: 0 | AA57: 0 | AB57: 0 | AC57: 5 | AD57: 3086837.3 | AE57: 5 | AF57: 46357
A58: Kone | B58: Cyrille | D58: 70000208 | E58: 70000208 | F58: Cyrille | G58: Kone | H58: 33139 | I58: Male | J58: Côte d'Ivoire | K58: 44593 | L58: Finance Manager | O58: D2 | P58: 35 | Q58: 4 | R58: KQ1910-Mining General | S58: Mining | T58: Special | U58: Unpaid leave | X58: 45018 | Y58: 1 | Z58: 0 | AA58: 0 | AB58: 0 | AC58: 1 | AD58: 617367.46 | AE58: 1 | AF58: 46357
A59: Kananga | B59: Hassan | D59: 70000233 | E59: 70000233 | F59: Hassan | G59: Kananga | H59: 34429 | I59: Male | J59: The Democratic Republic of the Congo | K59: 45446 | L59: Mining Shift Supervisor | O59: C3 | P59: 32 | Q59: 2 | R59: KQ1910-Mining General | S59: Mining | T59: Annual | U59: Annual Leave | V59: 22 days 12 to 15 years | W59: 2 | X59: 45446.083 | Y59: 25.711111 | Z59: 1.8333333 | AA59: -19 | AB59: 0 | AC59: 8.5444444 | AD59: 1484752.2
A60: Kananga | B60: Hassan | D60: 70000233 | E60: 70000233 | F60: Hassan | G60: Kananga | H60: 34429 | I60: Male | J60: The Democratic Republic of the Congo | K60: 45446 | L60: Mining Shift Supervisor | O60: C3 | P60: 32 | Q60: 2 | R60: KQ1910-Mining General | S60: Mining | T60: Sick | U60: conge de maladie | X60: 45446.083 | Y60: 180 | Z60: 0 | AA60: 0 | AB60: 0 | AC60: 180 | AD60: 31278265 | AE60: 180 | AF60: 46357
A61: Kananga | B61: Hassan | D61: 70000233 | E61: 70000233 | F61: Hassan | G61: Kananga | H61: 34429 | I61: Male | J61: The Democratic Republic of the Congo | K61: 45446 | L61: Mining Shift Supervisor | O61: C3 | P61: 32 | Q61: 2 | R61: KQ1910-Mining General | S61: Mining | T61: Special | U61: Circumstance Leave | X61: 45446.083 | Y61: 15 | Z61: 0 | AA61: 0 | AB61: 0 | AC61: 15 | AD61: 2606522.1 | AE61: 15 | AF61: 46357
A62: Kananga | B62: Hassan | D62: 70000233 | E62: 70000233 | F62: Hassan | G62: Kananga | H62: 34429 | I62: Male | J62: The Democratic Republic of the Congo | K62: 45446 | L62: Mining Shift Supervisor | O62: C3 | P62: 32 | Q62: 2 | R62: KQ1910-Mining General | S62: Mining | T62: Special | U62: Maternity leave | X62: 45446.083 | Y62: 98 | Z62: 0 | AA62: 0 | AB62: 0 | AC62: 98 | AD62: 17029277 | AE62: 98 | AF62: 46357
A63: Kananga | B63: Hassan | D63: 70000233 | E63: 70000233 | F63: Hassan | G63: Kananga | H63: 34429 | I63: Male | J63: The Democratic Republic of the Congo | K63: 45446 | L63: Mining Shift Supervisor | O63: C3 | P63: 32 | Q63: 2 | R63: KQ1910-Mining General | S63: Mining | T63: Special | U63: Paternity Leave | X63: 45446.083 | Y63: 2 | Z63: 0 | AA63: 0 | AB63: 0 | AC63: 2 | AD63: 347536.27 | AE63: 2 | AF63: 46357
A64: Kananga | B64: Hassan | D64: 70000233 | E64: 70000233 | F64: Hassan | G64: Kananga | H64: 34429 | I64: Male | J64: The Democratic Republic of the Congo | K64: 45446 | L64: Mining Shift Supervisor | O64: C3 | P64: 32 | Q64: 2 | R64: KQ1910-Mining General | S64: Mining | T64: Special | U64: Special Leave | X64: 45446.083 | Y64: 5 | Z64: 0 | AA64: 0 | AB64: 0 | AC64: 5 | AD64: 868840.68 | AE64: 5 | AF64: 46357
A65: Kananga | B65: Hassan | D65: 70000233 | E65: 70000233 | F65: Hassan | G65: Kananga | H65: 34429 | I65: Male | J65: The Democratic Republic of the Congo | K65: 45446 | L65: Mining Shift Supervisor | O65: C3 | P65: 32 | Q65: 2 | R65: KQ1910-Mining General | S65: Mining | T65: Special | U65: Unpaid leave | X65: 45446.083 | Y65: 0.5 | Z65: 0.08333333 | AA65: 0 | AB65: 0 | AC65: 0.58333333 | AD65: 101364.75 | AE65: 0.58 | AF65: 46357
A66: Rukomeza | B66: Giscard | D66: 70000266 | E66: 70000266 | F66: Giscard | G66: Rukomeza | H66: 31578 | I66: Male | J66: The Democratic Republic of the Congo | K66: 45414 | L66: Mining Manager | O66: D2 | P66: 40 | Q66: 2 | R66: KQ1910-Mining General | S66: Mining | T66: Annual | U66: Conge Annuel | V66: 20 days 0 to1 Years | W66: 2 | X66: 45414.083 | Y66: 19.935484 | Z66: 2 | AA66: 0 | AB66: 0 | AC66: 21.935484 | AD66: 11337889
A67: Rukomeza | B67: Giscard | D67: 70000266 | E67: 70000266 | F67: Giscard | G67: Rukomeza | H67: 31578 | I67: Male | J67: The Democratic Republic of the Congo | K67: 45414 | L67: Mining Manager | O67: D2 | P67: 40 | Q67: 2 | R67: KQ1910-Mining General | S67: Mining | T67: Sick | U67: Sick Leave | X67: 45414.083 | Y67: 180 | Z67: 0 | AA67: 0 | AB67: 0 | AC67: 180 | AD67: 93037380 | AE67: 180 | AF67: 46357
A68: Rukomeza | B68: Giscard | D68: 70000266 | E68: 70000266 | F68: Giscard | G68: Rukomeza | H68: 31578 | I68: Male | J68: The Democratic Republic of the Congo | K68: 45414 | L68: Mining Manager | O68: D2 | P68: 40 | Q68: 2 | R68: KQ1910-Mining General | S68: Mining | T68: Special | U68: Circumstance Leave | X68: 45414.083 | Y68: 14 | Z68: 0 | AA68: 0 | AB68: 0 | AC68: 14 | AD68: 7236240.7 | AE68: 14 | AF68: 46357
A69: Rukomeza | B69: Giscard | D69: 70000266 | E69: 70000266 | F69: Giscard | G69: Rukomeza | H69: 31578 | I69: Male | J69: The Democratic Republic of the Congo | K69: 45414 | L69: Mining Manager | O69: D2 | P69: 40 | Q69: 2 | R69: KQ1910-Mining General | S69: Mining | T69: Special | U69: Maternity leave | X69: 45414.083 | Y69: 98 | Z69: 0 | AA69: 0 | AB69: 0 | AC69: 98 | AD69: 50653685 | AE69: 98 | AF69: 46357
A70: Rukomeza | B70: Giscard | D70: 70000266 | E70: 70000266 | F70: Giscard | G70: Rukomeza | H70: 31578 | I70: Male | J70: The Democratic Republic of the Congo | K70: 45414 | L70: Mining Manager | O70: D2 | P70: 40 | Q70: 2 | R70: KQ1910-Mining General | S70: Mining | T70: Special | U70: Paternity Leave | X70: 45414.083 | Y70: 2 | Z70: 0 | AA70: 0 | AB70: 0 | AC70: 2 | AD70: 1033748.7 | AE70: 2 | AF70: 46357
A71: Rukomeza | B71: Giscard | D71: 70000266 | E71: 70000266 | F71: Giscard | G71: Rukomeza | H71: 31578 | I71: Male | J71: The Democratic Republic of the Congo | K71: 45414 | L71: Mining Manager | O71: D2 | P71: 40 | Q71: 2 | R71: KQ1910-Mining General | S71: Mining | T71: Special | U71: Special Leave | X71: 45414.083 | Y71: 5 | Z71: 0 | AA71: 0 | AB71: 0 | AC71: 5 | AD71: 2584371.7 | AE71: 5 | AF71: 46357
A72: Rukomeza | B72: Giscard | D72: 70000266 | E72: 70000266 | F72: Giscard | G72: Rukomeza | H72: 31578 | I72: Male | J72: The Democratic Republic of the Congo | K72: 45414 | L72: Mining Manager | O72: D2 | P72: 40 | Q72: 2 | R72: KQ1910-Mining General | S72: Mining | T72: Special | U72: Unpaid leave | X72: 45414.083 | Y72: 1 | Z72: 0 | AA72: 0 | AB72: 0 | AC72: 1 | AD72: 516874.33 | AE72: 1 | AF72: 46357
A73: Mbodi | B73: Gaël | D73: 70000002 | E73: 70000002 | F73: Gaël | G73: Mbodi | H73: 31575 | I73: Male | J73: Congo | K73: 41852 | L73: Site Manager | O73: D2 | P73: 40 | Q73: 11 | R73: DL5110-Lubudi team | S73: Administration | T73: Annual | U73: conge annuel | V73: 23 days 9 to 12Years | W73: 11 | X73: 45413 | Y73: 21.64 | Z73: 2.25 | AA73: 0 | AB73: 0 | AC73: 23.89 | AD73: 10165697
A74: Mbodi | B74: Gaël | D74: 70000002 | E74: 70000002 | F74: Gaël | G74: Mbodi | H74: 31575 | I74: Male | J74: Congo | K74: 41852 | L74: Site Manager | O74: D2 | P74: 40 | Q74: 11 | R74: DL5110-Lubudi team | S74: Administration | T74: Sick | U74: conge de maladie | X74: 45413 | Y74: 180 | Z74: 0 | AA74: 0 | AB74: 0 | AC74: 180 | AD74: 76593780 | AE74: 180 | AF74: 46357
A75: Mbodi | B75: Gaël | D75: 70000002 | E75: 70000002 | F75: Gaël | G75: Mbodi | H75: 31575 | I75: Male | J75: Congo | K75: 41852 | L75: Site Manager | O75: D2 | P75: 40 | Q75: 11 | R75: DL5110-Lubudi team | S75: Administration | T75: Special | U75: Circumstance Leave | X75: 45413 | Y75: 26 | Z75: 0 | AA75: 0 | AB75: 0 | AC75: 26 | AD75: 11063546 | AE75: 26 | AF75: 46357
A76: Mbodi | B76: Gaël | D76: 70000002 | E76: 70000002 | F76: Gaël | G76: Mbodi | H76: 31575 | I76: Male | J76: Congo | K76: 41852 | L76: Site Manager | O76: D2 | P76: 40 | Q76: 11 | R76: DL5110-Lubudi team | S76: Administration | T76: Special | U76: Maternity leave | X76: 45413 | Y76: 98 | Z76: 0 | AA76: 0 | AB76: 0 | AC76: 98 | AD76: 41701058 | AE76: 98 | AF76: 46357
A77: Mbodi | B77: Gaël | D77: 70000002 | E77: 70000002 | F77: Gaël | G77: Mbodi | H77: 31575 | I77: Male | J77: Congo | K77: 41852 | L77: Site Manager | O77: D2 | P77: 40 | Q77: 11 | R77: DL5110-Lubudi team | S77: Administration | T77: Special | U77: Paternity Leave | X77: 45413 | Y77: 2 | Z77: 0 | AA77: 0 | AB77: 0 | AC77: 2 | AD77: 851042 | AE77: 2 | AF77: 46357
A78: Mbodi | B78: Gaël | D78: 70000002 | E78: 70000002 | F78: Gaël | G78: Mbodi | H78: 31575 | I78: Male | J78: Congo | K78: 41852 | L78: Site Manager | O78: D2 | P78: 40 | Q78: 11 | R78: DL5110-Lubudi team | S78: Administration | T78: Special | U78: Special Leave | X78: 45413 | Y78: 5 | Z78: 0 | AA78: 0 | AB78: 0 | AC78: 5 | AD78: 2127605 | AE78: 5 | AF78: 46357
A79: Mbodi | B79: Gaël | D79: 70000002 | E79: 70000002 | F79: Gaël | G79: Mbodi | H79: 31575 | I79: Male | J79: Congo | K79: 41852 | L79: Site Manager | O79: D2 | P79: 40 | Q79: 11 | R79: DL5110-Lubudi team | S79: Administration | T79: Special | U79: Unpaid leave | X79: 45413 | Y79: 2.5 | Z79: 0.41666667 | AA79: 0 | AB79: 0 | AC79: 2.9166667 | AD79: 1241102.9 | AE79: 2.92 | AF79: 46357
A80: Muakasa | B80: Serge | D80: 70000008 | E80: 70000008 | F80: Serge | G80: Muakasa | H80: 28524 | I80: Male | J80: Congo | K80: 42099 | L80: Estate Officer | O80: C4 | P80: 48 | Q80: 11 | R80: KM5631-Village | S80: Human Resources | T80: Annual | U80: Annual Leave | V80: 25 days 9 to 12 years | W80: 11 | X80: 45018 | Y80: 16.82 | Z80: 2.0833333 | AA80: 0 | AB80: 0 | AC80: 18.903333 | AD80: 6288990.1
A81: Muakasa | B81: Serge | D81: 70000008 | E81: 70000008 | F81: Serge | G81: Muakasa | H81: 28524 | I81: Male | J81: Congo | K81: 42099 | L81: Estate Officer | O81: C4 | P81: 48 | Q81: 11 | R81: KM5631-Village | S81: Human Resources | T81: Sick | U81: Conge de Maladie | X81: 45018 | Y81: 180 | Z81: 0 | AA81: 0 | AB81: 0 | AC81: 180 | AD81: 59884582 | AE81: 180 | AF81: 46357
A82: Muakasa | B82: Serge | D82: 70000008 | E82: 70000008 | F82: Serge | G82: Muakasa | H82: 28524 | I82: Male | J82: Congo | K82: 42099 | L82: Estate Officer | O82: C4 | P82: 48 | Q82: 11 | R82: KM5631-Village | S82: Human Resources | T82: Special | U82: Circumstance Leave | X82: 45018 | Y82: 26 | Z82: 0 | AA82: 0 | AB82: 0 | AC82: 26 | AD82: 8649995.2 | AE82: 26 | AF82: 46357
A83: Muakasa | B83: Serge | D83: 70000008 | E83: 70000008 | F83: Serge | G83: Muakasa | H83: 28524 | I83: Male | J83: Congo | K83: 42099 | L83: Estate Officer | O83: C4 | P83: 48 | Q83: 11 | R83: KM5631-Village | S83: Human Resources | T83: Special | U83: Maternity leave | X83: 45018 | Y83: 98 | Z83: 0 | AA83: 0 | AB83: 0 | AC83: 98 | AD83: 32603828 | AE83: 98 | AF83: 46357
A84: Muakasa | B84: Serge | D84: 70000008 | E84: 70000008 | F84: Serge | G84: Muakasa | H84: 28524 | I84: Male | J84: Congo | K84: 42099 | L84: Estate Officer | O84: C4 | P84: 48 | Q84: 11 | R84: KM5631-Village | S84: Human Resources | T84: Special | U84: Paternity Leave | X84: 45018 | Y84: 2 | Z84: 0 | AA84: 0 | AB84: 0 | AC84: 2 | AD84: 665384.25 | AE84: 2 | AF84: 46357
A85: Muakasa | B85: Serge | D85: 70000008 | E85: 70000008 | F85: Serge | G85: Muakasa | H85: 28524 | I85: Male | J85: Congo | K85: 42099 | L85: Estate Officer | O85: C4 | P85: 48 | Q85: 11 | R85: KM5631-Village | S85: Human Resources | T85: Special | U85: Special Leave | X85: 45018 | Y85: 5 | Z85: 0 | AA85: 0 | AB85: 0 | AC85: 5 | AD85: 1663460.6 | AE85: 5 | AF85: 46357
A86: Muakasa | B86: Serge | D86: 70000008 | E86: 70000008 | F86: Serge | G86: Muakasa | H86: 28524 | I86: Male | J86: Congo | K86: 42099 | L86: Estate Officer | O86: C4 | P86: 48 | Q86: 11 | R86: KM5631-Village | S86: Human Resources | T86: Special | U86: Unpaid Leave | X86: 45018 | Y86: 2.5 | Z86: 0.41666667 | AA86: 0 | AB86: 0 | AC86: 2.9166667 | AD86: 970352.03 | AE86: 2.92 | AF86: 46357
A87: Zodulua | B87: Jean Jacques | D87: 70000009 | E87: 70000009 | F87: Jean Jacques | G87: Zodulua | H87: 25429 | I87: Male | J87: Congo | K87: 42135 | L87: Driver | O87: B2 | P87: 56 | Q87: 11 | R87: KC8710-HR Admin General | S87: Corporate Admin | T87: Annual | U87: Conge Annuel | V87: 23 days 9 to 12Years | W87: 11 | X87: 45018 | Y87: 25.916667 | Z87: 1.9166667 | AA87: 0 | AB87: 0 | AC87: 27.833333 | AD87: 2005095.9
A88: Zodulua | B88: Jean Jacques | D88: 70000009 | E88: 70000009 | F88: Jean Jacques | G88: Zodulua | H88: 25429 | I88: Male | J88: Congo | K88: 42135 | L88: Driver | O88: B2 | P88: 56 | Q88: 11 | R88: KC8710-HR Admin General | S88: Corporate Admin | T88: Sick | U88: conge de maladie | X88: 45018 | Y88: 180 | Z88: 0 | AA88: 0 | AB88: 0 | AC88: 180 | AD88: 12967087 | AE88: 180 | AF88: 46357
A89: Zodulua | B89: Jean Jacques | D89: 70000009 | E89: 70000009 | F89: Jean Jacques | G89: Zodulua | H89: 25429 | I89: Male | J89: Congo | K89: 42135 | L89: Driver | O89: B2 | P89: 56 | Q89: 11 | R89: KC8710-HR Admin General | S89: Corporate Admin | T89: Special | U89: Circumstance Leave | X89: 45018 | Y89: 26 | Z89: 0 | AA89: 0 | AB89: 0 | AC89: 26 | AD89: 1873023.7 | AE89: 26 | AF89: 46357
A90: Zodulua | B90: Jean Jacques | D90: 70000009 | E90: 70000009 | F90: Jean Jacques | G90: Zodulua | H90: 25429 | I90: Male | J90: Congo | K90: 42135 | L90: Driver | O90: B2 | P90: 56 | Q90: 11 | R90: KC8710-HR Admin General | S90: Corporate Admin | T90: Special | U90: Maternity leave | X90: 45018 | Y90: 98 | Z90: 0 | AA90: 0 | AB90: 0 | AC90: 98 | AD90: 7059858.5 | AE90: 98 | AF90: 46357
A91: Zodulua | B91: Jean Jacques | D91: 70000009 | E91: 70000009 | F91: Jean Jacques | G91: Zodulua | H91: 25429 | I91: Male | J91: Congo | K91: 42135 | L91: Driver | O91: B2 | P91: 56 | Q91: 11 | R91: KC8710-HR Admin General | S91: Corporate Admin | T91: Special | U91: Paternity Leave | X91: 45018 | Y91: 2 | Z91: 0 | AA91: 0 | AB91: 0 | AC91: 2 | AD91: 144078.75 | AE91: 2 | AF91: 46357
A92: Zodulua | B92: Jean Jacques | D92: 70000009 | E92: 70000009 | F92: Jean Jacques | G92: Zodulua | H92: 25429 | I92: Male | J92: Congo | K92: 42135 | L92: Driver | O92: B2 | P92: 56 | Q92: 11 | R92: KC8710-HR Admin General | S92: Corporate Admin | T92: Special | U92: Special Leave | X92: 45018 | Y92: 5 | Z92: 0 | AA92: 0 | AB92: 0 | AC92: 5 | AD92: 360196.86 | AE92: 5 | AF92: 46357
A93: Zodulua | B93: Jean Jacques | D93: 70000009 | E93: 70000009 | F93: Jean Jacques | G93: Zodulua | H93: 25429 | I93: Male | J93: Congo | K93: 42135 | L93: Driver | O93: B2 | P93: 56 | Q93: 11 | R93: KC8710-HR Admin General | S93: Corporate Admin | T93: Special | U93: Unpaid leave | X93: 45018 | Y93: 2.5 | Z93: 0.41666667 | AA93: 0 | AB93: 0 | AC93: 2.9166667 | AD93: 210114.84 | AE93: 2.92 | AF93: 46357
A94: Feinta | B94: Kimbanzi | D94: 70000011 | E94: 70000011 | F94: Kimbanzi | G94: Feinta | H94: 25330 | I94: Male | J94: Congo | K94: 42240 | L94: Senior Sales Consultant | O94: C4 | P94: 57 | Q94: 10 | R94: KC6111-Central Region | S94: Sales & Logistics | T94: Annual | U94: Annual Leave | V94: 25 days 9 to 12 years | W94: 10 | X94: 45018 | Y94: 27.333333 | Z94: 2.0833333 | AA94: 0 | AB94: 0 | AC94: 29.416667 | AD94: 6785219.7
A95: Feinta | B95: Kimbanzi | D95: 70000011 | E95: 70000011 | F95: Kimbanzi | G95: Feinta | H95: 25330 | I95: Male | J95: Congo | K95: 42240 | L95: Senior Sales Consultant | O95: C4 | P95: 57 | Q95: 10 | R95: KC6111-Central Region | S95: Sales & Logistics | T95: Sick | U95: Conge de Maladie | X95: 45018 | Y95: 180 | Z95: 0 | AA95: 0 | AB95: 0 | AC95: 180 | AD95: 41518625 | AE95: 180 | AF95: 46357
A96: Feinta | B96: Kimbanzi | D96: 70000011 | E96: 70000011 | F96: Kimbanzi | G96: Feinta | H96: 25330 | I96: Male | J96: Congo | K96: 42240 | L96: Senior Sales Consultant | O96: C4 | P96: 57 | Q96: 10 | R96: KC6111-Central Region | S96: Sales & Logistics | T96: Special | U96: Circumstance Leave | X96: 45018 | Y96: 26 | Z96: 0 | AA96: 0 | AB96: 0 | AC96: 26 | AD96: 5997134.7 | AE96: 26 | AF96: 46357
A97: Feinta | B97: Kimbanzi | D97: 70000011 | E97: 70000011 | F97: Kimbanzi | G97: Feinta | H97: 25330 | I97: Male | J97: Congo | K97: 42240 | L97: Senior Sales Consultant | O97: C4 | P97: 57 | Q97: 10 | R97: KC6111-Central Region | S97: Sales & Logistics | T97: Special | U97: Maternity leave | X97: 45018 | Y97: 98 | Z97: 0 | AA97: 0 | AB97: 0 | AC97: 98 | AD97: 22604584 | AE97: 98 | AF97: 46357
A98: Feinta | B98: Kimbanzi | D98: 70000011 | E98: 70000011 | F98: Kimbanzi | G98: Feinta | H98: 25330 | I98: Male | J98: Congo | K98: 42240 | L98: Senior Sales Consultant | O98: C4 | P98: 57 | Q98: 10 | R98: KC6111-Central Region | S98: Sales & Logistics | T98: Special | U98: Paternity Leave | X98: 45018 | Y98: 2 | Z98: 0 | AA98: 0 | AB98: 0 | AC98: 2 | AD98: 461318.05 | AE98: 2 | AF98: 46357
A99: Feinta | B99: Kimbanzi | D99: 70000011 | E99: 70000011 | F99: Kimbanzi | G99: Feinta | H99: 25330 | I99: Male | J99: Congo | K99: 42240 | L99: Senior Sales Consultant | O99: C4 | P99: 57 | Q99: 10 | R99: KC6111-Central Region | S99: Sales & Logistics | T99: Special | U99: Special Leave | X99: 45018 | Y99: 5 | Z99: 0 | AA99: 0 | AB99: 0 | AC99: 5 | AD99: 1153295.1 | AE99: 5 | AF99: 46357
A100: Feinta | B100: Kimbanzi | D100: 70000011 | E100: 70000011 | F100: Kimbanzi | G100: Feinta | H100: 25330 | I100: Male | J100: Congo | K100: 42240 | L100: Senior Sales Consultant | O100: C4 | P100: 57 | Q100: 10 | R100: KC6111-Central Region | S100: Sales & Logistics | T100: Special | U100: Unpaid Leave | X100: 45018 | Y100: 2.5 | Z100: 0.41666667 | AA100: 0 | AB100: 0 | AC100: 2.9166667 | AD100: 672755.49 | AE100: 2.92 | AF100: 46357
A101: NSEMBOLO | B101: LUZOLO | D101: 70000015 | E101: 70000015 | F101: LUZOLO | G101: NSEMBOLO | H101: 32509 | I101: Male | J101: Congo | K101: 44866 | L101: Mechanic | O101: C2 | P101: 37 | Q101: 10 | R101: KM5317 – Garage | S101: Engineering | T101: Annual | U101: Annual Leave | V101: 25 days 9 to 12 years | W101: 10 | X101: 45018 | Y101: 18.76 | Z101: 2.0833333 | AA101: 0 | AB101: 0 | AC101: 20.843333 | AD101: 3286173.2
...
