Workbook

Sheet Dashboard
B2: HR KPIs DASHBOARD — EMPLOYÉS
B3: ="Export du "&TEXT(TODAY(),"dd/mm/yyyy")&" — "&COUNTA(Base!$A$3:$A$177)&" employés" -> Export du 24/07/2026 — 175 employés
B4: TOTAL EMPLOYÉS | E4: HOMMES | H4: FEMMES
B5: =COUNTA(Base!$A$3:$A$177) -> 175 | E5: =COUNTIF(Base!$J$3:$J$177,"Male")+COUNTIF(Base!$J$3:$J$177,"M") -> 148 | H5: =COUNTIF(Base!$J$3:$J$177,"Female")+COUNTIF(Base!$J$3:$J$177,"F") -> 27
B6: ÂGE MOYEN | E6: MOY. ENFANTS | H6: MARIÉS
B7: =IFERROR(ROUND(AVERAGE(Base!$L$3:$L$177),1),0) -> 40.1 | E7: =IFERROR(ROUND(AVERAGE(Base!$O$3:$O$177),2),0) -> 2.25 | H7: =COUNTIF(Base!$N$3:$N$177,"*Married*") -> 128
B9: PAR LOCALISATION | E9: PAR GENRE | H9: PAR GRADE
B10: Catégorie | C10: Effectif | E10: Catégorie | F10: Effectif | H10: Catégorie | I10: Effectif
B11: Zamba | C11: =COUNTIF(Base!$G$3:$G$177,"Zamba") -> 101 | E11: Male | F11: =COUNTIF(Base!$J$3:$J$177,"Male") -> 148 | H11: C2 | I11: =COUNTIF(Base!$E$3:$E$177,"C2") -> 38
B12: Kinshasa | C12: =COUNTIF(Base!$G$3:$G$177,"Kinshasa") -> 66 | E12: Female | F12: =COUNTIF(Base!$J$3:$J$177,"Female") -> 27 | H12: C3 | I12: =COUNTIF(Base!$E$3:$E$177,"C3") -> 24
B13: Lubudi | C13: =COUNTIF(Base!$G$3:$G$177,"Lubudi") -> 8 | E13: female | F13: =COUNTIF(Base!$J$3:$J$177,"female") -> 27 | H13: C4 | I13: =COUNTIF(Base!$E$3:$E$177,"C4") -> 19
B14: TOTAL | C14: =SUM(C11:C13) -> 175 | E14: TOTAL | F14: =SUM(F11:F13) -> 202 | H14: D2 | I14: =COUNTIF(Base!$E$3:$E$177,"D2") -> 17
H15: B2 | I15: =COUNTIF(Base!$E$3:$E$177,"B2") -> 14
B16: PAR DÉPARTEMENT | E16: PAR TRANCHE D'ÂGE | H16: C1 | I16: =COUNTIF(Base!$E$3:$E$177,"C1") -> 12
B17: Catégorie | C17: Effectif | E17: Catégorie | F17: Effectif | H17: C5 | I17: =COUNTIF(Base!$E$3:$E$177,"C5") -> 11
B18: Sales & Logistics | C18: =COUNTIF(Base!$D$3:$D$177,"Sales & Logistics") -> 35 | E18: 35-44 | F18: =COUNTIFS(Base!$L$3:$L$177,">=35",Base!$L$3:$L$177,"<45") -> 91 | H18: D1 | I18: =COUNTIF(Base!$E$3:$E$177,"D1") -> 8
B19: Corporate Admin | C19: =COUNTIF(Base!$D$3:$D$177,"Corporate Admin") -> 34 | E19: 25-34 | F19: =COUNTIFS(Base!$L$3:$L$177,">=25",Base!$L$3:$L$177,"<35") -> 39 | H19: B3 | I19: =COUNTIF(Base!$E$3:$E$177,"B3") -> 7
B20: Engineering | C20: =COUNTIF(Base!$D$3:$D$177,"Engineering") -> 28 | E20: 45-54 | F20: =COUNTIFS(Base!$L$3:$L$177,">=45",Base!$L$3:$L$177,"<55") -> 33 | H20: B4 | I20: =COUNTIF(Base!$E$3:$E$177,"B4") -> 6
B21: Production | C21: =COUNTIF(Base!$D$3:$D$177,"Production") -> 21 | E21: 55+ | F21: =COUNTIF(Base!$L$3:$L$177,">=55") -> 11 | H21: D4 | I21: =COUNTIF(Base!$E$3:$E$177,"D4") -> 6
B22: Administration | C22: =COUNTIF(Base!$D$3:$D$177,"Administration") -> 18 | E22: < 25 | F22: =COUNTIFS(Base!$L$3:$L$177,">=0",Base!$L$3:$L$177,"<25") -> 1 | H22: D5 | I22: =COUNTIF(Base!$E$3:$E$177,"D5") -> 4
B23: Quality Assurance | C23: =COUNTIF(Base!$D$3:$D$177,"Quality Assurance") -> 11 | E23: TOTAL | F23: =SUM(F18:F22) -> 175 | H23: B1 | I23: =COUNTIF(Base!$E$3:$E$177,"B1") -> 3
B24: Mining | C24: =COUNTIF(Base!$D$3:$D$177,"Mining") -> 0 | H24: B5 | I24: =COUNTIF(Base!$E$3:$E$177,"B5") -> 3
B25: Human Resources | C25: =COUNTIF(Base!$D$3:$D$177,"Human Resources") -> 7 | E25: PAR NATIONALITÉ | H25: E1 | I25: =COUNTIF(Base!$E$3:$E$177,"E1") -> 1
B26: Packaging & Logistics | C26: =COUNTIF(Base!$D$3:$D$177,"Packaging & Logistics") -> 5 | E26: Catégorie | F26: Effectif | H26: E2 | I26: =COUNTIF(Base!$E$3:$E$177,"E2") -> 1
B27: Risk & Environment | C27: =COUNTIF(Base!$D$3:$D$177,"Risk & Environment") -> 5 | E27: Congolese | F27: =COUNTIF(Base!$M$3:$M$177,"Congolese") -> 169 | H27: E4 | I27: =COUNTIF(Base!$E$3:$E$177,"E4") -> 1
B28: Finance | C28: =COUNTIF(Base!$D$3:$D$177,"Finance") -> 2 | E28: congolese | F28: =COUNTIF(Base!$M$3:$M$177,"congolese") -> 169 | H28: TOTAL | I28: =SUM(I11:I27) -> 175
B29: TOTAL | C29: =SUM(C18:C28) -> 166 | E29: Kenyan | F29: =COUNTIF(Base!$M$3:$M$177,"Kenyan") -> 3
E30: Cameroonian | F30: =COUNTIF(Base!$M$3:$M$177,"Cameroonian") -> 2
E31: Ivorian | F31: =COUNTIF(Base!$M$3:$M$177,"Ivorian") -> 1
E32: TOTAL | F32: =SUM(F27:F31) -> 344
B34: SORTIES (EXIT)
B35: Total sorties | C35: =COUNTA(EXIT!$A$3:$A$3) -> 1
B36: Motif | C36: Effectif
B37: Demission | C37: =COUNTIF(EXIT!$AD$3:$AD$3,"Demission") -> 1
B38: Licenciement | C38: =COUNTIF(EXIT!$AD$3:$AD$3,"Licenciement") -> 0
B39: Retraite | C39: =COUNTIF(EXIT!$AD$3:$AD$3,"Retraite") -> 0
B40: Fin de contrat | C40: =COUNTIF(EXIT!$AD$3:$AD$3,"Fin de contrat") -> 0
B41: TOTAL | C41: =SUM(C37:C40) -> 1

Sheet Base
A1: EMPLOYEE BASE
A2: MATRICULE | B2: COMPANY | C2: COMPLET NAME | D2: DEPARTMENT | E2: GRADE | F2: JOB TITLE | G2: LOCALISATION | H2: CENTER DES COUTS | I2: Appointment Date | J2: Gender | K2: Date of Birth | L2: Age | M2: Nationality | N2: Marital Status | O2: number of children | P2: Personnal Area | Q2: Employee SubGroup | R2: Payroll Area | S2: Payroll periode | T2: Line Manager Name | U2: Line manager position
A3: 70000002 | B3: PPC Barnet DRC Manufacturing | C3: MBODI BAUSHILE GAEL | D3: Administration | E3: D2 | F3: Site Manager | G3: Lubudi | H3: DL5110 | I3: 41852 | J3: Male | K3: 31575 | L3: =DATEDIF(K3,TODAY(),"Y") -> 40 | M3: Congolese | N3: Married | O3: 3 | P3: DRC | Q3: Zamba | R3: Permanent | S3: Monthly | T3: KABEYA KABENGELE Tresor Michel | U3: =IFERROR(VLOOKUP(T3,Base!$C$3:$F$177,4,FALSE),"Production Manager") -> Production Manager
A4: 70000008 | B4: PPC Barnet DRC Manufacturing | C4: MUAKASA NSONI SERGE | D4: Human Resources | E4: C4 | F4: Estate Officer | G4: Zamba | H4: KM5631 | I4: 42099 | J4: Male | K4: 28524 | L4: =DATEDIF(K4,TODAY(),"Y") -> 48 | M4: Congolese | N4: Married | O4: 4 | P4: DRC | Q4: Zamba | R4: Permanent | S4: Monthly | T4: ZAKUANI BAHATI BENNY | U4: =IFERROR(VLOOKUP(T4,Base!$C$3:$F$177,4,FALSE),"Plant HR Manager") -> Talent & Development Manager
A5: 70000009 | B5: PPC Barnet DRC Manufacturing | C5: ZODULUA GADUA Jean Jacques | D5: Corporate Admin | E5: B2 | F5: Driver | G5: Kinshasa | H5: KC8710 | I5: 42135 | J5: Male | K5: 25429 | L5: =DATEDIF(K5,TODAY(),"Y") -> 56 | M5: Congolese | N5: Married | O5: 2 | P5: DRC | Q5: Kinshasa | R5: Permanent | S5: Monthly | T5: Lisangola Marie Jose | U5: =IFERROR(VLOOKUP(T5,Base!$C$3:$F$177,4,FALSE),"Facilities coordinator and adm (HQ)") -> Facilities coordinator and adm (HQ)
A6: 70000011 | B6: PPC Barnet DRC Manufacturing | C6: KIMBANZI FEINTA BOVICK | D6: Sales & Logistics | E6: C4 | F6: Senior Sales Consultant | G6: Zamba | H6: KC6111 | I6: 42240 | J6: Male | K6: 25330 | L6: =DATEDIF(K6,TODAY(),"Y") -> 57 | M6: Congolese | N6: Married | O6: 4 | P6: DRC | Q6: Kwango | R6: Permanent | S6: Monthly | T6: Bashige Rurabura Jean-Pierre | U6: =IFERROR(VLOOKUP(T6,Base!$C$3:$F$177,4,FALSE),"Regional Sales Manager") -> Regional Sales Manager
A7: 70000013 | B7: PPC Barnet DRC Quarrying | C7: KUASA KINSIONA CHRISPIN | D7: Mining | E7: B2 | F7: Drilling Operator | G7: Zamba | H7: KQ1010 | I7: 42240 | J7: Male | K7: 30277 | L7: =DATEDIF(K7,TODAY(),"Y") -> 43 | M7: Congolese | N7: Married | O7: 5 | P7: DRC | Q7: Zamba | R7: Permanent | S7: Monthly | T7: LONGO ZOLA CHRISPIN | U7: =IFERROR(VLOOKUP(T7,Base!$C$3:$F$177,4,FALSE),"Shift Supervisor/ blaster") -> Shift Supervisor
A8: 70000015 | B8: PPC Barnet DRC Manufacturing | C8: LUZOLO NSEMBOLO THOMAS | D8: Engineering | E8: C2 | F8: Mechanic | G8: Zamba | H8: KM5317 | I8: 42286 | J8: Male | K8: 32509 | L8: =DATEDIF(K8,TODAY(),"Y") -> 37 | M8: Congolese | N8: Married | O8: 7 | P8: DRC | Q8: Zamba | R8: Permanent | S8: Monthly | T8: Mechanical Engineer | U8: =IFERROR(VLOOKUP(T8,Base!$C$3:$F$177,4,FALSE),"Mechanical Engineer") -> Mechanical Engineer
A9: 70000019 | B9: PPC Barnet DRC Manufacturing | C9: BANGULI KIESSE SANDRINE | D9: Corporate Admin | E9: D1 | F9: Payroll and Admin Manager | G9: Kinshasa | H9: KC8710 | I9: 41771 | J9: Female | K9: 28799 | L9: =DATEDIF(K9,TODAY(),"Y") -> 47 | M9: Congolese | N9: Married | O9: 0 | P9: DRC | Q9: Kinshasa | R9: Permanent | S9: Monthly | T9: Carine Ewuli | U9: =IFERROR(VLOOKUP(T9,Base!$C$3:$F$177,4,FALSE),"Head of HR") -> Head of HR
A10: 70000021 | B10: PPC Barnet DRC Manufacturing | C10: LISANGOLA YOWALI Marie-Josee | D10: Corporate Admin | E10: C4 | F10: Facilities Officer | G10: Kinshasa | H10: KC8710 | I10: 41771 | J10: Female | K10: 29642 | L10: =DATEDIF(K10,TODAY(),"Y") -> 45 | M10: Congolese | N10: Married | O10: 2 | P10: DRC | Q10: Kinshasa | R10: Permanent | S10: Monthly | T10: Kiesse Banguli | U10: =IFERROR(VLOOKUP(T10,Base!$C$3:$F$177,4,FALSE),"Payroll and Admin Manager") -> Payroll and Admin Manager
A11: 70000022 | B11: PPC Barnet DRC Manufacturing | C11: MUNANGA DINA CARINE | D11: Sales & Logistics | E11: C5 | F11: Customer Demand Supply Planner | G11: Kinshasa | H11: KC6312 | I11: 41771 | J11: Female | K11: 29186 | L11: =DATEDIF(K11,TODAY(),"Y") -> 46 | M11: Congolese | N11: Married | O11: 2 | P11: DRC | Q11: Kinshasa | R11: Permanent | S11: Monthly | T11: 0 | U11: =IFERROR(VLOOKUP(T11,Base!$C$3:$F$177,4,FALSE),"Lead Customer Excellence") -> Lead Customer Excellence
A12: 70000023 | B12: PPC Barnet DRC Manufacturing | C12: BANGA BANGA APEA ONESIME | D12: Corporate Admin | E12: B2 | F12: Driver | G12: Kinshasa | H12: KC8710 | I12: 41913 | J12: Male | K12: 25208 | L12: =DATEDIF(K12,TODAY(),"Y") -> 57 | M12: Congolese | N12: Married | O12: 2 | P12: DRC | Q12: Kinshasa | R12: Permanent | S12: Monthly | T12: Lisangola Marie Jose | U12: =IFERROR(VLOOKUP(T12,Base!$C$3:$F$177,4,FALSE),"Facilities coordinator and adm (HQ)") -> Facilities coordinator and adm (HQ)
A13: 70000024 | B13: PPC Barnet DRC Manufacturing | C13: KITAMBO SENEMONA MEDARD | D13: Human Resources | E13: B2 | F13: Driver | G13: Zamba | H13: KM5413 | I13: 41897 | J13: Male | K13: 23836 | L13: =DATEDIF(K13,TODAY(),"Y") -> 61 | M13: Congolese | N13: Married | O13: 0 | P13: DRC | Q13: Zamba | R13: Permanent | S13: Monthly | T13: MUAKASA NSONI SERGE | U13: =IFERROR(VLOOKUP(T13,Base!$C$3:$F$177,4,FALSE),"State Officer") -> Estate Officer
A14: 70000026 | B14: PPC Barnet DRC Manufacturing | C14: KABANGU MUTAMBAYI CHARLIE | D14: Production | E14: C3 | F14: Shift Supervisor | G14: Zamba | H14: KM4421 | I14: 42317 | J14: Male | K14: 32392 | L14: =DATEDIF(K14,TODAY(),"Y") -> 37 | M14: Congolese | N14: Married | O14: 2 | P14: DRC | Q14: Zamba | R14: Permanent | S14: Monthly | T14: KABEYA KABENGELE Tresor Michel | U14: =IFERROR(VLOOKUP(T14,Base!$C$3:$F$177,4,FALSE),"Production Manager") -> Production Manager
A15: 70000027 | B15: PPC Barnet DRC Manufacturing | C15: KABEYA KABENGELE Tresor Michel | D15: Production | E15: D4 | F15: Production Manager | G15: Zamba | H15: KM5110 | I15: 42317 | J15: Male | K15: 31255 | L15: =DATEDIF(K15,TODAY(),"Y") -> 40 | M15: Congolese | N15: Married | O15: 0 | P15: DRC | Q15: Zamba | R15: Permanent | S15: Monthly | T15: Andrew Molonga | U15: =IFERROR(VLOOKUP(T15,Base!$C$3:$F$177,4,FALSE),"Plant Manager") -> Plant Manager
A16: 70000028 | B16: PPC Barnet DRC Manufacturing | C16: KADIMOYO ILUNGA YVAN | D16: Production | E16: D1 | F16: Production Superintendent | G16: Zamba | H16: KM4421 | I16: 42317 | J16: Male | K16: 33504 | L16: =DATEDIF(K16,TODAY(),"Y") -> 34 | M16: Congolese | N16: Married | O16: 1 | P16: DRC | Q16: Zamba | R16: Permanent | S16: Monthly | T16: Michel Kabeya | U16: =IFERROR(VLOOKUP(T16,Base!$C$3:$F$177,4,FALSE),"Production Manager") -> Production Manager
A17: 70000029 | B17: PPC Barnet DRC Manufacturing | C17: MAPHASI VANGU PHILIPPE | D17: Production | E17: C3 | F17: Production Shift Supervisor | G17: Zamba | H17: KM4510 | I17: 42317 | J17: Male | K17: 30405 | L17: =DATEDIF(K17,TODAY(),"Y") -> 43 | M17: Congolese | N17: Married | O17: 4 | P17: DRC | Q17: Zamba | R17: Permanent | S17: Monthly | T17: Yvan Kadimoyo | U17: =IFERROR(VLOOKUP(T17,Base!$C$3:$F$177,4,FALSE),"Production Superintendent") -> Production Superintendent
A18: 70000030 | B18: PPC Barnet DRC Manufacturing | C18: MUBA KAYEMBE JEREMIE | D18: Packaging & Logistics | E18: C4 | F18: Packing Plant Foreman | G18: Zamba | H18: KM4610 | I18: 42317 | J18: Male | K18: 32730 | L18: =DATEDIF(K18,TODAY(),"Y") -> 36 | M18: Congolese | N18: Married | O18: 2 | P18: DRC | Q18: Zamba | R18: Permanent | S18: Monthly | T18: Yvan Kadimoyo | U18: =IFERROR(VLOOKUP(T18,Base!$C$3:$F$177,4,FALSE),"Production Superintendent") -> Production Superintendent
A19: 70000032 | B19: PPC Barnet DRC Manufacturing | C19: NEMWANDJARE PERO PHILEMON | D19: Administration | E19: C5 | F19: Junior Process Engineer | G19: Zamba | H19: KM5910 | I19: 42317 | J19: Male | K19: 32748 | L19: =DATEDIF(K19,TODAY(),"Y") -> 36 | M19: Congolese | N19: Married | O19: 2 | P19: DRC | Q19: Zamba | R19: Permanent | S19: Monthly | T19: Parician Ucchi | U19: =IFERROR(VLOOKUP(T19,Base!$C$3:$F$177,4,FALSE),"Process Engineer") -> Process Engineer
A20: 70000033 | B20: PPC Barnet DRC Manufacturing | C20: UUCHI UMIRAMBE PARICIAN | D20: Administration | E20: D1 | F20: Optimisation Process Engineer | G20: Zamba | H20: KM5910 | I20: 42317 | J20: Male | K20: 32408 | L20: =DATEDIF(K20,TODAY(),"Y") -> 37 | M20: Congolese | N20: Married | O20: 3 | P20: DRC | Q20: Zamba | R20: Permanent | S20: Monthly | T20: Andrew Molonga | U20: =IFERROR(VLOOKUP(T20,Base!$C$3:$F$177,4,FALSE),"Plant Manager") -> Plant Manager
A21: 70000034 | B21: PPC Barnet DRC Manufacturing | C21: MULOLO KANKOLONGO MANIX | D21: Corporate Admin | E21: D2 | F21: IT Manager | G21: Kinshasa | H21: KC8414 | I21: 42338 | J21: Male | K21: 31762 | L21: =DATEDIF(K21,TODAY(),"Y") -> 39 | M21: Congolese | N21: Married | O21: 3 | P21: DRC | Q21: Kinshasa | R21: Permanent | S21: Monthly | T21: Cedric Muzadi | U21: =IFERROR(VLOOKUP(T21,Base!$C$3:$F$177,4,FALSE),"Head of Finance") -> Head of Finance
A22: 70000038 | B22: PPC Barnet DRC Manufacturing | C22: MACHARIA KINYANJUI SIMON | D22: Engineering | E22: D1 | F22: Electrical & Instrumentation Engineer | G22: Zamba | H22: KM5310 | I22: 42430 | J22: Male | K22: 29048 | L22: =DATEDIF(K22,TODAY(),"Y") -> 47 | M22: Kenyan | N22: Single | O22: 0 | P22: DRC | Q22: Zamba | R22: Permanent | S22: Monthly | T22: Jack Ilondo | U22: =IFERROR(VLOOKUP(T22,Base!$C$3:$F$177,4,FALSE),"Engineering Manager") -> Engineering Manager
A23: 70000040 | B23: PPC Barnet DRC Manufacturing | C23: ILONDO LIKOMBA Jack Lethycien | D23: Engineering | E23: D4 | F23: Engineering Manager | G23: Zamba | H23: KM5310 | I23: 42471 | J23: Male | K23: 31855 | L23: =DATEDIF(K23,TODAY(),"Y") -> 39 | M23: Congolese | N23: Married | O23: 3 | P23: DRC | Q23: Zamba | R23: Permanent | S23: Monthly | T23: Andrew Molonga | U23: =IFERROR(VLOOKUP(T23,Base!$C$3:$F$177,4,FALSE),"Plant Manager") -> Plant Manager
A24: 70000042 | B24: PPC Barnet DRC Quarrying | C24: NZAZI KALUZAKI TOUBI | D24: Mining | E24: B2 | F24: Drilling Operator | G24: Zamba | H24: KQ1010 | I24: 42499 | J24: Male | K24: 25820 | L24: =DATEDIF(K24,TODAY(),"Y") -> 55 | M24: Congolese | N24: Single | O24: 5 | P24: DRC | Q24: Zamba | R24: Permanent | S24: Monthly | T24: LONGO ZOLA CHRISPIN | U24: =IFERROR(VLOOKUP(T24,Base!$C$3:$F$177,4,FALSE),"Mining Supervisor/blaster") -> Shift Supervisor
A25: 70000043 | B25: PPC Barnet DRC Manufacturing | C25: MAKIVOVI KEVENA EDDO | D25: Risk & Environment | E25: C2 | F25: Safety Officer | G25: Zamba | H25: KM5811 | I25: 42499 | J25: Male | K25: 26131 | L25: =DATEDIF(K25,TODAY(),"Y") -> 55 | M25: Congolese | N25: Married | O25: 6 | P25: DRC | Q25: Zamba | R25: Permanent | S25: Monthly | T25: Mobile Equipment Operator | U25: =IFERROR(VLOOKUP(T25,Base!$C$3:$F$177,4,FALSE),"Mining Supervisor/blaster") -> Mining Supervisor/blaster
A26: 70000045 | B26: PPC Barnet DRC Manufacturing | C26: BILONDA KAZADI DIANE | D26: Sales & Logistics | E26: C5 | F26: Senior Regional Sales Consultant Construction, Ready Mix & Indus | G26: Kinshasa | H26: KC6111 | I26: 42506 | J26: Female | K26: 32197 | L26: =DATEDIF(K26,TODAY(),"Y") -> 38 | M26: Congolese | N26: Married | O26: 0 | P26: DRC | Q26: Kinshasa | R26: Permanent | S26: Monthly | T26: KILOSO SANDA HELENA | U26: =IFERROR(VLOOKUP(T26,Base!$C$3:$F$177,4,FALSE),"Regional Sales Manager") -> Senior Regional Sales Consultant Retail & Funa
A27: 70000046 | B27: PPC Barnet DRC Manufacturing | C27: MUKENDI KABONGO PATRICK | D27: Engineering | E27: D1 | F27: Mechanical Engineer | G27: Zamba | H27: KM5311 | I27: 42522 | J27: Male | K27: 29323 | L27: =DATEDIF(K27,TODAY(),"Y") -> 46 | M27: Congolese | N27: Married | O27: 5 | P27: DRC | Q27: Zamba | R27: Permanent | S27: Monthly | T27: Jack Ilondo | U27: =IFERROR(VLOOKUP(T27,Base!$C$3:$F$177,4,FALSE),"Engineering manager") -> Engineering manager
A28: 70000048 | B28: PPC Barnet DRC Manufacturing | C28: KILOSO SANDA HELENA | D28: Sales & Logistics | E28: C5 | F28: Senior Regional Sales Consultant Retail & Funa | G28: Kinshasa | H28: KC6111 | I28: 42522 | J28: Female | K28: 32543 | L28: =DATEDIF(K28,TODAY(),"Y") -> 37 | M28: Congolese | N28: Single | O28: 0 | P28: DRC | Q28: Kinshasa | R28: Permanent | S28: Monthly | T28: Serge Bazola | U28: =IFERROR(VLOOKUP(T28,Base!$C$3:$F$177,4,FALSE),"Head of Business Development") -> Head of Business Development
A29: 70000049 | B29: PPC Barnet DRC Manufacturing | C29: PONGO PONGO LIWANDA LUTE CHARLES | D29: Quality Assurance | E29: D2 | F29: Quality Assurance Manager | G29: Zamba | H29: KM5510 | I29: 42515 | J29: Male | K29: 23282 | L29: =DATEDIF(K29,TODAY(),"Y") -> 62 | M29: Congolese | N29: Married | O29: 6 | P29: DRC | Q29: Zamba | R29: Permanent | S29: Monthly | T29: Andrew Molonga | U29: =IFERROR(VLOOKUP(T29,Base!$C$3:$F$177,4,FALSE),"Plant Manager") -> Plant Manager
A30: 70000050 | B30: PPC Barnet DRC Manufacturing | C30: TANUI KIPRUTO ELIAS | D30: Administration | E30: D4 | F30: Project Manager | G30: Zamba | H30: KM8910 | I30: 42562 | J30: Male | K30: 27214 | L30: =DATEDIF(K30,TODAY(),"Y") -> 52 | M30: Kenyan | N30: Married | O30: 1 | P30: DRC | Q30: Zamba | R30: Permanent | S30: Monthly | T30: Patrick Kahasha | U30: =IFERROR(VLOOKUP(T30,Base!$C$3:$F$177,4,FALSE),"Managing Director") -> Managing Director
A31: 70000051 | B31: PPC Barnet DRC Manufacturing | C31: DIAKIESE LUTUTALA GRACE | D31: Sales & Logistics | E31: C2 | F31: Sales Consultant Tshangu | G31: Kinshasa | H31: KC6111 | I31: 42569 | J31: Female | K31: 34355 | L31: =DATEDIF(K31,TODAY(),"Y") -> 32 | M31: Congolese | N31: Married | O31: 4 | P31: DRC | Q31: Kinshasa | R31: Permanent | S31: Monthly | T31: KILOSO SANDA HELENA | U31: =IFERROR(VLOOKUP(T31,Base!$C$3:$F$177,4,FALSE),"Regional Sales Manager") -> Senior Regional Sales Consultant Retail & Funa
A32: 70000052 | B32: PPC Barnet DRC Manufacturing | C32: BAYISA SIMON DIDIER | D32: Engineering | E32: C2 | F32: Fitter & Turner | G32: Zamba | H32: KM5310 | I32: 42569 | J32: Male | K32: 29768 | L32: =DATEDIF(K32,TODAY(),"Y") -> 45 | M32: Congolese | N32: Married | O32: 5 | P32: DRC | Q32: Zamba | R32: Permanent | S32: Monthly | T32: Patrick Mukendi | U32: =IFERROR(VLOOKUP(T32,Base!$C$3:$F$177,4,FALSE),"Mechanical Foreman") -> Mechanical Foreman
A33: 70000056 | B33: PPC Barnet DRC Manufacturing | C33: NSAKALA KUNIEKI GAYLOR | D33: Production | E33: B4 | F33: Operator Support | G33: Zamba | H33: KM4510 | I33: 42632 | J33: Male | K33: 30206 | L33: =DATEDIF(K33,TODAY(),"Y") -> 43 | M33: Congolese | N33: Married | O33: 4 | P33: DRC | Q33: Zamba | R33: Permanent | S33: Monthly | T33: MPONGO KOLONGO LEON | U33: =IFERROR(VLOOKUP(T33,Base!$C$3:$F$177,4,FALSE),"Packing/ Loading shift supervisor") -> Buyer
A34: 70000057 | B34: PPC Barnet DRC Manufacturing | C34: LUTONADIO NGUAWANI OLIVIER | D34: Packaging & Logistics | E34: C2 | F34: Packing/Loading Shift Supervisor | G34: Zamba | H34: KM4610 | I34: 42632 | J34: Male | K34: 32768 | L34: =DATEDIF(K34,TODAY(),"Y") -> 36 | M34: Congolese | N34: Single | O34: 2 | P34: DRC | Q34: Zamba | R34: Permanent | S34: Monthly | T34: ADHULE NYADRIA JOEL | U34: =IFERROR(VLOOKUP(T34,Base!$C$3:$F$177,4,FALSE),"Packing Plant Manager") -> Safety Manager
A35: 70000058 | B35: PPC Barnet DRC Manufacturing | C35: TULENGI KASIAMA REAGAN | D35: Engineering | E35: C2 | F35: Fitter & Crane Specialist | G35: Zamba | H35: KM5310 | I35: 42632 | J35: Male | K35: 31705 | L35: =DATEDIF(K35,TODAY(),"Y") -> 39 | M35: Congolese | N35: Married | O35: 5 | P35: DRC | Q35: Zamba | R35: Permanent | S35: Monthly | T35: Patrick Mukendi | U35: =IFERROR(VLOOKUP(T35,Base!$C$3:$F$177,4,FALSE),"Mechanical Foreman") -> Mechanical Foreman
A36: 70000059 | B36: PPC Barnet DRC Manufacturing | C36: LUZOLAWO MANKELA RODRIGUE | D36: Packaging & Logistics | E36: C2 | F36: Packing/Loading Shift Supervisor | G36: Zamba | H36: KM4610 | I36: 42632 | J36: Male | K36: 31885 | L36: =DATEDIF(K36,TODAY(),"Y") -> 39 | M36: Congolese | N36: Married | O36: 2 | P36: DRC | Q36: Zamba | R36: Permanent | S36: Monthly | T36: Gael Mbodi | U36: =IFERROR(VLOOKUP(T36,Base!$C$3:$F$177,4,FALSE),"Packing Plant Superintendant") -> Packing Plant Superintendant
A37: 70000061 | B37: PPC Barnet DRC Manufacturing | C37: NZUZI TABILA JOEL | D37: Packaging & Logistics | E37: C2 | F37: Packing/Loading Shift Supervisor | G37: Zamba | H37: KM4610 | I37: 42632 | J37: Male | K37: 25800 | L37: =DATEDIF(K37,TODAY(),"Y") -> 55 | M37: Congolese | N37: Married | O37: 5 | P37: DRC | Q37: Zamba | R37: Permanent | S37: Monthly | T37: Gael Mbodi | U37: =IFERROR(VLOOKUP(T37,Base!$C$3:$F$177,4,FALSE),"Packing Plant Superintendant") -> Packing Plant Superintendant
A38: 70000063 | B38: PPC Barnet DRC Manufacturing | C38: MUANDA BALOKI JISCA | D38: Production | E38: C3 | F38: Shift Supervisor | G38: Zamba | H38: KM4421 | I38: 42632 | J38: Male | K38: 30284 | L38: =DATEDIF(K38,TODAY(),"Y") -> 43 | M38: Congolese | N38: Married | O38: 3 | P38: DRC | Q38: Zamba | R38: Permanent | S38: Monthly | T38: Yvan Kadimoyo | U38: =IFERROR(VLOOKUP(T38,Base!$C$3:$F$177,4,FALSE),"Production Superintendent") -> Production Superintendent
A39: 70000064 | B39: PPC Barnet DRC Manufacturing | C39: KALUNGA MASELE RAMSES | D39: Production | E39: C1 | F39: Process Operator | G39: Zamba | H39: KM4421 | I39: 42632 | J39: Male | K39: 31917 | L39: =DATEDIF(K39,TODAY(),"Y") -> 39 | M39: Congolese | N39: Married | O39: 2 | P39: DRC | Q39: Zamba | R39: Permanent | S39: Monthly | T39: Jeremie Muba | U39: =IFERROR(VLOOKUP(T39,Base!$C$3:$F$177,4,FALSE),"Shift Supervisor") -> Shift Supervisor
A40: 70000067 | B40: PPC Barnet DRC Manufacturing | C40: MPONGO KOLONGO LEON | D40: Sales & Logistics | E40: C3 | F40: Buyer | G40: Zamba | H40: KC8813 | I40: 42632 | J40: Male | K40: 33425 | L40: =DATEDIF(K40,TODAY(),"Y") -> 35 | M40: Congolese | N40: Single | O40: 1 | P40: DRC | Q40: Zamba | R40: Permanent | S40: Monthly | T40: Nelly Biganiro | U40: =IFERROR(VLOOKUP(T40,Base!$C$3:$F$177,4,FALSE),"Purchasing Manager") -> Purchasing Manager
A41: 70000068 | B41: PPC Barnet DRC Manufacturing | C41: DUNGA KUEKUBATU PLATINI | D41: Production | E41: C1 | F41: Process Operator | G41: Zamba | H41: KM4510 | I41: 42632 | J41: Male | K41: 32582 | L41: =DATEDIF(K41,TODAY(),"Y") -> 37 | M41: Congolese | N41: Married | O41: 3 | P41: DRC | Q41: Zamba | R41: Permanent | S41: Monthly | T41: Jeremie Muba | U41: =IFERROR(VLOOKUP(T41,Base!$C$3:$F$177,4,FALSE),"Shift Supervisor") -> Shift Supervisor
A42: 70000069 | B42: PPC Barnet DRC Manufacturing | C42: BAVIBIDILA MUNTANA GERVAIS | D42: Production | E42: B2 | F42: Operator Support | G42: Zamba | H42: KM4321 | I42: 42632 | J42: Male | K42: 27917 | L42: =DATEDIF(K42,TODAY(),"Y") -> 50 | M42: Congolese | N42: Married | O42: 2 | P42: DRC | Q42: Zamba | R42: Permanent | S42: Monthly | T42: Philippe Vangu | U42: =IFERROR(VLOOKUP(T42,Base!$C$3:$F$177,4,FALSE),"Shift Supervisor") -> Shift Supervisor
A43: 70000070 | B43: PPC Barnet DRC Manufacturing | C43: BITUTU NDUNGU EDER | D43: Production | E43: B2 | F43: Operator Support | G43: Zamba | H43: KM4321 | I43: 42632 | J43: Male | K43: 31105 | L43: =DATEDIF(K43,TODAY(),"Y") -> 41 | M43: Congolese | N43: Married | O43: 5 | P43: DRC | Q43: Zamba | R43: Permanent | S43: Monthly | T43: Yvan Kadimoyo | U43: =IFERROR(VLOOKUP(T43,Base!$C$3:$F$177,4,FALSE),"Shift Supervisor") -> Shift Supervisor
A44: 70000072 | B44: PPC Barnet DRC Manufacturing | C44: NDONGA NGANGULA NOEL | D44: Production | E44: C1 | F44: Process Operator | G44: Zamba | H44: KM4421 | I44: 42632 | J44: Male | K44: 33232 | L44: =DATEDIF(K44,TODAY(),"Y") -> 35 | M44: Congolese | N44: Single | O44: 0 | P44: DRC | Q44: Zamba | R44: Permanent | S44: Monthly | T44: Yvan Kadimoyo | U44: =IFERROR(VLOOKUP(T44,Base!$C$3:$F$177,4,FALSE),"Shift Supervisor") -> Shift Supervisor
A45: 70000076 | B45: PPC Barnet DRC Manufacturing | C45: NLANDU NDONGALA ERICK | D45: Quality Assurance | E45: B5 | F45: Lab Analyst | G45: Zamba | H45: KM5510 | I45: 42646 | J45: Male | K45: 29763 | L45: =DATEDIF(K45,TODAY(),"Y") -> 45 | M45: Congolese | N45: Married | O45: 4 | P45: DRC | Q45: Zamba | R45: Permanent | S45: Monthly | T45: Sosthène Kamanda | U45: =IFERROR(VLOOKUP(T45,Base!$C$3:$F$177,4,FALSE),"Senior Lab Analyst") -> Senior Lab Analyst
A46: 70000077 | B46: PPC Barnet DRC Manufacturing | C46: SAMBA ZANKEMBO CADET | D46: Quality Assurance | E46: B3 | F46: Routine Tester | G46: Zamba | H46: KM5510 | I46: 42646 | J46: Male | K46: 33577 | L46: =DATEDIF(K46,TODAY(),"Y") -> 34 | M46: Congolese | N46: Married | O46: 2 | P46: DRC | Q46: Zamba | R46: Permanent | S46: Monthly | T46: Pongo Pongo Charles | U46: =IFERROR(VLOOKUP(T46,Base!$C$3:$F$177,4,FALSE),"QA Chemist") -> QA Chemist
A47: 70000078 | B47: PPC Barnet DRC Manufacturing | C47: BATEKISA MIABANGANA NICHA | D47: Sales & Logistics | E47: C2 | F47: Customer Relationship Officer | G47: Kinshasa | H47: KC6310 | I47: 42646 | J47: Female | K47: 35405 | L47: =DATEDIF(K47,TODAY(),"Y") -> 29 | M47: Congolese | N47: Single | O47: 0 | P47: DRC | Q47: Kinshasa | R47: Permanent | S47: Monthly | T47: 0 | U47: =IFERROR(VLOOKUP(T47,Base!$C$3:$F$177,4,FALSE),"0") -> 0
A48: 70000079 | B48: PPC Barnet DRC Manufacturing | C48: DINANDI MVUMBI PHILIPPE | D48: Engineering | E48: C2 | F48: Boilermaker | G48: Zamba | H48: KM5310 | I48: 42639 | J48: Male | K48: 28178 | L48: =DATEDIF(K48,TODAY(),"Y") -> 49 | M48: Congolese | N48: Married | O48: 5 | P48: DRC | Q48: Zamba | R48: Permanent | S48: Monthly | T48: Patrick Mukendi | U48: =IFERROR(VLOOKUP(T48,Base!$C$3:$F$177,4,FALSE),"Mechanical Foreman") -> Mechanical Foreman
A49: 70000080 | B49: PPC Barnet DRC Manufacturing | C49: NSILU MALUTA NADEGE | D49: Quality Assurance | E49: B3 | F49: Physical Lab Tester | G49: Zamba | H49: KM5510 | I49: 42646 | J49: Female | K49: 32347 | L49: =DATEDIF(K49,TODAY(),"Y") -> 38 | M49: Congolese | N49: Married | O49: 2 | P49: DRC | Q49: Zamba | R49: Permanent | S49: Monthly | T49: Sosthène Kamanda | U49: =IFERROR(VLOOKUP(T49,Base!$C$3:$F$177,4,FALSE),"Senior Lab Analyst") -> Senior Lab Analyst
A50: 70000081 | B50: PPC Barnet DRC Manufacturing | C50: TANDU NKWALA BERTIN | D50: Quality Assurance | E50: B3 | F50: Routine Tester | G50: Zamba | H50: KM5510 | I50: 42646 | J50: Male | K50: 28513 | L50: =DATEDIF(K50,TODAY(),"Y") -> 48 | M50: Congolese | N50: Married | O50: 4 | P50: DRC | Q50: Zamba | R50: Permanent | S50: Monthly | T50: MUSAKO KINZONZOLI MOISE | U50: =IFERROR(VLOOKUP(T50,Base!$C$3:$F$177,4,FALSE),"QA Chemist") -> QA Chemist
A51: 70000082 | B51: PPC Barnet DRC Manufacturing | C51: FINKIDI MAYETO EDGARD | D51: Quality Assurance | E51: B3 | F51: Routine Tester | G51: Zamba | H51: KM5510 | I51: 42646 | J51: Male | K51: 30794 | L51: =DATEDIF(K51,TODAY(),"Y") -> 42 | M51: Congolese | N51: Married | O51: 5 | P51: DRC | Q51: Zamba | R51: Permanent | S51: Monthly | T51: MUSAKO KINZONZOLI MOISE | U51: =IFERROR(VLOOKUP(T51,Base!$C$3:$F$177,4,FALSE),"QA Chemist") -> QA Chemist
A52: 70000083 | B52: PPC Barnet DRC Manufacturing | C52: MUSAKO KINZONZOLI MOISE | D52: Quality Assurance | E52: C3 | F52: QA Chemist | G52: Zamba | H52: KM5510 | I52: 42644 | J52: Male | K52: 34515 | L52: =DATEDIF(K52,TODAY(),"Y") -> 32 | M52: Congolese | N52: Married | O52: 2 | P52: DRC | Q52: Zamba | R52: Permanent | S52: Monthly | T52: Charles Pongo Pongo | U52: =IFERROR(VLOOKUP(T52,Base!$C$3:$F$177,4,FALSE),"Quality Manager") -> Quality Manager
A53: 70000084 | B53: PPC Barnet DRC Manufacturing | C53: MVILAMBI BIMPALU DELVIS | D53: Quality Assurance | E53: B3 | F53: Routine Tester | G53: Zamba | H53: KM5510 | I53: 42646 | J53: Male | K53: 34125 | L53: =DATEDIF(K53,TODAY(),"Y") -> 33 | M53: Congolese | N53: Single | O53: 2 | P53: DRC | Q53: Zamba | R53: Permanent | S53: Monthly | T53: Moise Musako | U53: =IFERROR(VLOOKUP(T53,Base!$C$3:$F$177,4,FALSE),"QA Chemist") -> QA Chemist
A54: 70000085 | B54: PPC Barnet DRC Manufacturing | C54: EKWALANGA MONGALIKITA BONIFACE | D54: Corporate Admin | E54: D4 | F54: Financial Controller | G54: Kinshasa | H54: KC8412 | I54: 42653 | J54: Male | K54: 32706 | L54: =DATEDIF(K54,TODAY(),"Y") -> 37 | M54: Congolese | N54: Married | O54: 3 | P54: DRC | Q54: Kinshasa | R54: Permanent | S54: Monthly | T54: Cedric Muzadi | U54: =IFERROR(VLOOKUP(T54,Base!$C$3:$F$177,4,FALSE),"Head of Finance") -> Head of Finance
A55: 70000087 | B55: PPC Barnet DRC Manufacturing | C55: ZIWANUKA KIANGEBENI MITHA | D55: Engineering | E55: B4 | F55: Planning Administrator | G55: Zamba | H55: KM5310 | I55: 42653 | J55: Female | K55: 30793 | L55: =DATEDIF(K55,TODAY(),"Y") -> 42 | M55: Congolese | N55: Single | O55: 2 | P55: DRC | Q55: Zamba | R55: Permanent | S55: Monthly | T55: Mpay Rufin | U55: =IFERROR(VLOOKUP(T55,Base!$C$3:$F$177,4,FALSE),"Planner") -> Planner
A56: 70000088 | B56: PPC Barnet DRC Manufacturing | C56: TULOMBA BALELE OVIE | D56: Engineering | E56: C2 | F56: Electrician | G56: Zamba | H56: KM5310 | I56: 42653 | J56: Male | K56: 33662 | L56: =DATEDIF(K56,TODAY(),"Y") -> 34 | M56: Congolese | N56: Married | O56: 5 | P56: DRC | Q56: Zamba | R56: Permanent | S56: Monthly | T56: Marcel Ngoyi | U56: =IFERROR(VLOOKUP(T56,Base!$C$3:$F$177,4,FALSE),"Electrical Foreman") -> Electrical Foreman
A57: 70000091 | B57: PPC Barnet DRC Manufacturing | C57: NGOYI MUIKULU MARCEL | D57: Engineering | E57: C4 | F57: Electrical Foreman | G57: Zamba | H57: KM5310 | I57: 42660 | J57: Male | K57: 27307 | L57: =DATEDIF(K57,TODAY(),"Y") -> 51 | M57: Congolese | N57: Married | O57: 2 | P57: DRC | Q57: Zamba | R57: Permanent | S57: Monthly | T57: Simon Macharia | U57: =IFERROR(VLOOKUP(T57,Base!$C$3:$F$177,4,FALSE),"Electrical & instrumentation Engineer") -> Electrical & instrumentation Engineer
A58: 70000093 | B58: PPC Barnet DRC Manufacturing | C58: MBANGI MAKULENDA ANDRE | D58: Engineering | E58: B2 | F58: Handyman Electrical | G58: Zamba | H58: KM5310 | I58: 42660 | J58: Male | K58: 25543 | L58: =DATEDIF(K58,TODAY(),"Y") -> 56 | M58: Congolese | N58: Married | O58: 5 | P58: DRC | Q58: Zamba | R58: Permanent | S58: Monthly | T58: Patrick Mukendi | U58: =IFERROR(VLOOKUP(T58,Base!$C$3:$F$177,4,FALSE),"Mechanical Foreman") -> Mechanical Foreman
A59: 70000094 | B59: PPC Barnet DRC Manufacturing | C59: KADIMA TSHONDO Ben Paulin | D59: Sales & Logistics | E59: C5 | F59: Senior Regional Sales Consultant | G59: Kinshasa | H59: KC6113 | I59: 42662 | J59: Male | K59: 31638 | L59: =DATEDIF(K59,TODAY(),"Y") -> 39 | M59: Congolese | N59: Married | O59: 3 | P59: DRC | Q59: Kinshasa | R59: Permanent | S59: Monthly | T59: Bashige Rurabura Jean-Pierre | U59: =IFERROR(VLOOKUP(T59,Base!$C$3:$F$177,4,FALSE),"Regional Sales Manager") -> Regional Sales Manager
A60: 70000096 | B60: PPC Barnet DRC Manufacturing | C60: LUKUAYI MANKUENIA OSEE | D60: Production | E60: B1 | F60: Operator Support | G60: Zamba | H60: KM4510 | I60: 42679 | J60: Male | K60: 34280 | L60: =DATEDIF(K60,TODAY(),"Y") -> 32 | M60: Congolese | N60: Married | O60: 4 | P60: DRC | Q60: Zamba | R60: Permanent | S60: Monthly | T60: KABEYA KABENGELE Tresor Michel | U60: =IFERROR(VLOOKUP(T60,Base!$C$3:$F$177,4,FALSE),"Production Manager") -> Production Manager
A61: 70000097 | B61: PPC Barnet DRC Quarrying | C61: NKOSI LIMA MASUDI BIENVENU | D61: Mining | E61: B2 | F61: Mining Mobile Equipment Operator | G61: Zamba | H61: KQ1910 | I61: 42679 | J61: Male | K61: 32060 | L61: =DATEDIF(K61,TODAY(),"Y") -> 38 | M61: Congolese | N61: Single | O61: 4 | P61: DRC | Q61: Zamba | R61: Permanent | S61: Monthly | T61: LONGO ZOLA CHRISPIN | U61: =IFERROR(VLOOKUP(T61,Base!$C$3:$F$177,4,FALSE),"Shift Supervisor/ blaster") -> Shift Supervisor
A62: 70000099 | B62: PPC Barnet DRC Manufacturing | C62: DIMENENE LUZAYADIO PAMPHIL | D62: Production | E62: B1 | F62: Production Mobile Equipment Operator | G62: Zamba | H62: KM4421 | I62: 42679 | J62: Male | K62: 26447 | L62: =DATEDIF(K62,TODAY(),"Y") -> 54 | M62: Congolese | N62: Married | O62: 4 | P62: DRC | Q62: Zamba | R62: Permanent | S62: Monthly | T62: Yvan Kadimoyo | U62: =IFERROR(VLOOKUP(T62,Base!$C$3:$F$177,4,FALSE),"Production Superintendent") -> Production Superintendent
A63: 70000100 | B63: PPC Barnet DRC Manufacturing | C63: LUFUA LUA NGUALA JOSEPH | D63: Sales & Logistics | E63: C4 | F63: Senior Sales Consultant Tshangu | G63: Kinshasa | H63: KC6111 | I63: 42679 | J63: Male | K63: 27917 | L63: =DATEDIF(K63,TODAY(),"Y") -> 50 | M63: Congolese | N63: Married | O63: 8 | P63: DRC | Q63: Equateur | R63: Permanent | S63: Monthly | T63: Bashige Rurabura Jean-Pierre | U63: =IFERROR(VLOOKUP(T63,Base!$C$3:$F$177,4,FALSE),"Regional Sales Manager") -> Regional Sales Manager
A64: 70000101 | B64: PPC Barnet DRC Manufacturing | C64: KANAHUNA LUZAYADIO MIRTHA | D64: Corporate Admin | E64: B4 | F64: Invoice Verification Clerk | G64: Zamba | H64: KC8411 | I64: 42679 | J64: Female | K64: 30130 | L64: =DATEDIF(K64,TODAY(),"Y") -> 44 | M64: Congolese | N64: Married | O64: 4 | P64: DRC | Q64: Zamba | R64: Permanent | S64: Monthly | T64: Cyril Kone | U64: =IFERROR(VLOOKUP(T64,Base!$C$3:$F$177,4,FALSE),"Finance Manager") -> Finance Manager
A65: 70000102 | B65: PPC Barnet DRC Quarrying | C65: LUMANISA WASOLOKELE CEDRICK | D65: Mining | E65: B1 | F65: Drilling Operator | G65: Zamba | H65: KQ1010 | I65: 42679 | J65: Male | K65: 30322 | L65: =DATEDIF(K65,TODAY(),"Y") -> 43 | M65: Congolese | N65: Married | O65: 7 | P65: DRC | Q65: Zamba | R65: Permanent | S65: Monthly | T65: LONGO ZOLA CHRISPIN | U65: =IFERROR(VLOOKUP(T65,Base!$C$3:$F$177,4,FALSE),"Shift Supervisor/ blaster") -> Shift Supervisor
A66: 70000104 | B66: PPC Barnet DRC Manufacturing | C66: NGOMA NALOLO DIEU | D66: Engineering | E66: C3 | F66: Lead Fitter | G66: Zamba | H66: KM5310 | I66: 42679 | J66: Male | K66: 32600 | L66: =DATEDIF(K66,TODAY(),"Y") -> 37 | M66: Congolese | N66: Single | O66: 4 | P66: DRC | Q66: Zamba | R66: Permanent | S66: Monthly | T66: Patrick Mukendi | U66: =IFERROR(VLOOKUP(T66,Base!$C$3:$F$177,4,FALSE),"Mechanical Foreman") -> Mechanical Foreman
A67: 70000107 | B67: PPC Barnet DRC Manufacturing | C67: MVUTU LUTEMBE KARINE | D67: Risk & Environment | E67: C2 | F67: OH Nurse | G67: Zamba | H67: KM5721 | I67: 42690 | J67: Female | K67: 31105 | L67: =DATEDIF(K67,TODAY(),"Y") -> 41 | M67: Congolese | N67: Married | O67: 2 | P67: DRC | Q67: Zamba | R67: Permanent | S67: Monthly | T67: Joel Adhule | U67: =IFERROR(VLOOKUP(T67,Base!$C$3:$F$177,4,FALSE),"Safety Manager") -> Safety Manager
A68: 70000109 | B68: PPC Barnet DRC Manufacturing | C68: MOLEKA GBANGA FRED | D68: Engineering | E68: C4 | F68: Mechanical Foreman | G68: Zamba | H68: KM5310 | I68: 42711 | J68: Male | K68: 33072 | L68: =DATEDIF(K68,TODAY(),"Y") -> 36 | M68: Congolese | N68: Married | O68: 5 | P68: DRC | Q68: Zamba | R68: Permanent | S68: monthly | T68: Kumarasamy | U68: =IFERROR(VLOOKUP(T68,Base!$C$3:$F$177,4,FALSE),"Mechanical Engineer") -> Mechanical Engineer
A69: 70000110 | B69: PPC Barnet DRC Manufacturing | C69: NGOMA NIMI GLODY | D69: Sales & Logistics | E69: D2 | F69: Transport Optimisation Manager | G69: Kinshasa | H69: KC8812 | I69: 42711 | J69: Male | K69: 32373 | L69: =DATEDIF(K69,TODAY(),"Y") -> 37 | M69: Congolese | N69: Married | O69: 1 | P69: DRC | Q69: Zamba | R69: Permanent | S69: Monthly | T69: Transport optimisation Manager | U69: =IFERROR(VLOOKUP(T69,Base!$C$3:$F$177,4,FALSE),"Head of Supply Chain") -> Head of Supply Chain
A70: 70000111 | B70: PPC Barnet DRC Manufacturing | C70: MANANGA MAMBULU JOSEPH | D70: Human Resources | E70: C1 | F70: CEC Officer | G70: Zamba | H70: KM5416 | I70: 42711 | J70: Male | K70: 28924 | L70: =DATEDIF(K70,TODAY(),"Y") -> 47 | M70: Congolese | N70: Married | O70: 2 | P70: DRC | Q70: Zamba | R70: Permanent | S70: Monthly | T70: 0 | U70: =IFERROR(VLOOKUP(T70,Base!$C$3:$F$177,4,FALSE),"Plant CRO") -> Plant CRO
A71: 70000112 | B71: PPC Barnet DRC Manufacturing | C71: ADHULE NYADRIA JOEL | D71: Risk & Environment | E71: D2 | F71: Safety Manager | G71: Zamba | H71: KM5711 | I71: 42711 | J71: Male | K71: 30328 | L71: =DATEDIF(K71,TODAY(),"Y") -> 43 | M71: Congolese | N71: Married | O71: 4 | P71: DRC | Q71: Zamba | R71: Permanent | S71: Monthly | T71: Andrew Molonga | U71: =IFERROR(VLOOKUP(T71,Base!$C$3:$F$177,4,FALSE),"Plant Manager") -> Plant Manager
A72: 70000115 | B72: PPC Barnet DRC Manufacturing | C72: ONOSAMBA LUNDI LUNDI | D72: Engineering | E72: C2 | F72: Fitter & Turner | G72: Zamba | H72: KM5310 | I72: 42786 | J72: Male | K72: 28210 | L72: =DATEDIF(K72,TODAY(),"Y") -> 49 | M72: Congolese | N72: Married | O72: 4 | P72: DRC | Q72: Zamba | R72: Permanent | S72: Monthly | T72: Patrick Mukendi | U72: =IFERROR(VLOOKUP(T72,Base!$C$3:$F$177,4,FALSE),"Mechanical Foreman") -> Mechanical Foreman
A73: 70000116 | B73: PPC Barnet DRC Manufacturing | C73: NZUNGU ANTOINE BONHEUR | D73: Engineering | E73: C2 | F73: Boilermaker | G73: Zamba | H73: KM5310 | I73: 42788 | J73: Male | K73: 30546 | L73: =DATEDIF(K73,TODAY(),"Y") -> 42 | M73: Congolese | N73: Single | O73: 2 | P73: DRC | Q73: Zamba | R73: Permanent | S73: Monthly | T73: Patrick Mukendi | U73: =IFERROR(VLOOKUP(T73,Base!$C$3:$F$177,4,FALSE),"Mechanical Foreman") -> Mechanical Foreman
A74: 70000117 | B74: PPC Barnet DRC Manufacturing | C74: NSEKA LUGUNGU DHEINS | D74: Sales & Logistics | E74: C5 | F74: Senior Regional Sales Consultant Distribution & Wholesale | G74: Kinshasa | H74: KC6111 | I74: 42800 | J74: Male | K74: 28560 | L74: =DATEDIF(K74,TODAY(),"Y") -> 48 | M74: Congolese | N74: Married | O74: 3 | P74: DRC | Q74: Kinshasa | R74: Permanent | S74: Monthly | T74: Bashige Rurabura Jean-Pierre | U74: =IFERROR(VLOOKUP(T74,Base!$C$3:$F$177,4,FALSE),"Regional Sales Manager") -> Regional Sales Manager
A75: 70000118 | B75: PPC Barnet DRC Manufacturing | C75: KABOTO META CLEMENTINE | D75: Corporate Admin | E75: C3 | F75: Creditor Controler | G75: Kinshasa | H75: KC8411 | I75: 42858 | J75: Female | K75: 30115 | L75: =DATEDIF(K75,TODAY(),"Y") -> 44 | M75: Congolese | N75: Divorced | O75: 1 | P75: DRC | Q75: Kinshasa | R75: Permanent | S75: Monthly | T75: Boniface Ekwalanga | U75: =IFERROR(VLOOKUP(T75,Base!$C$3:$F$177,4,FALSE),"Financial controller") -> Financial controller
A76: 70000124 | B76: PPC Barnet DRC Quarrying | C76: LONGO ZOLA CHRISPIN | D76: Mining | E76: C3 | F76: Shift Supervisor | G76: Zamba | H76: KQ1023 | I76: 42240 | J76: Male | K76: 28108 | L76: =DATEDIF(K76,TODAY(),"Y") -> 49 | M76: Congolese | N76: Married | O76: 5 | P76: DRC | Q76: Zamba | R76: Permanent | S76: Monthly | T76: MPUNGWE KAPEPULA MARQUES | U76: =IFERROR(VLOOKUP(T76,Base!$C$3:$F$177,4,FALSE),"Mining Superintendant") -> Mining Superintendant
A77: 70000129 | B77: PPC Barnet DRC Quarrying | C77: KILUMONIKO DIAWAWANA RACHIE | D77: Mining | E77: B3 | F77: Mobile Equipment Operator - Grader | G77: Zamba | H77: KQ1910 | I77: 43192 | J77: Male | K77: 30536 | L77: =DATEDIF(K77,TODAY(),"Y") -> 42 | M77: Congolese | N77: Married | O77: 7 | P77: DRC | Q77: Zamba | R77: Permanent | S77: Monthly | T77: Nsuami Nsuami Elie | U77: =IFERROR(VLOOKUP(T77,Base!$C$3:$F$177,4,FALSE),"Mining Supervisor/blaster") -> Mining Supervisor/blaster
A78: 70000130 | B78: PPC Barnet DRC Manufacturing | C78: SAMBA LUINDA HONORE | D78: Corporate Admin | E78: B2 | F78: Driver | G78: Kinshasa | H78: KC8710 | I78: 43190 | J78: Male | K78: 26862 | L78: =DATEDIF(K78,TODAY(),"Y") -> 53 | M78: Congolese | N78: Married | O78: 5 | P78: DRC | Q78: Kinshasa | R78: Permanent | S78: Monthly | T78: Lisangola Marie Jose | U78: =IFERROR(VLOOKUP(T78,Base!$C$3:$F$177,4,FALSE),"Facilities coordinator and adm (HQ)") -> Facilities coordinator and adm (HQ)
A79: 70000134 | B79: PPC Barnet DRC Manufacturing | C79: KAMUNGOMA WENGA EMMANUEL | D79: Sales & Logistics | E79: C2 | F79: Customer Relationship Officer | G79: Kinshasa | H79: KC6310 | I79: 43283 | J79: Male | K79: 32874 | L79: =DATEDIF(K79,TODAY(),"Y") -> 36 | M79: Congolese | N79: Single | O79: 0 | P79: DRC | Q79: Zamba | R79: Permanent | S79: Monthly | T79: NGOMA NIMI GLODY | U79: =IFERROR(VLOOKUP(T79,Base!$C$3:$F$177,4,FALSE),"Customer Excellence Officer") -> Transport Optimisation Manager
A80: 70000135 | B80: PPC Barnet DRC Manufacturing | C80: MUZADI LUKOKESHA CEDRIC | D80: Corporate Admin | E80: E2 | F80: Head of Finance and IT | G80: Kinshasa | H80: KC8410 | I80: 43314 | J80: Male | K80: 31172 | L80: =DATEDIF(K80,TODAY(),"Y") -> 41 | M80: Congolese | N80: Married | O80: 0 | P80: DRC | Q80: Kinshasa | R80: Permanent | S80: Monthly | T80: Patrick Kahasha | U80: =IFERROR(VLOOKUP(T80,Base!$C$3:$F$177,4,FALSE),"Managing Director") -> Managing Director
A81: 70000137 | B81: PPC Barnet DRC Manufacturing | C81: LISANGOLA ITOFELE L EMMANUEL | D81: Administration | E81: C5 | F81: Warehouse Administrator | G81: Zamba | H81: KM5412 | I81: 43374 | J81: Male | K81: 31303 | L81: =DATEDIF(K81,TODAY(),"Y") -> 40 | M81: Congolese | N81: Married | O81: 0 | P81: DRC | Q81: Zamba | R81: Permanent | S81: Monthly | T81: Jean-Pierre Mavuangala Mvioki | U81: =IFERROR(VLOOKUP(T81,Base!$C$3:$F$177,4,FALSE),"Lead Logistics") -> Lead Logistics
A82: 70000139 | B82: PPC Barnet DRC Manufacturing | C82: MULAMBA KASONGO JUNIOR | D82: Sales & Logistics | E82: C4 | F82: Senior Sales Consultant IHB Segment | G82: Kinshasa | H82: KC6113 | I82: 43360 | J82: Male | K82: 30898 | L82: =DATEDIF(K82,TODAY(),"Y") -> 41 | M82: Congolese | N82: Married | O82: 4 | P82: DRC | Q82: Mbandaka | R82: Permanent | S82: Monthly | T82: Bashige Rurabura Jean-Pierre | U82: =IFERROR(VLOOKUP(T82,Base!$C$3:$F$177,4,FALSE),"Regional Sales Manager") -> Regional Sales Manager
A83: 70000144 | B83: PPC Barnet DRC Manufacturing | C83: TSASA NKONGO PAUL | D83: Sales & Logistics | E83: C5 | F83: Senior Regional Sales Consultant | G83: Kinshasa | H83: KC6111 | I83: 43570 | J83: Male | K83: 32435 | L83: =DATEDIF(K83,TODAY(),"Y") -> 37 | M83: congolese | N83: Married | O83: 2 | P83: DRC | Q83: Kinshasa | R83: Permanent | S83: Monthly | T83: KILOSO SANDA HELENA | U83: =IFERROR(VLOOKUP(T83,Base!$C$3:$F$177,4,FALSE),"Regional Sales Manager") -> Senior Regional Sales Consultant Retail & Funa
A84: 70000152 | B84: PPC Barnet DRC Manufacturing | C84: MALONDA PHUATI FRANCIS | D84: Corporate Admin | E84: C4 | F84: Financial Accountant | G84: Kinshasa | H84: KC8411 | I84: 43647 | J84: Male | K84: 33329 | L84: =DATEDIF(K84,TODAY(),"Y") -> 35 | M84: Congolese | N84: Married | O84: 1 | P84: DRC | Q84: Kinshasa | R84: Permanent | S84: Monthly | T84: Cedric Muzadi | U84: =IFERROR(VLOOKUP(T84,Base!$C$3:$F$177,4,FALSE),"Head of Finance") -> Head of Finance
A85: 70000155 | B85: PPC Barnet DRC Manufacturing | C85: KIAMUENEDIOKO KINSOMONA HORNEL | D85: Human Resources | E85: C2 | F85: Customer Relationship Clerk | G85: Zamba | H85: KM5416 | I85: 43711 | J85: Female | K85: 34084 | L85: =DATEDIF(K85,TODAY(),"Y") -> 33 | M85: Congolese | N85: Married | O85: 2 | P85: DRC | Q85: Zamba | R85: Permanent | S85: Monthly | T85: 0 | U85: =IFERROR(VLOOKUP(T85,Base!$C$3:$F$177,4,FALSE),"Customer Excellence Officer") -> Customer Excellence Officer
A86: 70000157 | B86: PPC Barnet DRC Manufacturing | C86: KAHAMBO ALIMASI NALIK | D86: Sales & Logistics | E86: C2 | F86: Sales Consultant Mont Amba | G86: Kinshasa | H86: KC6111 | I86: 43752 | J86: Male | K86: 32229 | L86: =DATEDIF(K86,TODAY(),"Y") -> 38 | M86: Congolese | N86: Married | O86: 0 | P86: DRC | Q86: Kinshasa | R86: Permanent | S86: Monthly | T86: KADIMA TSHONDO Ben Paulin | U86: =IFERROR(VLOOKUP(T86,Base!$C$3:$F$177,4,FALSE),"Senior Sales Consultant") -> Senior Regional Sales Consultant
A87: 70000159 | B87: PPC Barnet DRC Manufacturing | C87: MAKAYA DIAMATONDO DENIS | D87: Sales & Logistics | E87: C3 | F87: Shipping Coordinator | G87: Kinshasa | H87: KC8812 | I87: 43831 | J87: Male | K87: 27164 | L87: =DATEDIF(K87,TODAY(),"Y") -> 52 | M87: Congolese | N87: Married | O87: 2 | P87: DRC | Q87: Kinshasa | R87: Permanent | S87: Monthly | T87: Jean-Pierre Mavuangala Mvioki | U87: =IFERROR(VLOOKUP(T87,Base!$C$3:$F$177,4,FALSE),"Procurement Manager") -> Procurement Manager
A88: 70000164 | B88: PPC Barnet DRC Manufacturing | C88: MALU MALUNGA SEBASTIEN | D88: Human Resources | E88: C2 | F88: Customer Service Clerk | G88: Zamba | H88: KM5416 | I88: 44046 | J88: Male | K88: 24105 | L88: =DATEDIF(K88,TODAY(),"Y") -> 60 | M88: Congolese | N88: Married | O88: 1 | P88: DRC | Q88: Zamba | R88: Permanent | S88: Monthly | T88: 0 | U88: =IFERROR(VLOOKUP(T88,Base!$C$3:$F$177,4,FALSE),"Customer Relationship Officer") -> Customer Relationship Officer
A89: 70000171 | B89: PPC Barnet DRC Manufacturing | C89: KUABI PANZU CHRISTIAN | D89: Production | E89: C1 | F89: Process Operator | G89: Zamba | H89: KM5110 | I89: 44059 | J89: Male | K89: 32111 | L89: =DATEDIF(K89,TODAY(),"Y") -> 38 | M89: Congolese | N89: Married | O89: 1 | P89: DRC | Q89: Zamba | R89: Permanent | S89: Monthly | T89: Jérémie Muba | U89: =IFERROR(VLOOKUP(T89,Base!$C$3:$F$177,4,FALSE),"Shift Supervisor") -> Shift Supervisor
A90: 70000175 | B90: PPC Barnet DRC Manufacturing | C90: MANEKA MPUDI TRESOR | D90: Corporate Admin | E90: C2 | F90: Immigration Officer | G90: Kinshasa | H90: KC8710 | I90: 44105 | J90: Male | K90: 28866 | L90: =DATEDIF(K90,TODAY(),"Y") -> 47 | M90: Congolese | N90: Married | O90: 4 | P90: DRC | Q90: Kinshasa | R90: Permanent | S90: Monthly | T90: Carine Ewuli | U90: =IFERROR(VLOOKUP(T90,Base!$C$3:$F$177,4,FALSE),"Head of HR") -> Head of HR
A91: 70000176 | B91: PPC Barnet DRC Manufacturing | C91: KILENDA BANGI ALI | D91: Corporate Admin | E91: B2 | F91: Driver | G91: Kinshasa | H91: KC8710 | I91: 44105 | J91: Male | K91: 28062 | L91: =DATEDIF(K91,TODAY(),"Y") -> 49 | M91: Congolese | N91: Married | O91: 6 | P91: DRC | Q91: Kinshasa | R91: Permanent | S91: Monthly | T91: Lisangola Marie Jose | U91: =IFERROR(VLOOKUP(T91,Base!$C$3:$F$177,4,FALSE),"Facilities coordinator and adm (HQ)") -> Facilities coordinator and adm (HQ)
A92: 70000177 | B92: PPC Barnet DRC Manufacturing | C92: ZAKUANI BAHATI BENNY | D92: Corporate Admin | E92: D2 | F92: Talent & Development Manager | G92: Kinshasa | H92: KC8711 | I92: 44105 | J92: Male | K92: 30120 | L92: =DATEDIF(K92,TODAY(),"Y") -> 44 | M92: Congolese | N92: Married | O92: 3 | P92: DRC | Q92: Zamba | R92: Permanent | S92: Monthly | T92: Carine Ewuli | U92: =IFERROR(VLOOKUP(T92,Base!$C$3:$F$177,4,FALSE),"Head of HR") -> Head of HR
A93: 70000178 | B93: PPC Barnet DRC Manufacturing | C93: KABAMBA MUTUNGILAYI GERVAIS | D93: Sales & Logistics | E93: D1 | F93: Marketing Analyst | G93: Kinshasa | H93: KC6210 | I93: 44102 | J93: Male | K93: 31598 | L93: =DATEDIF(K93,TODAY(),"Y") -> 40 | M93: Congolese | N93: Married | O93: 5 | P93: DRC | Q93: Kinshasa | R93: Permanent | S93: Monthly | T93: Papy Muzila | U93: =IFERROR(VLOOKUP(T93,Base!$C$3:$F$177,4,FALSE),"Marketing Manager") -> Marketing Manager
A94: 70000179 | B94: PPC Barnet DRC Manufacturing | C94: BIGANIRO NDAMUSO NELLY | D94: Sales & Logistics | E94: D2 | F94: Purchasing Manager | G94: Kinshasa | H94: KC8813 | I94: 44123 | J94: Female | K94: 31542 | L94: =DATEDIF(K94,TODAY(),"Y") -> 40 | M94: Congolese | N94: Single | O94: 0 | P94: DRC | Q94: Kinshasa | R94: Permanent | S94: Monthly | T94: Patrick Kahasha | U94: =IFERROR(VLOOKUP(T94,Base!$C$3:$F$177,4,FALSE),"Managing Director") -> Managing Director
A95: 70000180 | B95: PPC Barnet DRC Manufacturing | C95: MUTOMBO NTALAJA ACHILLE | D95: Corporate Admin | E95: D5 | F95: Head of legal | G95: Kinshasa | H95: KC9215 | I95: 44120 | J95: Male | K95: 29501 | L95: =DATEDIF(K95,TODAY(),"Y") -> 45 | M95: Congolese | N95: Married | O95: 1 | P95: DRC | Q95: Kinshasa | R95: Permanent | S95: Monthly | T95: Patrick Kahasha | U95: =IFERROR(VLOOKUP(T95,Base!$C$3:$F$177,4,FALSE),"Managing Director") -> Managing Director
A96: 70000184 | B96: PPC Barnet DRC Manufacturing | C96: MBALE KABANGU HUGO | D96: Corporate Admin | E96: D2 | F96: Tax Manager | G96: Kinshasa | H96: KC8413 | I96: 44166 | J96: Male | K96: 31590 | L96: =DATEDIF(K96,TODAY(),"Y") -> 40 | M96: Congolese | N96: Married | O96: 2 | P96: DRC | Q96: Kinshasa | R96: Permanent | S96: Monthly | T96: Cedric Muzadi | U96: =IFERROR(VLOOKUP(T96,Base!$C$3:$F$177,4,FALSE),"Head of Finance") -> Head of Finance
A97: 70000185 | B97: PPC Barnet DRC Manufacturing | C97: MAVUANGALA MVIOKI JEAN-PIERRE | D97: Sales & Logistics | E97: D4 | F97: Logistic Manager | G97: Kinshasa | H97: KC8812 | I97: 44172 | J97: Male | K97: 27867 | L97: =DATEDIF(K97,TODAY(),"Y") -> 50 | M97: Congolese | N97: Married | O97: 3 | P97: DRC | Q97: Kinshasa | R97: Permanent | S97: Monthly | T97: Patrick Kahasha | U97: =IFERROR(VLOOKUP(T97,Base!$C$3:$F$177,4,FALSE),"Managing Director") -> Managing Director
A98: 70000186 | B98: PPC Barnet DRC Manufacturing | C98: BINTU SAFI BARBARA | D98: Sales & Logistics | E98: B4 | F98: TMS Clerk | G98: Kinshasa | H98: KC8811 | I98: 44228 | J98: Female | K98: 32273 | L98: =DATEDIF(K98,TODAY(),"Y") -> 38 | M98: Congolese | N98: Single | O98: 0 | P98: DRC | Q98: Kinshasa | R98: Permanent | S98: Monthly | T98: Jean Pierre Mavuangala | U98: =IFERROR(VLOOKUP(T98,Base!$C$3:$F$177,4,FALSE),"Lead Logistics") -> Lead Logistics
A99: 70000187 | B99: PPC Barnet DRC Manufacturing | C99: KODJAWA MAGA PATRICK | D99: Sales & Logistics | E99: C4 | F99: Ports Coordinator | G99: Kinshasa | H99: KC8811 | I99: 44228 | J99: Male | K99: 31685 | L99: =DATEDIF(K99,TODAY(),"Y") -> 39 | M99: Congolese | N99: Single | O99: 0 | P99: DRC | Q99: Kisangani | R99: Permanent | S99: Monthly | T99: Joseph Marhegero | U99: =IFERROR(VLOOKUP(T99,Base!$C$3:$F$177,4,FALSE),"Transport & Transit Manager") -> Transport & Transit Manager
A100: 70000191 | B100: PPC Barnet DRC Manufacturing | C100: MPAY MAYELE RUFIN | D100: Engineering | E100: C4 | F100: Maintenance Planner | G100: Zamba | H100: KM5310 | I100: 44270 | J100: Male | K100: 31626 | L100: =DATEDIF(K100,TODAY(),"Y") -> 39 | M100: Congolese | N100: Married | O100: 0 | P100: DRC | Q100: Zamba | R100: Permanent | S100: Monthly | T100: Jack Ilondo | U100: =IFERROR(VLOOKUP(T100,Base!$C$3:$F$177,4,FALSE),"Engineering Manager") -> Engineering Manager
...

Sheet EXIT
A1: EXIT — AGENTS SORTIS
A2: MATRICULE | B2: COMPANY | C2: COMPLET NAME | D2: DEPARTMENT | E2: GRADE | F2: JOB TITLE | G2: LOCALISATION | H2: CENTER DES COUTS | I2: Appointment Date | J2: Gender | K2: Date of Birth | L2: Age | M2: Nationality | N2: Marital Status | O2: number of children | P2: Personnal Area | Q2: Employee SubGroup | R2: Payroll Area | S2: Departement | V2: Line Manager Name | W2: Line manager position
A3: 70000273 | B3: PPC Barnet DRC Manufacturing | C3: NDUSHA CLEMENT | D3: Administration | E3: C2 | F3: Process Technician | G3: Zamba | H3: KM5910 | I3: 45446 | J3: Male | K3: 36512 | L3: =DATEDIF(K3,TODAY(),"Y") -> 26 | M3: congolese | N3: Single | O3: 0 | P3: DRC | R3: Contract | S3: Monthly | V3: Parician Ucchi | W3: =IFERROR(VLOOKUP(V3,Base!$C$3:$F$177,4,FALSE),"Optimization Process Engineer") -> Optimization Process Engineer | Y3: Inactive | Z3: CDD | AA3: 26 | AB3: 46237 | AC3: 46217 | AD3: Demission
